Workbook

Sheet OLD
M1: =SUBTOTAL(9,M3:M1048576) -> 9 | N1: =SUBTOTAL(9,N3:N1048576) -> 381411.3 | O1: =SUBTOTAL(9,O3:O1048576) -> 0 | P1: =SUBTOTAL(9,P3:P1048576) -> 381411.3
A2: No | B2: Status | C2: Completion_status | D2: Project type | E2: Customer code | F2: Customer Name | G2: Project Name | H2: PIC | I2: PIC OLD | J2: Market | K2: Stage | L2: Prototype requested | M2: Total SKU | N2: Project total amount (USD) | O2: Shipped amount (USD) | P2: Outstanding amount (USD) | Q2: Payment term | R2: PRE-PAYMENT RECEIVED | S2: BOQ date | T2: PO received | U2: PO date | V2: Prototype requested SD | W2: Prototype confirmed SW | X2: Prototype confirmed SD | Y2: Prototype confirmed SM | Z2: Production requested SD | AA2: Production requested SM | AB2: Production confirmed SW | AC2: Production confirmed SD | AD2: Production confirmed SM | AE2: Shipping information | AF2: Drawing status | AG2: Veneer /wood | AH2: Marble | AI2: Metal | AJ2: Mirror | AK2: Electrical part | AL2: Fabric | AM2: Remark | AN2: Notes | AO2: Forecase Value | AP2: Forecast SM | AQ2: Customer required SW | AR2: SAMPLE SHIPPED DATE
A3: =ROW(A3)-ROW($A$2) -> 1 | B3: Green | C3: IN PROGRESS | D3: NON RH | E3: RFF-CO | F3: COSMIC REALTY PARTNERS LLC | G3: 250 FIFTH AVENUE HOTEL | H3: THƯ | I3: THƯ | J3: US | K3: PRODUCTION | M3: 17 | N3: 54476.23 | O3: 52267.43 | P3: =N3-O3 -> 2208.8 | R3: YES | S3: 45968 | X3: =VLOOKUP(W3,'2026 Calendar'!A:E,4,0) -> #N/A | Y3: =VLOOKUP(W3,'2026 Calendar'!A:B,2,0) -> #N/A | Z3: 46116 | AA3: April | AB3: W14 | AC3: =VLOOKUP(AB3,'2026 Calendar'!A:E,4,0) -> #N/A | AD3: =VLOOKUP(AB3,'2026 Calendar'!A:B,2,0) -> #N/A | AF3: Approved | AG3: Approved | AH3: Approved | AI3: Approved | AJ3: Approved | AK3: Approved | AL3: COM | AM3: Reorder | AQ3: 46062
A4: =ROW(A4)-ROW($A$2) -> 2 | B4: Green | C4: IN PROGRESS | D4: RH | E4: RFF-RH/HS | F4: RESTORATION HARDWARE_HS | G4: BOUTIQUE HOTEL | H4: DŨNG | I4: DŨNG | J4: US | K4: PRODUCTION | L4: NO | M4: 9 | N4: 54061.6 | P4: =N4-O4 -> 54061.6 | Q4: NO REQUIRE | S4: 45955 | T4: YES | U4: 45964 | Y4: =VLOOKUP(W4,'2026 Calendar'!A:B,2,0) -> #N/A | AB4: W15 | AC4: =VLOOKUP(AB4,'2026 Calendar'!A:E,4,0) -> #N/A | AD4: =VLOOKUP(AB4,'2026 Calendar'!A:B,2,0) -> #N/A | AF4: Approved | AG4: Approved | AH4: None | AI4: Approved | AJ4: None | AK4: RSC purchase | AL4: COM | AM4: COM received. Pending MCP for metal (black color) | AN4: COM received. Pending MCP for metal (black color) | AQ4: 46174 | AR4: 46174
A5: =ROW(A5)-ROW($A$2) -> 3 | C5: IN PROGRESS | D5: RH | E5: RFF-RH/HS | F5: RESTORATION HARDWARE_HS | G5: CHICAGO PENDRY | H5: DŨNG | I5: SƯƠNG | J5: US | K5: PRODUCTION | L5: NO | M5: 2 | N5: 135705 | P5: =N5-O5 -> 135705 | S5: 45856 | T5: NO | X5: =VLOOKUP(W5,'2026 Calendar'!A:E,4,0) -> #N/A | Y5: =VLOOKUP(W5,'2026 Calendar'!A:B,2,0) -> #N/A | AC5: =VLOOKUP(AB5,'2026 Calendar'!A:E,4,0) -> #N/A | AD5: =VLOOKUP(AB5,'2026 Calendar'!A:B,2,0) -> #N/A | AF5: Pending approval | AG5: Pending approval | AH5: Pending approval | AI5: Pending approval | AJ5: None | AK5: None | AL5: None | AQ5: N/A
A6: =ROW(A6)-ROW($A$2) -> 4 | C6: IN PROGRESS | D6: RH | E6: RFF-RH/HS | F6: RESTORATION HARDWARE_HS | G6: CIA O&O GUESTROOMS | H6: DŨNG | I6: DŨNG | J6: US | K6: PRODUCTION | M6: 14 | N6: 100196.28 | P6: =N6-O6 -> 100196.28 | Q6: NO REQUIRE | S6: N/A | T6: NO | X6: =VLOOKUP(W6,'2026 Calendar'!A:E,4,0) -> #N/A | Y6: =VLOOKUP(W6,'2026 Calendar'!A:B,2,0) -> #N/A | AC6: =VLOOKUP(AB6,'2026 Calendar'!A:E,4,0) -> #N/A | AD6: =VLOOKUP(AB6,'2026 Calendar'!A:B,2,0) -> #N/A | AQ6: N/A
A7: =ROW(A7)-ROW($A$2) -> 5 | B7: Yellow | C7: IN PROGRESS | D7: RH | E7: RFF-RH/HS | F7: RESTORATION HARDWARE_HS | G7: CIA O&O GUESTROOMS | H7: DŨNG | I7: DŨNG | J7: US | K7: SAMPLE ROOM | L7: YES | M7: 14 | N7: 10991.34 | P7: =N7-O7 -> 10991.34 | Q7: NO REQUIRE | S7: 45981 | T7: YES | U7: 45992 | X7: 46157 | Y7: =VLOOKUP(W7,'2026 Calendar'!A:B,2,0) -> #N/A | AC7: =VLOOKUP(AB7,'2026 Calendar'!A:E,4,0) -> #N/A | AD7: =VLOOKUP(AB7,'2026 Calendar'!A:B,2,0) -> #N/A | AF7: WIP revision | AG7: Pending approval | AH7: Pending approval | AI7: Pending approval | AJ7: Use available | AK7: None | AL7: COM | AM7: Marble: Graphite WIP sourcing | AQ7: 46112 | AR7: 46112
A8: =ROW(A8)-ROW($A$2) -> 6 | B8: Grey | C8: IN PROGRESS | D8: NON RH | E8: RFF-TMSJ | F8: LANG & SCHWANDER LLC | G8: DELAMAR MYSTIC | H8: THƯ | I8: THƯ | J8: US | K8: PRODUCTION FOC | M8: 1 | N8: 16800 | P8: =N8-O8 -> 16800 | Q8: NO REQUIRE | X8: =VLOOKUP(W8,'2026 Calendar'!A:E,4,0) -> #N/A | Y8: =VLOOKUP(W8,'2026 Calendar'!A:B,2,0) -> #N/A | Z8: 46101 | AA8: March | AB8: W12 | AC8: =VLOOKUP(AB8,'2026 Calendar'!A:E,4,0) -> #N/A | AD8: =VLOOKUP(AB8,'2026 Calendar'!A:B,2,0) -> #N/A | AF8: Approved | AG8: Approved | AH8: Approved | AI8: Approved | AJ8: Approved | AK8: Approved | AL8: RSC purchase | AM8: FOC replacements, pending approval of used leather from customer | AQ8: Pending
A9: =ROW(A9)-ROW($A$2) -> 7 | B9: Red | C9: IN PROGRESS | D9: NON RH | E9: RFF-TMSJ | F9: LANG & SCHWANDER LLC | G9: ELYSEE HOTEL | H9: THƯ | I9: SƯƠNG | J9: US | K9: PRODUCTION | M9: 35 | N9: 232948 | P9: =N9-O9 -> 232948 | R9: YES | S9: 46009 | T9: YES | U9: 46009 | X9: =VLOOKUP(W9,'2026 Calendar'!A:E,4,0) -> #N/A | Y9: =VLOOKUP(W9,'2026 Calendar'!A:B,2,0) -> #N/A | Z9: 46188 | AA9: June | AB9: NA | AC9: =VLOOKUP(AB9,'2026 Calendar'!A:E,4,0) -> #N/A | AD9: =VLOOKUP(AB9,'2026 Calendar'!A:B,2,0) -> #N/A | AF9: Pending approval | AG9: Pending approval | AH9: Pending approval | AI9: Pending approval | AJ9: Pending approval | AK9: None | AL9: COM | AM9: pending submission drawing from ME, waiting client to approve color and bed drawing | AQ9: 46128
A10: =ROW(A10)-ROW($A$2) -> 8 | B10: Red | C10: IN PROGRESS | D10: NON RH | E10: RFF-TMSJ | F10: LANG & SCHWANDER LLC | G10: ELYSEE HOTEL | H10: THƯ | I10: SƯƠNG | J10: US | K10: SAMPLE ROOM | M10: 5 | N10: 1936.89 | P10: =N10-O10 -> 1936.89 | R10: YES | S10: 46009 | T10: YES | U10: 46009 | V10: 46122 | X10: =VLOOKUP(W10,'2026 Calendar'!A:E,4,0) -> #N/A | Y10: =VLOOKUP(W10,'2026 Calendar'!A:B,2,0) -> #N/A | AC10: =VLOOKUP(AB10,'2026 Calendar'!A:E,4,0) -> #N/A | AD10: =VLOOKUP(AB10,'2026 Calendar'!A:B,2,0) -> #N/A | AF10: Pending approval | AG10: Pending approval | AH10: Pending approval | AI10: Pending approval | AJ10: Pending approval | AK10: None | AL10: COM | AM10: pending submission drawing from ME, waiting client to approve color and bed drawing | AQ10: 46128
A11: =ROW(A11)-ROW($A$2) -> 9 | C11: IN PROGRESS | D11: NON RH | E11: RFF-TMSJ | F11: LANG & SCHWANDER LLC | G11: FAENA TULLUM (FTMX) | H11: TÚ ANH | I11: TÚ ANH | J11: MX | K11: PRODUCTION | L11: YES | M11: 12 | N11: 949496.23 | P11: =N11-O11 -> 949496.23 | S11: 45798 | T11: NO | X11: =VLOOKUP(W11,'2026 Calendar'!A:E,4,0) -> #N/A | Y11: =VLOOKUP(W11,'2026 Calendar'!A:B,2,0) -> #N/A | AC11: =VLOOKUP(AB11,'2026 Calendar'!A:E,4,0) -> #N/A | AD11: =VLOOKUP(AB11,'2026 Calendar'!A:B,2,0) -> #N/A | AQ11: N/A
A12: =ROW(A12)-ROW($A$2) -> 10 | B12: Red | C12: IN PROGRESS | D12: NON RH | E12: RFF-FLF | F12: FLEETWOOD FURNITURE | G12: FOUR SEASON JACKSONVILLE | H12: TÚ ANH | I12: TÚ ANH | J12: US | K12: PRODUCTION | L12: YES | M12: 37 | N12: 197691.81 | P12: =N12-O12 -> 197691.81 | R12: YES | S12: 45986 | T12: YES | U12: 46053 | X12: =VLOOKUP(W12,'2026 Calendar'!A:E,4,0) -> #N/A | Y12: =VLOOKUP(W12,'2026 Calendar'!A:B,2,0) -> #N/A | Z12: 46121 | AA12: April | AB12: W16 | AC12: 46128 | AD12: April | AE12: Airship and Sea | AF12: Approved | AG12: Approved | AH12: None | AI12: Approved | AJ12: None | AK12: Approved | AL12: None | AN12: Ask customer if have QC inspection. Client request production status update including images | AQ12: 46112 | AR12: 45744
A13: =ROW(A13)-ROW($A$2) -> 11 | B13: Green | C13: IN PROGRESS | D13: RH | E13: RFF-RH/HS | F13: RESTORATION HARDWARE_HS | G13: FOX HARBOR | H13: TUYẾT | I13: TUYẾT | J13: US | K13: PRODUCTION | M13: 12 | N13: 66302.16 | O13: 35918.61 | P13: =N13-O13 -> 30383.55 | Q13: NO REQUIRE | S13: 46000 | X13: =VLOOKUP(W13,'2026 Calendar'!A:E,4,0) -> #N/A | Y13: =VLOOKUP(W13,'2026 Calendar'!A:B,2,0) -> #N/A | AC13: =VLOOKUP(AB13,'2026 Calendar'!A:E,4,0) -> #N/A | AD13: =VLOOKUP(AB13,'2026 Calendar'!A:B,2,0) -> #N/A | AF13: Approved | AG13: Approved | AH13: Approved | AI13: Approved | AJ13: Approved | AK13: Approved | AL13: COM | AM13: COM: 3/3 received, Phase 3 | AQ13: 46116
A14: =ROW(A14)-ROW($A$2) -> 12 | B14: Red | C14: IN PROGRESS | D14: RH | E14: RFF-RH/HS | F14: RESTORATION HARDWARE_HS | G14: GRAND HYATT BAHA MAR | H14: TUYẾT | I14: TUYẾT | J14: US | K14: PRODUCTION | L14: YES | M14: 26 | N14: 2416687.2 | P14: =N14-O14 -> 2416687.2 | Q14: NO REQUIRE | S14: 46011 | T14: YES | X14: =VLOOKUP(W14,'2026 Calendar'!A:E,4,0) -> #N/A | Y14: =VLOOKUP(W14,'2026 Calendar'!A:B,2,0) -> #N/A | AC14: =VLOOKUP(AB14,'2026 Calendar'!A:E,4,0) -> #N/A | AD14: =VLOOKUP(AB14,'2026 Calendar'!A:B,2,0) -> #N/A | AF14: Pending approval | AG14: Approved | AH14: Pending approval | AI14: Approved | AJ14: Approved | AK14: Approved | AL14: COM | AQ14: 46028
A15: =ROW(A15)-ROW($A$2) -> 13 | B15: Red | C15: IN PROGRESS | D15: RH | E15: RFF-RH/HS | F15: RESTORATION HARDWARE_HS | G15: HA Studio Pico/Wilkins | H15: TÚ ANH | I15: TÚ ANH | J15: US | K15: PRODUCTION | L15: NO | M15: 1 | N15: 10770.2 | P15: =N15-O15 -> 10770.2 | Q15: NO REQUIRE | S15: 46037 | T15: YES | U15: 46048 | X15: =VLOOKUP(W15,'2026 Calendar'!A:E,4,0) -> #N/A | Y15: =VLOOKUP(W15,'2026 Calendar'!A:B,2,0) -> #N/A | Z15: 46171 | AA15: May | AB15: W27 | AC15: 46207 | AD15: May | AE15: Sea | AF15: Approved | AG15: Pending approval | AH15: None | AI15: Approved | AJ15: None | AK15: None | AL15: None | AQ15: 46171
A16: =ROW(A16)-ROW($A$2) -> 14 | C16: IN PROGRESS | D16: NON RH | E16: RFF-FLF | F16: FLEETWOOD FURNITURE | G16: HARD ROCK LAS VEGAS WEST TOWER | H16: THẢO | I16: SƯƠNG | J16: US | K16: PRODUCTION | L16: YES | M16: 130 | N16: 4410979.8 | P16: =N16-O16 -> 4410979.8 | S16: 45891 | T16: NO | X16: =VLOOKUP(W16,'2026 Calendar'!A:E,4,0) -> #N/A | Y16: =VLOOKUP(W16,'2026 Calendar'!A:B,2,0) -> #N/A | AC16: =VLOOKUP(AB16,'2026 Calendar'!A:E,4,0) -> #N/A | AD16: =VLOOKUP(AB16,'2026 Calendar'!A:B,2,0) -> #N/A | AF16: RSC WIP | AG16: Approved | AH16: WIP soucing | AI16: Pending approval | AJ16: Pending approval | AK16: COM | AL16: COM | AM16: Metal: pending final confirmation to do PVD/baking. Mirror: pending final color for production, shipped swatches to customer. Still pending one kind of marble. | AQ16: N/A | AR16: 45996
A17: =ROW(A17)-ROW($A$2) -> 15 | B17: Green | C17: IN PROGRESS | D17: NON RH | E17: RFF-FLF | F17: FLEETWOOD FURNITURE | G17: HWVP PHASE 2 | H17: DŨNG | I17: DŨNG | J17: US | K17: PRODUCTION | L17: NO | M17: 5 | N17: 7415 | P17: =N17-O17 -> 7415 | R17: YES | S17: 45327 | T17: YES | U17: 46024 | X17: =VLOOKUP(W17,'2026 Calendar'!A:E,4,0) -> #N/A | Y17: =VLOOKUP(W17,'2026 Calendar'!A:B,2,0) -> #N/A | AC17: =VLOOKUP(AB17,'2026 Calendar'!A:E,4,0) -> #N/A | AD17: April | AF17: Approved | AG17: Approved | AH17: None | AI17: Approved | AJ17: None | AK17: RSC purchase | AL17: COM | AM17: Reorder | AQ17: 46123 | AR17: 46123
A18: =ROW(A18)-ROW($A$2) -> 16 | B18: Green | C18: IN PROGRESS | D18: NON RH | E18: RFF-TPC | F18: THE PARKER COMPANY | G18: JAMES NY NOMAD | H18: THƯ | I18: THƯ | J18: US | K18: PRODUCTION | M18: 1 | N18: 3167.51 | P18: 3167.51 | R18: NO | T18: YES | U18: 46031 | X18: =VLOOKUP(W18,'2026 Calendar'!A:E,4,0) -> #N/A | Y18: =VLOOKUP(W18,'2026 Calendar'!A:B,2,0) -> #N/A | Z18: 46116 | AA18: April | AB18: W14 | AC18: =VLOOKUP(AB18,'2026 Calendar'!A:E,4,0) -> #N/A | AD18: =VLOOKUP(AB18,'2026 Calendar'!A:B,2,0) -> #N/A | AF18: Approved | AG18: Approved | AH18: None | AI18: Approved | AJ18: None | AK18: Approved | AL18: COM | AM18: Reorder | AQ18: 46116
A19: =ROW(A19)-ROW($A$2) -> 17 | B19: Yellow | C19: IN PROGRESS | D19: NON RH | E19: RFF-KD | F19: KD TRAVIS BLOCK HOLDCO, LLC | G19: KNOX DALLAS | H19: TÚ ANH | I19: TÚ ANH | J19: US | K19: PRODUCTION | L19: YES | M19: 30 | N19: =892983.35 -> 892983.35 | O19: =756408.44+33400 -> 789808.44 | P19: =N19-O19 -> 103174.91 | R19: YES | S19: 45762 | T19: YES | U19: 46113 | X19: =VLOOKUP(W19,'2026 Calendar'!A:E,4,0) -> #N/A | Y19: =VLOOKUP(W19,'2026 Calendar'!A:B,2,0) -> #N/A | Z19: 45891 | AA19: August | AB19: W31/2025 | AC19: 45872 | AD19: August | AE19: Sea | AF19: Approved | AG19: Approved | AH19: Approved | AI19: Approved | AJ19: Approved | AK19: Approved | AL19: COM | AM19: Pending COM for specialty suite closet and addtional COM for HB | AQ19: 45993
A20: 35 | B20: Red | C20: IN PROGRESS | D20: NON RH | E20: RFF-KD | F20: KD TRAVIS BLOCK HOLDCO, LLC | G20: KNOX DALLAS SUITE | H20: TÚ ANH | I20: TÚ ANH | J20: US | K20: PRODUCTION | L20: YES | M20: 50 | N20: 369199.72 | P20: =N20-O20 -> 369199.72 | R20: YES | T20: YES | U20: 46053 | X20: =VLOOKUP(W20,'2026 Calendar'!A:E,4,0) -> #N/A | Y20: =VLOOKUP(W20,'2026 Calendar'!A:B,2,0) -> #N/A | Z20: 46157 | AA20: May | AC20: =VLOOKUP(AB20,'2026 Calendar'!A:E,4,0) -> #N/A | AD20: =VLOOKUP(AB20,'2026 Calendar'!A:B,2,0) -> #N/A | AE20: Sea | AF20: Pending approval | AG20: Pending approval | AH20: Approved | AI20: Approved | AJ20: Approved | AK20: RSC purchase | AL20: COM | AN20: NPI proposed SW28/29/30 (Jul) Deposit Must be received by 18 March Fabric COM (Leather) Must be received by 13 April Veneer – Tabu: estimates the air cost to be at ~950 | AQ20: 46157
A21: =ROW(A21)-ROW($A$2) -> 19 | C21: IN PROGRESS | D21: NON RH | E21: RFF-AHMA | F21: AHMADIAH CONTRACTING & TRADING CO.-BRANCH KSA | G21: MARRIOTT KHOBAR | H21: THƯ | I21: THƯ | J21: SA | K21: PRODUCTION | L21: YES | M21: 35 | N21: 1998983 | P21: =N21-O21 -> 1998983 | S21: 45853 | T21: NO | X21: =VLOOKUP(W21,'2026 Calendar'!A:E,4,0) -> #N/A | Y21: =VLOOKUP(W21,'2026 Calendar'!A:B,2,0) -> #N/A | AC21: =VLOOKUP(AB21,'2026 Calendar'!A:E,4,0) -> #N/A | AD21: =VLOOKUP(AB21,'2026 Calendar'!A:B,2,0) -> #N/A | AF21: Approved | AG21: Approved | AH21: Approved | AI21: Approved | AK21: RSC purchase | AL21: RSC purchase | AQ21: 45931 | AR21: 45931
A22: =ROW(A22)-ROW($A$2) -> 20 | B22: Grey | C22: CANCELLED | D22: NON RH | E22: RFF-FLF | F22: FLEETWOOD FURNITURE | G22: MGM ARIA | H22: THƯ | I22: THƯ | J22: US | K22: DROPPED | L22: YES | N22: 6000000 | P22: =N22-O22 -> 6000000 | S22: 46045 | T22: NO | X22: =VLOOKUP(W22,'2026 Calendar'!A:E,4,0) -> #N/A | Y22: =VLOOKUP(W22,'2026 Calendar'!A:B,2,0) -> #N/A | AC22: =VLOOKUP(AB22,'2026 Calendar'!A:E,4,0) -> #N/A | AD22: =VLOOKUP(AB22,'2026 Calendar'!A:B,2,0) -> #N/A | AF22: Approved | AG22: Approved | AH22: WIP soucing | AI22: WIP soucing | AJ22: WIP soucing | AK22: RSC purchase | AL22: COM | AM22: Mock up no finishing | AQ22: 46060 | AR22: 45782
A23: =ROW(A23)-ROW($A$2) -> 21 | B23: Green | C23: COMPLETED | D23: NON RH | E23: RFF-FLF | F23: FLEETWOOD FURNITURE | G23: MGM ARIA | H23: THƯ | I23: THƯ | J23: US | K23: SAMPLE ROOM | L23: YES | M23: 2 | N23: 575.1 | O23: 575.1 | P23: =N23-O23 -> 0 | S23: 46045 | T23: YES | X23: =VLOOKUP(W23,'2026 Calendar'!A:E,4,0) -> #N/A | Y23: =VLOOKUP(W23,'2026 Calendar'!A:B,2,0) -> #N/A | AC23: =VLOOKUP(AB23,'2026 Calendar'!A:E,4,0) -> #N/A | AD23: =VLOOKUP(AB23,'2026 Calendar'!A:B,2,0) -> #N/A | AF23: Approved | AG23: Approved | AH23: WIP soucing | AI23: WIP soucing | AJ23: WIP soucing | AK23: RSC purchase | AL23: COM | AM23: Mock up no finishing | AQ23: 46060 | AR23: 45782
A24: =ROW(A24)-ROW($A$2) -> 22 | C24: IN PROGRESS | D24: NON RH | E24: RFF-MH | F24: MODERN HISTORY | G24: MH HOTEL PROJECT | H24: THƯ | I24: THƯ | J24: US | K24: PRODUCTION | L24: NO | M24: 6 | N24: 48755 | P24: =N24-O24 -> 48755 | S24: 46038 | T24: NO | X24: =VLOOKUP(W24,'2026 Calendar'!A:E,4,0) -> #N/A | Y24: =VLOOKUP(W24,'2026 Calendar'!A:B,2,0) -> #N/A | Z24: 46183 | AA24: June | AB24: NA | AC24: =VLOOKUP(AB24,'2026 Calendar'!A:E,4,0) -> #N/A | AD24: =VLOOKUP(AB24,'2026 Calendar'!A:B,2,0) -> #N/A | AF24: Approved | AG24: Approved | AH24: None | AI24: Approved | AJ24: None | AK24: None | AL24: None | AM24: COSTING STAGE, waiting for Luc confirmation for official PO | AQ24: 46188
A25: =ROW(A25)-ROW($A$2) -> 23 | B25: Yellow | C25: IN PROGRESS | D25: NON RH | E25: RFF-MOHI | F25: HOTEL MOHI C/O ABSOLUTE PROCUREMENT | G25: MOHI APPELLATION | H25: TUYẾT | I25: TUYẾT | J25: US | K25: PRODUCTION | M25: 32 | N25: 406396.56 | P25: =N25-O25 -> 406396.56 | R25: YES | S25: 46009 | X25: =VLOOKUP(W25,'2026 Calendar'!A:E,4,0) -> #N/A | Y25: =VLOOKUP(W25,'2026 Calendar'!A:B,2,0) -> #N/A | AC25: =VLOOKUP(AB25,'2026 Calendar'!A:E,4,0) -> #N/A | AD25: =VLOOKUP(AB25,'2026 Calendar'!A:B,2,0) -> #N/A | AF25: Pending approval | AG25: Approved | AH25: Approved | AI25: Approved | AJ25: Approved | AK25: Approved | AL25: RSC purchase | AM25: 13 drawings wait for client feedback | AQ25: 46142
A26: =ROW(A26)-ROW($A$2) -> 24 | C26: IN PROGRESS | D26: RH | E26: RFF-RH/HS | F26: RESTORATION HARDWARE_HS | G26: NAMA LISBON | H26: THƯ | I26: SƯƠNG | J26: PT | K26: PRODUCTION | L26: NO | M26: 11 | N26: 199073 | P26: =N26-O26 -> 199073 | S26: 46051 | T26: YES | U26: 46083 | X26: =VLOOKUP(W26,'2026 Calendar'!A:E,4,0) -> #N/A | Y26: =VLOOKUP(W26,'2026 Calendar'!A:B,2,0) -> #N/A | Z26: 46170 | AA26: May | AB26: W24 | AC26: =VLOOKUP(AB26,'2026 Calendar'!A:E,4,0) -> #N/A | AD26: =VLOOKUP(AB26,'2026 Calendar'!A:B,2,0) -> #N/A | AF26: Approved | AG26: Use available | AH26: None | AI26: Use available | AJ26: None | AK26: None | AL26: None | AQ26: 46203
A27: 34 | C27: IN PROGRESS | D27: NON RH | E27: TBC | F27: BROOKFILED PROPERTIES | G27: PARK HYATT VANCOUVER | H27: DŨNG | I27: DŨNG | J27: CA | K27: SAMPLE ROOM | L27: YES | M27: 9 | N27: 13096.1 | P27: =N27-O27 -> 13096.1 | R27: NO | S27: 46041 | T27: YES | U27: 46055 | X27: =VLOOKUP(W27,'2026 Calendar'!A:E,4,0) -> #N/A | Y27: =VLOOKUP(W27,'2026 Calendar'!A:B,2,0) -> #N/A | AC27: =VLOOKUP(AB27,'2026 Calendar'!A:E,4,0) -> #N/A | AD27: =VLOOKUP(AB27,'2026 Calendar'!A:B,2,0) -> #N/A | AF27: RSC WIP | AG27: Pending approval | AH27: Pending approval | AI27: WIP soucing | AJ27: WIP soucing | AK27: RSC purchase | AL27: COM | AM27: Awaiting order | AQ27: 46157
A28: =ROW(A28)-ROW($A$2) -> 26 | C28: IN PROGRESS | D28: RH | E28: RFF-RH/HS | F28: RESTORATION HARDWARE_HS | G28: RANCHO VALENCIA | H28: TUYẾT | I28: TUYẾT | J28: US | K28: PRODUCTION | L28: NO | M28: 1 | N28: 14520 | P28: =N28-O28 -> 14520 | S28: 46015 | T28: NO | X28: =VLOOKUP(W28,'2026 Calendar'!A:E,4,0) -> #N/A | Y28: =VLOOKUP(W28,'2026 Calendar'!A:B,2,0) -> #N/A | AC28: =VLOOKUP(AB28,'2026 Calendar'!A:E,4,0) -> #N/A | AD28: =VLOOKUP(AB28,'2026 Calendar'!A:B,2,0) -> #N/A | AF28: Pending approval | AG28: Pending approval | AH28: None | AI28: None | AJ28: None | AK28: None | AL28: RSC purchase | AQ28: N/A
A29: =ROW(A29)-ROW($A$2) -> 27 | C29: IN PROGRESS | D29: RH | E29: RFF-RH/HS | F29: RESTORATION HARDWARE_HS | G29: RH CASSIA CONDO | H29: TUYẾT | I29: TUYẾT | J29: US | K29: PRODUCTION | L29: NO | M29: 50 | N29: 1171637 | P29: =N29-O29 -> 1171637 | S29: 46023 | T29: NO | X29: =VLOOKUP(W29,'2026 Calendar'!A:E,4,0) -> #N/A | Y29: =VLOOKUP(W29,'2026 Calendar'!A:B,2,0) -> #N/A | AC29: =VLOOKUP(AB29,'2026 Calendar'!A:E,4,0) -> #N/A | AD29: =VLOOKUP(AB29,'2026 Calendar'!A:B,2,0) -> #N/A | AF29: Pending approval | AG29: Pending approval | AH29: None | AI29: Pending approval | AJ29: None | AK29: None | AL29: COM | AM29: RCS Cover and 3 types of COM, | AQ29: 46203
A30: =ROW(A30)-ROW($A$2) -> 28 | B30: Green | C30: IN PROGRESS | D30: RH | E30: RFF-RH/HS | F30: RESTORATION HARDWARE_HS | G30: RH contract | H30: THƯ | I30: SƯƠNG | J30: US | K30: PRODUCTION | L30: NO | M30: 1 | N30: 4200 | P30: =N30-O30 -> 4200 | Q30: NO REQUIRE | S30: N/A | T30: YES | U30: 46034 | X30: =VLOOKUP(W30,'2026 Calendar'!A:E,4,0) -> #N/A | Y30: =VLOOKUP(W30,'2026 Calendar'!A:B,2,0) -> #N/A | Z30: 46109 | AA30: March | AB30: W13 | AC30: =VLOOKUP(AB30,'2026 Calendar'!A:E,4,0) -> #N/A | AD30: =VLOOKUP(AB30,'2026 Calendar'!A:B,2,0) -> #N/A | AF30: Approved | AG30: Approved | AH30: None | AI30: None | AJ30: None | AK30: None | AL30: COM | AM30: CONTRACT STOCK | AQ30: 46109
A31: =ROW(A31)-ROW($A$2) -> 29 | C31: IN PROGRESS | D31: RH | E31: RFF-RH/HS | F31: RESTORATION HARDWARE_HS | G31: RH TRUMP SUITES NYC | H31: TUYẾT | I31: TUYẾT | J31: US | K31: PRODUCTION | L31: YES | M31: 51 | N31: 1653853 | P31: =N31-O31 -> 1653853 | S31: N/A | T31: NO | X31: =VLOOKUP(W31,'2026 Calendar'!A:E,4,0) -> #N/A | Y31: =VLOOKUP(W31,'2026 Calendar'!A:B,2,0) -> #N/A | AC31: =VLOOKUP(AB31,'2026 Calendar'!A:E,4,0) -> #N/A | AD31: =VLOOKUP(AB31,'2026 Calendar'!A:B,2,0) -> #N/A | AF31: Approved | AG31: Approved | AH31: Approved | AI31: Approved | AJ31: Approved | AK31: Approved | AL31: COM | AM31: * 21/51 drawings approved and shipped sample, Tuyet working on final BOQ to proceed more drawings for production * 9 types of COM, 12 types of RSC cover * The client is expecting to place the order for this project in June/July 2026. | AQ31: N/A
A32: =ROW(A32)-ROW($A$2) -> 30 | C32: IN PROGRESS | D32: NON RH | E32: RFF-TMSJ | F32: LANG & SCHWANDER | G32: RITZ CARLTON COTTON BAY | H32: NHI | I32: NHI | J32: US | K32: PRODUCTION | L32: YES | M32: 117 | N32: 2589501.9 | P32: =N32-O32 -> 2589501.9 | S32: 45730 | T32: NO | X32: =VLOOKUP(W32,'2026 Calendar'!A:E,4,0) -> #N/A | Y32: =VLOOKUP(W32,'2026 Calendar'!A:B,2,0) -> #N/A | AC32: =VLOOKUP(AB32,'2026 Calendar'!A:E,4,0) -> #N/A | AD32: =VLOOKUP(AB32,'2026 Calendar'!A:B,2,0) -> #N/A | AF32: Approved | AG32: Approved | AH32: Approved | AI32: Approved | AJ32: Approved | AK32: RSC purchase | AL32: COM | AQ32: N/A | AR32: 45861
A33: =ROW(A33)-ROW($A$2) -> 31 | C33: IN PROGRESS | D33: RH | E33: RFF-RH/HS | F33: RESTORATION HARDWARE_HS | G33: ROSEWOOD CALISTOGA | H33: NHI | I33: SƯƠNG | J33: US | K33: PRODUCTION | L33: NO | M33: 33 | N33: 367724.28 | P33: =N33-O33 -> 367724.28 | S33: 46036 | T33: NO | X33: =VLOOKUP(W33,'2026 Calendar'!A:E,4,0) -> #N/A | Y33: =VLOOKUP(W33,'2026 Calendar'!A:B,2,0) -> #N/A | AC33: =VLOOKUP(AB33,'2026 Calendar'!A:E,4,0) -> #N/A | AD33: =VLOOKUP(AB33,'2026 Calendar'!A:B,2,0) -> #N/A | AF33: RSC WIP | AG33: Use available | AH33: Pending approval | AI33: Use available | AJ33: None | AK33: None | AL33: COM | AQ33: N/A
A34: =ROW(A34)-ROW($A$2) -> 32 | C34: IN PROGRESS | D34: RH | E34: RFF-RH/HS | F34: RESTORATION HARDWARE_HS | G34: SNAKE RIVER LODGE BLUEFLAG | H34: TÚ ANH | I34: TÚ ANH | J34: US | K34: PRODUCTION | L34: YES | M34: 9 | N34: 381411.3 | P34: =N34-O34 -> 381411.3 | S34: 45800 | T34: NO | X34: =VLOOKUP(W34,'2026 Calendar'!A:E,4,0) -> #N/A | Y34: =VLOOKUP(W34,'2026 Calendar'!A:B,2,0) -> #N/A | AC34: =VLOOKUP(AB34,'2026 Calendar'!A:E,4,0) -> #N/A | AD34: =VLOOKUP(AB34,'2026 Calendar'!A:B,2,0) -> #N/A | AE34: Sea | AQ34: N/A | AR34: 45929
A35: =ROW(A35)-ROW($A$2) -> 33 | B35: Green | C35: IN PROGRESS | D35: NON RH | E35: RFF-PLUS | F35: PLUS CORPORATION | G35: SOHO HOUSE TOKYO+E25:P35 | H35: THẢO | I35: THẢO | J35: JP | K35: PRODUCTION | M35: 29 | N35: =126270.32+2668 -> 128938.32 | O35: 104926.32 | P35: =N35-O35 -> 24012 | Q35: 50% deposit, 50% prior shipment | R35: YES | S35: 45905 | T35: YES | U35: 46087 | X35: =VLOOKUP(W35,'2026 Calendar'!A:E,4,0) -> #N/A | Y35: =VLOOKUP(W35,'2026 Calendar'!A:B,2,0) -> #N/A | Z35: 46128 | AA35: April | AB35: W18 | AC35: 46141 | AD35: April | AE35: Airship | AF35: Approved | AG35: Approved | AH35: Approved | AI35: Approved | AJ35: Approved | AK35: None | AL35: COM | AQ35: 46128
A36: =ROW(A36)-ROW($A$2) -> 34 | B36: Red | C36: IN PROGRESS | D36: NON RH | E36: RFF-SK | F36: MBMA CORP. D/B/A SPECTRUM KITCHENS | G36: SPECTRUM KITCHENS | H36: THẢO | I36: THẢO | J36: US | K36: PRODUCTION | M36: 20 | N36: 94962.66 | P36: =N36-O36 -> 94962.66 | Q36: 50% deposit, 50% prior shipment | R36: NO | S36: 45961 | T36: YES | U36: 46306 | X36: =VLOOKUP(W36,'2026 Calendar'!A:E,4,0) -> #N/A | Y36: =VLOOKUP(W36,'2026 Calendar'!A:B,2,0) -> #N/A | Z36: 46199 | AA36: June | AC36: =VLOOKUP(#REF!,'2026 Calendar'!A:E,4,0) -> #REF! | AD36: =VLOOKUP(#REF!,'2026 Calendar'!A:B,2,0) -> #REF! | AF36: Pending approval | AG36: Pending approval | AH36: None | AI36: Pending approval | AJ36: None | AK36: None | AL36: None | AM36: BOQ updated 9-Mar. Pending planning cfm SW | AN36: Ship week 29 (7/19/26), approval and deposit deadline is W14. | AQ36: 46199
A37: =ROW(A37)-ROW($A$2) -> 35 | B37: Green | C37: IN PROGRESS | D37: NON RH | E37: RSC-MK | F37: MARKETING | G37: THẢO ĐIỀN OFFICE | H37: THẢO | I37: THẢO | J37: VN | K37: PRODUCTION | M37: 7 | N37: 12312 | O37: 2308.5 | P37: =N37-O37 -> 10003.5 | R37: NO | S37: 46029 | T37: NO | V37: 46164 | X37: =VLOOKUP(W37,'2026 Calendar'!A:E,4,0) -> #N/A | Y37: =VLOOKUP(W37,'2026 Calendar'!A:B,2,0) -> #N/A | AC37: =VLOOKUP(AB37,'2026 Calendar'!A:E,4,0) -> #N/A | AD37: =VLOOKUP(AB37,'2026 Calendar'!A:B,2,0) -> #N/A | AF37: Approved | AG37: Approved | AH37: Approved | AI37: None | AJ37: None | AK37: RSC purchase | AL37: None | AM37: Shipped Batch 1 | AQ37: 46059
A38: =ROW(A38)-ROW($A$2) -> 36 | C38: IN PROGRESS | D38: RH | E38: RFF-RH/HS | F38: RESTORATION HARDWARE_HS | G38: TRUMP LAS VEGAS PENTHOUSES | H38: NHI | I38: NHI | J38: US | K38: PRODUCTION | N38: 731096.8 | P38: =N38-O38 -> 731096.8 | Q38: NO REQUIRE | S38: N/A | T38: NO | X38: =VLOOKUP(W38,'2026 Calendar'!A:E,4,0) -> #N/A | Y38: =VLOOKUP(W38,'2026 Calendar'!A:B,2,0) -> #N/A | AC38: =VLOOKUP(AB38,'2026 Calendar'!A:E,4,0) -> #N/A | AD38: =VLOOKUP(AB38,'2026 Calendar'!A:B,2,0) -> #N/A | AQ38: N/A
A39: =ROW(A39)-ROW($A$2) -> 37 | B39: Green | C39: COMPLETED | D39: RH | E39: RFF-RH/HS | F39: RESTORATION HARDWARE_HS | G39: TRUMP LAS VEGAS PENTHOUSES | H39: NHI | I39: NHI | J39: US | K39: SAMPLE ROOM | L39: YES | M39: 15 | N39: 28773.56 | O39: 28773.56 | P39: =N39-O39 -> 0 | Q39: NO REQUIRE | S39: 45890 | X39: =VLOOKUP(W39,'2026 Calendar'!A:E,4,0) -> #N/A | Y39: =VLOOKUP(W39,'2026 Calendar'!A:B,2,0) -> #N/A | AC39: =VLOOKUP(AB39,'2026 Calendar'!A:E,4,0) -> #N/A | AD39: =VLOOKUP(AB39,'2026 Calendar'!A:B,2,0) -> #N/A | AF39: Approved | AG39: Approved | AH39: Approved | AI39: Approved | AJ39: Approved | AK39: Approved | AL39: COM | AM39: Shipped | AQ39: 46087
A40: =ROW(A40)-ROW($A$2) -> 38 | B40: Grey | C40: CANCELLED | D40: NON RH | E40: RFF-TMSJ | F40: LANG & SCHWANDER LLC | G40: WESTIN HOTEL COCOA BEACH | H40: SƯƠNG | I40: SƯƠNG | J40: US | K40: DROPPED | M40: 1 | N40: 3396.6 | P40: =N40-O40 -> 3396.6 | R40: YES | S40: 45846 | X40: =VLOOKUP(W40,'2026 Calendar'!A:E,4,0) -> #N/A | Y40: =VLOOKUP(W40,'2026 Calendar'!A:B,2,0) -> #N/A | AC40: =VLOOKUP(AB40,'2026 Calendar'!A:E,4,0) -> #N/A | AD40: =VLOOKUP(AB40,'2026 Calendar'!A:B,2,0) -> #N/A | AF40: Approved | AG40: Approved | AH40: None | AI40: None | AJ40: None | AK40: None | AL40: COM | AM40: Sample done. Wait for shipping instruction from customer | AQ40: 45666
A41: =ROW(A41)-ROW($A$2) -> 39 | B41: Red | C41: IN PROGRESS | D41: NON RH | E41: RFF-FLF | F41: FLEETWOOD FURNITURE | G41: W-HOTEL-LAS-VEGAS | H41: NHI | I41: NHI | J41: US | K41: SAMPLE ROOM | L41: YES | M41: 12 | N41: 15271.3 | P41: =N41-O41 -> 15271.3 | R41: YES | S41: 45958 | U41: 46338 | V41: 46343 | X41: =VLOOKUP(W41,'2026 Calendar'!A:E,4,0) -> #N/A | Y41: =VLOOKUP(W41,'2026 Calendar'!A:B,2,0) -> #N/A | AC41: =VLOOKUP(AB41,'2026 Calendar'!A:E,4,0) -> #N/A | AD41: =VLOOKUP(AB41,'2026 Calendar'!A:B,2,0) -> #N/A | AF41: Approved | AG41: Approved | AH41: Approved | AI41: Approved | AJ41: Approved | AK41: RSC purchase | AL41: COM | AM41: STONE TOPS ISSUE | AQ41: 46108
A42: 40 | C42: IN PROGRESS | D42: NON RH | E42: LS | F42: LANG & SCHWANDER | G42: HARD ROCK SAN JUAN | H42: THẢO | I42: THẢO | J42: US | K42: SAMPLE ROOM | L42: YES | M42: 5 | N42: 6614.04 | P42: =N42-O42 -> 6614.04 | Q42: 50% deposit, 50% prior shipment | R42: NO | S42: 46072 | T42: YES | U42: 46070 | V42: 46164 | AF42: RSC WIP | AG42: WIP soucing | AH42: WIP soucing | AI42: Use available | AJ42: WIP soucing | AK42: RSC purchase | AL42: None | AQ42: 46171
A43: 41 | C43: IN PROGRESS | D43: RH | E43: RFF-RH/HS | F43: RESTORATION HARDWARE_HS | G43: Maybourne_One Wall Street NY | H43: TÚ ANH | I43: TÚ ANH | J43: US | K43: PRODUCTION | M43: 1 | N43: 1672 | P43: =N43-O43 -> 1672 | T43: YES | U43: 46079 | Z43: 46120 | AB43: W17 | AC43: 46137 | AD43: April | AE43: Sea | AF43: Approved | AG43: Approved | AH43: None | AI43: None | AJ43: None | AK43: None | AL43: COM
A44: 42 | C44: IN PROGRESS | D44: RH | E44: RFF-RH/HS | F44: RESTORATION HARDWARE_HS | G44: RITZ DOVE MOUNTAIN | H44: TÚ ANH | I44: TÚ ANH | J44: US | K44: PRODUCTION | M44: 14 | N44: 223691.34 | P44: 223691.34 | S44: 46056 | T44: NO | AF44: RSC WIP | AG44: Pending approval | AH44: None | AI44: Pending approval | AJ44: None | AK44: None | AL44: COM
A45: 43 | B45: Red | C45: IN PROGRESS | D45: NON RH | E45: TK | F45: TRIMA KASI LIMITED | G45: JRH | H45: TÚ ANH | I45: TÚ ANH | J45: JM | K45: PRODUCTION | L45: YES | M45: 4 | N45: 1024479.5 | P45: 1024479.5 | Q45: 50% deposit, 50% prior shipment | R45: NO | S45: 46084 | T45: YES | U45: 46090 | V45: 46122 | AF45: RSC WIP | AG45: Pending approval | AH45: None | AI45: Pending approval | AJ45: None | AK45: None | AL45: COM | AN45: Prototype apr, Main run Jul/Aug for now
A46: 44 | C46: IN PROGRESS | D46: RH | E46: RFF-RH/HS | F46: RESTORATION HARDWARE_HS | G46: St Regis Kanai | H46: NHI | J46: US | K46: DEVELOPMENT | M46: 18 | N46: 160909.77 | P46: 160909.77 | S46: 46091 | T46: NO | AF46: RSC WIP | AG46: Pending approval | AH46: Pending approval | AI46: None | AJ46: None | AK46: None | AL46: COM
A47: 45 | C47: IN PROGRESS | D47: NON RH | E47: SK | F47: SPECTRUM KITCHENS | G47: OTMB | H47: DŨNG | I47: DŨNG | J47: US | K47: SAMPLE ROOM | L47: YES | M47: 4 | N47: 3273.84 | Q47: 50% deposit, 50% prior shipment | R47: NO | S47: 46093 | T47: NO | V47: 46142 | AF47: RSC WIP | AG47: WIP soucing | AH47: None | AI47: WIP soucing | AJ47: WIP soucing | AL47: None
G48: Trump NYC

Sheet Detail_New
A1: FORMULA | B1: DROP LIST | C1: MANUAL INPUT | H1: [YEAR]_[CUST NAME]_[PROJ-NAME]
A2: PROJECT TYPE | B2: STAGE | C2: PIC | D2: CUSTOMER PIC | E2: CUSTOMER NAME | F2: CUSTOMER SHORTEN NAME | G2: PROJECT NAME (SHORT) | H2: PROJECT NAME | I2: COUNT | J2: STATUS | K2: POOL | L2: NPD/NPI STAGE | M2: BOQ DATE | N2: PO RECEIVED DATE | O2: DEPOSIT RECEIVED DATE | P2: MARKET | Q2: MARKET STATE (US ONLY) | R2: BE SKU | S2: BE QTY | T2: CG QTY | U2: UPH QTY | V2: PROJECT SKU | W2: PROJECT QTY | X2: PROJECT VALUE $ | Y2: PROJECT BREAK VALUE | Z2: SHIP MONTH FC | AA2: SHIP YEAR | AB2: REQUESTED FIRST SD | AC2: REQUESTED LAST SD | AD2: CONFIRMED FIRST SD | AE2: CONFIRMED LAST SD | AF2: CONFIRMED FIRST SW | AG2: CONFIRMED LAST SW | AH2: DRAWING STATUS | AI2: DRAWING PLAN/DUE DATE | AJ2: DRAWING APPROVED DATE | AK2: VENEER/WOOD STATUS | AL2: VENEER/WOOD PLAN/DUE DATE | AM2: VENEER/WOOD APPROVED DATE | AN2: MARBLE STATUS | AO2: MARBLE PLAN/DUE DATE | AP2: MARBLE APPROVED DATE | AQ2: METAL STATUS | AR2: METAL PLAN/DUE DATE | AS2: METAL APPROVED DATE | AT2: MIRROR STATUS | AU2: MIRROR PLAN/DUE DATE | AV2: MIRROR APPROVED DATE | AW2: ELECTRICAL STATUS | AX2: ELECTRICAL PLAN/DUE DATE | AY2: ELECTRICAL APPROVED DATE | AZ2: FABRIC STATUS | BA2: FABRIC PLAN/DUE DATE | BB2: FABRIC DUE DATE | BC2: LIFECYCLE | BD2: CPSC + TSCA | BE2: DEVELOPMENT STATUS | BF2: Remarks
A3: =IFERROR(VLOOKUP(E3,'Customer '!$A$4:$D$23,3,FALSE),"") -> RH | B3: NPI | C3: TRINH | D3: Sue Bilstad | E3: RESTORATION HARDWARE_HS | F3: =IFERROR(VLOOKUP(E3,'Customer '!$A$4:$D$28,2,FALSE),"") -> RH | G3: GRAND HYATT BAHA MAR | H3: =IF(OR(DetailTracker[[#This Row],[PROJECT NAME (SHORT)]]="",DetailTracker[[#This Row],[CUSTOMER SHORTEN NAME]]=""),"",IF(ISNUMBER(DetailTracker[[#This Row],[BOQ DATE]]),YEAR(DetailTracker[[#This Row],[BOQ DATE]])&"-"&DetailTracker[[#This Row],[CUSTOMER SHORTEN NAME]]&"-"&DetailTracker[[#This Row],[PROJECT NAME (SHORT)]],IF(OR(DetailTracker[[#This Row],[SHIP MONTH FC]]="TBC",DetailTracker[[#This Row],[SHIP MONTH FC]]="Removed"),DetailTracker[[#This Row],[SHIP MONTH FC]]&"-"&DetailTracker[[#This Row],[CUSTOMER SHORTEN NAME]]&"-"&DetailTracker[[#This Row],[PROJECT NAME (SHORT)]],YEAR(TODAY())&"-"&DetailTracker[[#This Row],[CUSTOMER SHORTEN NAME]]&"-"&DetailTracker[[#This Row],[PROJECT NAME (SHORT)]]))) -> 2026-RH-GRAND HYATT BAHA MAR | I3: =IF(OR($H3="",$B3=""),0,--(COUNTIFS($H$3:$H3,$H3,$B$3:$B3,$B3)=1)) -> 1 | J3: SHIPPED | K3: NEW | L3: 8. Shipment | M3: 46033 | N3: 46098 | P3: BS | Q3: Bahamas | V3: 26 | X3: 2454228 | Y3: 153379 | Z3: 2026/M05 | AA3: =IF(Z3="","",IF(OR(Z3="TBC",Z3="Removed"),Z3,LEFT(Z3,4))) -> 2026 | AB3: 46167 | AC3: 46201 | AD3: 46173 | AE3: 46257 | AF3: =IF(AD3="","",IF(ISNUMBER(AD3),IF(AND(AD3>='2026 Calendar'!$C$4,AD3<='2026 Calendar'!$E$107),LOOKUP(AD3,'2026 Calendar'!$C$4:$C$107,'2026 Calendar'!$A$4:$A$107),YEAR(AD3-WEEKDAY(AD3,2)+4)&"/W"&TEXT(WEEKNUM(AD3,21),"00")),IF(IFERROR(ISNUMBER(SEARCH("/W",AD3)),FALSE),IF(IFERROR(ISNUMBER(SEARCH("-",AD3)),FALSE),LEFT(AD3,SEARCH("-",AD3)-1),AD3),AD3))) -> 2026/W22 | AG3: =IF(AE3="","",IF(ISNUMBER(AE3),IF(AND(AE3>='2026 Calendar'!$C$4,AE3<='2026 Calendar'!$E$107),LOOKUP(AE3,'2026 Calendar'!$C$4:$C$107,'2026 Calendar'!$A$4:$A$107),YEAR(AE3-WEEKDAY(AE3,2)+4)&"/W"&TEXT(WEEKNUM(AE3,21),"00")),IF(IFERROR(ISNUMBER(SEARCH("/W",AE3)),FALSE),IF(IFERROR(ISNUMBER(SEARCH("-",AE3)),FALSE),MID(AE3,SEARCH("-",AE3)+1,100),AE3),AE3))) -> 2026/W34 | AH3: Approved | AK3: Approved | AN3: Approved | AQ3: Approved | AT3: N/A | AW3: Approved | AZ3: COM Received | BC3: =IF(J3="","",IF(OR(J3="OB",J3="NOR",J3="FC",J3="PIPELINE"),"Active","Complete")) -> Complete | BD3: Yes | BE3: =IF(UPPER(TRIM(J3))="SHIPPED","READY",_xlfn.LET(_xlpm.stage,IF(B3="","",B3&": "),_xlpm.ip,_xlfn.TEXTJOIN(", ",TRUE,IF(LOWER(AH3)="in progress","Drawing",""),IF(LOWER(AK3)="in progress","Veneer/Wood",""),IF(LOWER(AN3)="in progress","Marble",""),IF(LOWER(AQ3)="in progress","Metal",""),IF(LOWER(AT3)="in progress","Mirror",""),IF(LOWER(AW3)="in progress","Electrical",""),IF(LOWER(AZ3)="in progress","Fabric","")),_xlpm.pa,_xlfn.TEXTJOIN(", ",TRUE,IF(LOWER(AH3)="pending approval","Drawing",""),IF(LOWER(AK3)="pending approval","Veneer/Wood",""),IF(LOWER(AN3)="pending approval","Marble",""),IF(LOWER(AQ3)="pending approval","Metal",""),IF(LOWER(AT3)="pending approval","Mirror",""),IF(LOWER(AW3)="pending approval","Electrical",""),IF(LOWER(AZ3)="pending approval","Fabric","")),_xlpm.ns,_xlfn.TEXTJOIN(", ",TRUE,IF(LOWER(AH3)="not started","Drawing",""),IF(LOWER(AK3)="not started","Veneer/Wood",""),IF(LOWER(AN3)="not started","Marble",""),IF(LOWER(AQ3)="not started","Metal",""),IF(LOWER(AT3)="not started","Mirror",""),IF(LOWER(AW3)="not started","Electrical",""),IF(LOWER(AZ3)="not started","Fabric","")),_xlpm.fab,IF(OR(LOWER(AZ3)="com",LOWER(AZ3)="com pending",LOWER(AZ3)="com received"),"Fabric is "&LOWER(AZ3),""),_xlpm.parts,_xlfn.TEXTJOIN("; ",TRUE,IF(_xlpm.ip<>"","In progress: "&_xlpm.ip,""),IF(_xlpm.pa<>"","Pending approval: "&_xlpm.pa,""),IF(_xlpm.ns<>"","Not started: "&_xlpm.ns,""),_xlpm.fab),_xlpm.deadline,MIN(IF(AND(AH3<>"",LOWER(AH3)<>"approved",LOWER(AH3)<>"n/a",ISNUMBER(AI3)),AI3,1E+99),IF(AND(AK3<>"",LOWER(AK3)<>"approved",LOWER(AK3)<>"n/a",ISNUMBER(AL3)),AL3,1E+99),IF(AND(AN3<>"",LOWER(AN3)<>"approved",LOWER(AN3)<>"n/a",ISNUMBER(AO3)),AO3,1E+99),IF(AND(AQ3<>"",LOWER(AQ3)<>"approved",LOWER(AQ3)<>"n/a",ISNUMBER(AR3)),AR3,1E+99),IF(AND(AT3<>"",LOWER(AT3)<>"approved",LOWER(AT3)<>"n/a",ISNUMBER(AU3)),AU3,1E+99),IF(AND(AW3<>"",LOWER(AW3)<>"approved",LOWER(AW3)<>"n/a",ISNUMBER(AX3)),AX3,1E+99),IF(AND(AZ3<>"",LOWER(AZ3)<>"approved",LOWER(AZ3)<>"n/a",ISNUMBER(BA3)),BA3,1E+99)),_xlpm.sw,IF(AG3="","",IFERROR("SW"&MID(AG3,FIND("/W",AG3)+2,99),"SW "&AG3)),_xlpm.stage&IF(_xlpm.parts="","All development items approved/closed",_xlpm.parts)&IF(AND(_xlpm.parts<>"",_xlpm.deadline<1E+99),"; need approval by "&TEXT(_xlpm.deadline,"d-mmm-yy"),"")&IF(_xlpm.sw<>""," for "&_xlpm.sw,""))) -> READY
A4: =IFERROR(VLOOKUP(E4,'Customer '!$A$4:$D$23,3,FALSE),"") -> RH | B4: NPI | C4: TRINH | D4: Sue Bilstad | E4: RESTORATION HARDWARE_HS | F4: =IFERROR(VLOOKUP(E4,'Customer '!$A$4:$D$28,2,FALSE),"") -> RH | G4: GRAND HYATT BAHA MAR | H4: =IF(OR(DetailTracker[[#This Row],[PROJECT NAME (SHORT)]]="",DetailTracker[[#This Row],[CUSTOMER SHORTEN NAME]]=""),"",IF(ISNUMBER(DetailTracker[[#This Row],[BOQ DATE]]),YEAR(DetailTracker[[#This Row],[BOQ DATE]])&"-"&DetailTracker[[#This Row],[CUSTOMER SHORTEN NAME]]&"-"&DetailTracker[[#This Row],[PROJECT NAME (SHORT)]],IF(OR(DetailTracker[[#This Row],[SHIP MONTH FC]]="TBC",DetailTracker[[#This Row],[SHIP MONTH FC]]="Removed"),DetailTracker[[#This Row],[SHIP MONTH FC]]&"-"&DetailTracker[[#This Row],[CUSTOMER SHORTEN NAME]]&"-"&DetailTracker[[#This Row],[PROJECT NAME (SHORT)]],YEAR(TODAY())&"-"&DetailTracker[[#This Row],[CUSTOMER SHORTEN NAME]]&"-"&DetailTracker[[#This Row],[PROJECT NAME (SHORT)]]))) -> 2026-RH-GRAND HYATT BAHA MAR | I4: =IF(OR($H4="",$B4=""),0,--(COUNTIFS($H$3:$H4,$H4,$B$3:$B4,$B4)=1)) -> 1 | J4: SHIPPED | K4: NEW | L4: 8. Shipment | M4: 46033 | N4: 46098 | P4: BS | Q4: Bahamas | V4: 26 | X4: 2454228 | Y4: 1004676 | Z4: 2026/M06 | AA4: =IF(Z4="","",IF(OR(Z4="TBC",Z4="Removed"),Z4,LEFT(Z4,4))) -> 2026 | AB4: 46167 | AC4: 46201 | AD4: 46173 | AE4: 46257 | AF4: =IF(AD4="","",IF(ISNUMBER(AD4),IF(AND(AD4>='2026 Calendar'!$C$4,AD4<='2026 Calendar'!$E$107),LOOKUP(AD4,'2026 Calendar'!$C$4:$C$107,'2026 Calendar'!$A$4:$A$107),YEAR(AD4-WEEKDAY(AD4,2)+4)&"/W"&TEXT(WEEKNUM(AD4,21),"00")),IF(IFERROR(ISNUMBER(SEARCH("/W",AD4)),FALSE),IF(IFERROR(ISNUMBER(SEARCH("-",AD4)),FALSE),LEFT(AD4,SEARCH("-",AD4)-1),AD4),AD4))) -> 2026/W22 | AG4: =IF(AE4="","",IF(ISNUMBER(AE4),IF(AND(AE4>='2026 Calendar'!$C$4,AE4<='2026 Calendar'!$E$107),LOOKUP(AE4,'2026 Calendar'!$C$4:$C$107,'2026 Calendar'!$A$4:$A$107),YEAR(AE4-WEEKDAY(AE4,2)+4)&"/W"&TEXT(WEEKNUM(AE4,21),"00")),IF(IFERROR(ISNUMBER(SEARCH("/W",AE4)),FALSE),IF(IFERROR(ISNUMBER(SEARCH("-",AE4)),FALSE),MID(AE4,SEARCH("-",AE4)+1,100),AE4),AE4))) -> 2026/W34 | AH4: Approved | AK4: Approved | AN4: Approved | AQ4: Approved | AT4: N/A | AW4: Approved | AZ4: COM Received | BC4: =IF(J4="","",IF(OR(J4="OB",J4="NOR",J4="FC",J4="PIPELINE"),"Active","Complete")) -> Complete | BD4: Yes | BE4: =IF(UPPER(TRIM(J4))="SHIPPED","READY",_xlfn.LET(_xlpm.stage,IF(B4="","",B4&": "),_xlpm.ip,_xlfn.TEXTJOIN(", ",TRUE,IF(LOWER(AH4)="in progress","Drawing",""),IF(LOWER(AK4)="in progress","Veneer/Wood",""),IF(LOWER(AN4)="in progress","Marble",""),IF(LOWER(AQ4)="in progress","Metal",""),IF(LOWER(AT4)="in progress","Mirror",""),IF(LOWER(AW4)="in progress","Electrical",""),IF(LOWER(AZ4)="in progress","Fabric","")),_xlpm.pa,_xlfn.TEXTJOIN(", ",TRUE,IF(LOWER(AH4)="pending approval","Drawing",""),IF(LOWER(AK4)="pending approval","Veneer/Wood",""),IF(LOWER(AN4)="pending approval","Marble",""),IF(LOWER(AQ4)="pending approval","Metal",""),IF(LOWER(AT4)="pending approval","Mirror",""),IF(LOWER(AW4)="pending approval","Electrical",""),IF(LOWER(AZ4)="pending approval","Fabric","")),_xlpm.ns,_xlfn.TEXTJOIN(", ",TRUE,IF(LOWER(AH4)="not started","Drawing",""),IF(LOWER(AK4)="not started","Veneer/Wood",""),IF(LOWER(AN4)="not started","Marble",""),IF(LOWER(AQ4)="not started","Metal",""),IF(LOWER(AT4)="not started","Mirror",""),IF(LOWER(AW4)="not started","Electrical",""),IF(LOWER(AZ4)="not started","Fabric","")),_xlpm.fab,IF(OR(LOWER(AZ4)="com",LOWER(AZ4)="com pending",LOWER(AZ4)="com received"),"Fabric is "&LOWER(AZ4),""),_xlpm.parts,_xlfn.TEXTJOIN("; ",TRUE,IF(_xlpm.ip<>"","In progress: "&_xlpm.ip,""),IF(_xlpm.pa<>"","Pending approval: "&_xlpm.pa,""),IF(_xlpm.ns<>"","Not started: "&_xlpm.ns,""),_xlpm.fab),_xlpm.deadline,MIN(IF(AND(AH4<>"",LOWER(AH4)<>"approved",LOWER(AH4)<>"n/a",ISNUMBER(AI4)),AI4,1E+99),IF(AND(AK4<>"",LOWER(AK4)<>"approved",LOWER(AK4)<>"n/a",ISNUMBER(AL4)),AL4,1E+99),IF(AND(AN4<>"",LOWER(AN4)<>"approved",LOWER(AN4)<>"n/a",ISNUMBER(AO4)),AO4,1E+99),IF(AND(AQ4<>"",LOWER(AQ4)<>"approved",LOWER(AQ4)<>"n/a",ISNUMBER(AR4)),AR4,1E+99),IF(AND(AT4<>"",LOWER(AT4)<>"approved",LOWER(AT4)<>"n/a",ISNUMBER(AU4)),AU4,1E+99),IF(AND(AW4<>"",LOWER(AW4)<>"approved",LOWER(AW4)<>"n/a",ISNUMBER(AX4)),AX4,1E+99),IF(AND(AZ4<>"",LOWER(AZ4)<>"approved",LOWER(AZ4)<>"n/a",ISNUMBER(BA4)),BA4,1E+99)),_xlpm.sw,IF(AG4="","",IFERROR("SW"&MID(AG4,FIND("/W",AG4)+2,99),"SW "&AG4)),_xlpm.stage&IF(_xlpm.parts="","All development items approved/closed",_xlpm.parts)&IF(AND(_xlpm.parts<>"",_xlpm.deadline<1E+99),"; need approval by "&TEXT(_xlpm.deadline,"d-mmm-yy"),"")&IF(_xlpm.sw<>""," for "&_xlpm.sw,""))) -> READY
A5: =IFERROR(VLOOKUP(E5,'Customer '!$A$4:$D$23,3,FALSE),"") -> RH | B5: NPI | C5: TRINH | D5: Sue Bilstad | E5: RESTORATION HARDWARE_HS | F5: =IFERROR(VLOOKUP(E5,'Customer '!$A$4:$D$28,2,FALSE),"") -> RH | G5: GRAND HYATT BAHA MAR | H5: =IF(OR(DetailTracker[[#This Row],[PROJECT NAME (SHORT)]]="",DetailTracker[[#This Row],[CUSTOMER SHORTEN NAME]]=""),"",IF(ISNUMBER(DetailTracker[[#This Row],[BOQ DATE]]),YEAR(DetailTracker[[#This Row],[BOQ DATE]])&"-"&DetailTracker[[#This Row],[CUSTOMER SHORTEN NAME]]&"-"&DetailTracker[[#This Row],[PROJECT NAME (SHORT)]],IF(OR(DetailTracker[[#This Row],[SHIP MONTH FC]]="TBC",DetailTracker[[#This Row],[SHIP MONTH FC]]="Removed"),DetailTracker[[#This Row],[SHIP MONTH FC]]&"-"&DetailTracker[[#This Row],[CUSTOMER SHORTEN NAME]]&"-"&DetailTracker[[#This Row],[PROJECT NAME (SHORT)]],YEAR(TODAY())&"-"&DetailTracker[[#This Row],[CUSTOMER SHORTEN NAME]]&"-"&DetailTracker[[#This Row],[PROJECT NAME (SHORT)]]))) -> 2026-RH-GRAND HYATT BAHA MAR | I5: =IF(OR($H5="",$B5=""),0,--(COUNTIFS($H$3:$H5,$H5,$B$3:$B5,$B5)=1)) -> 0 | J5: SHIPPED | K5: NEW | L5: 8. Shipment | M5: 46033 | N5: 46098 | P5: BS | Q5: Bahamas | V5: 26 | X5: 2454228 | Y5: 969712.83 | Z5: 2026/M07 | AA5: =IF(Z5="","",IF(OR(Z5="TBC",Z5="Removed"),Z5,LEFT(Z5,4))) -> 2026 | AB5: 46167 | AC5: 46201 | AD5: 46173 | AE5: 46257 | AF5: =IF(AD5="","",IF(ISNUMBER(AD5),IF(AND(AD5>='2026 Calendar'!$C$4,AD5<='2026 Calendar'!$E$107),LOOKUP(AD5,'2026 Calendar'!$C$4:$C$107,'2026 Calendar'!$A$4:$A$107),YEAR(AD5-WEEKDAY(AD5,2)+4)&"/W"&TEXT(WEEKNUM(AD5,21),"00")),IF(IFERROR(ISNUMBER(SEARCH("/W",AD5)),FALSE),IF(IFERROR(ISNUMBER(SEARCH("-",AD5)),FALSE),LEFT(AD5,SEARCH("-",AD5)-1),AD5),AD5))) -> 2026/W22 | AG5: =IF(AE5="","",IF(ISNUMBER(AE5),IF(AND(AE5>='2026 Calendar'!$C$4,AE5<='2026 Calendar'!$E$107),LOOKUP(AE5,'2026 Calendar'!$C$4:$C$107,'2026 Calendar'!$A$4:$A$107),YEAR(AE5-WEEKDAY(AE5,2)+4)&"/W"&TEXT(WEEKNUM(AE5,21),"00")),IF(IFERROR(ISNUMBER(SEARCH("/W",AE5)),FALSE),IF(IFERROR(ISNUMBER(SEARCH("-",AE5)),FALSE),MID(AE5,SEARCH("-",AE5)+1,100),AE5),AE5))) -> 2026/W34 | AH5: Approved | AK5: Approved | AN5: Approved | AQ5: Approved | AT5: N/A | AW5: Approved | AZ5: COM Received | BC5: =IF(J5="","",IF(OR(J5="OB",J5="NOR",J5="FC",J5="PIPELINE"),"Active","Complete")) -> Complete | BD5: Yes | BE5: =IF(UPPER(TRIM(J5))="SHIPPED","READY",_xlfn.LET(_xlpm.stage,IF(B5="","",B5&": "),_xlpm.ip,_xlfn.TEXTJOIN(", ",TRUE,IF(LOWER(AH5)="in progress","Drawing",""),IF(LOWER(AK5)="in progress","Veneer/Wood",""),IF(LOWER(AN5)="in progress","Marble",""),IF(LOWER(AQ5)="in progress","Metal",""),IF(LOWER(AT5)="in progress","Mirror",""),IF(LOWER(AW5)="in progress","Electrical",""),IF(LOWER(AZ5)="in progress","Fabric","")),_xlpm.pa,_xlfn.TEXTJOIN(", ",TRUE,IF(LOWER(AH5)="pending approval","Drawing",""),IF(LOWER(AK5)="pending approval","Veneer/Wood",""),IF(LOWER(AN5)="pending approval","Marble",""),IF(LOWER(AQ5)="pending approval","Metal",""),IF(LOWER(AT5)="pending approval","Mirror",""),IF(LOWER(AW5)="pending approval","Electrical",""),IF(LOWER(AZ5)="pending approval","Fabric","")),_xlpm.ns,_xlfn.TEXTJOIN(", ",TRUE,IF(LOWER(AH5)="not started","Drawing",""),IF(LOWER(AK5)="not started","Veneer/Wood",""),IF(LOWER(AN5)="not started","Marble",""),IF(LOWER(AQ5)="not started","Metal",""),IF(LOWER(AT5)="not started","Mirror",""),IF(LOWER(AW5)="not started","Electrical",""),IF(LOWER(AZ5)="not started","Fabric","")),_xlpm.fab,IF(OR(LOWER(AZ5)="com",LOWER(AZ5)="com pending",LOWER(AZ5)="com received"),"Fabric is "&LOWER(AZ5),""),_xlpm.parts,_xlfn.TEXTJOIN("; ",TRUE,IF(_xlpm.ip<>"","In progress: "&_xlpm.ip,""),IF(_xlpm.pa<>"","Pending approval: "&_xlpm.pa,""),IF(_xlpm.ns<>"","Not started: "&_xlpm.ns,""),_xlpm.fab),_xlpm.deadline,MIN(IF(AND(AH5<>"",LOWER(AH5)<>"approved",LOWER(AH5)<>"n/a",ISNUMBER(AI5)),AI5,1E+99),IF(AND(AK5<>"",LOWER(AK5)<>"approved",LOWER(AK5)<>"n/a",ISNUMBER(AL5)),AL5,1E+99),IF(AND(AN5<>"",LOWER(AN5)<>"approved",LOWER(AN5)<>"n/a",ISNUMBER(AO5)),AO5,1E+99),IF(AND(AQ5<>"",LOWER(AQ5)<>"approved",LOWER(AQ5)<>"n/a",ISNUMBER(AR5)),AR5,1E+99),IF(AND(AT5<>"",LOWER(AT5)<>"approved",LOWER(AT5)<>"n/a",ISNUMBER(AU5)),AU5,1E+99),IF(AND(AW5<>"",LOWER(AW5)<>"approved",LOWER(AW5)<>"n/a",ISNUMBER(AX5)),AX5,1E+99),IF(AND(AZ5<>"",LOWER(AZ5)<>"approved",LOWER(AZ5)<>"n/a",ISNUMBER(BA5)),BA5,1E+99)),_xlpm.sw,IF(AG5="","",IFERROR("SW"&MID(AG5,FIND("/W",AG5)+2,99),"SW "&AG5)),_xlpm.stage&IF(_xlpm.parts="","All development items approved/closed",_xlpm.parts)&IF(AND(_xlpm.parts<>"",_xlpm.deadline<1E+99),"; need approval by "&TEXT(_xlpm.deadline,"d-mmm-yy"),"")&IF(_xlpm.sw<>""," for "&_xlpm.sw,""))) -> READY
A6: =IFERROR(VLOOKUP(E6,'Customer '!$A$4:$D$23,3,FALSE),"") -> RH | B6: NPI | C6: TRINH | D6: Sue Bilstad | E6: RESTORATION HARDWARE_HS | F6: =IFERROR(VLOOKUP(E6,'Customer '!$A$4:$D$28,2,FALSE),"") -> RH | G6: GRAND HYATT BAHA MAR | H6: =IF(OR(DetailTracker[[#This Row],[PROJECT NAME (SHORT)]]="",DetailTracker[[#This Row],[CUSTOMER SHORTEN NAME]]=""),"",IF(ISNUMBER(DetailTracker[[#This Row],[BOQ DATE]]),YEAR(DetailTracker[[#This Row],[BOQ DATE]])&"-"&DetailTracker[[#This Row],[CUSTOMER SHORTEN NAME]]&"-"&DetailTracker[[#This Row],[PROJECT NAME (SHORT)]],IF(OR(DetailTracker[[#This Row],[SHIP MONTH FC]]="TBC",DetailTracker[[#This Row],[SHIP MONTH FC]]="Removed"),DetailTracker[[#This Row],[SHIP MONTH FC]]&"-"&DetailTracker[[#This Row],[CUSTOMER SHORTEN NAME]]&"-"&DetailTracker[[#This Row],[PROJECT NAME (SHORT)]],YEAR(TODAY())&"-"&DetailTracker[[#This Row],[CUSTOMER SHORTEN NAME]]&"-"&DetailTracker[[#This Row],[PROJECT NAME (SHORT)]]))) -> 2026-RH-GRAND HYATT BAHA MAR | I6: =IF(OR($H6="",$B6=""),0,--(COUNTIFS($H$3:$H6,$H6,$B$3:$B6,$B6)=1)) -> 0 | J6: SHIPPED | K6: NEW | L6: 8. Shipment | M6: 46033 | N6: 46098 | P6: BS | Q6: Bahamas | V6: 26 | X6: 2454228 | Y6: 308393 | Z6: 2026/M08 | AA6: =IF(Z6="","",IF(OR(Z6="TBC",Z6="Removed"),Z6,LEFT(Z6,4))) -> 2026 | AB6: 46167 | AC6: 46201 | AD6: 46173 | AE6: 46257 | AF6: =IF(AD6="","",IF(ISNUMBER(AD6),IF(AND(AD6>='2026 Calendar'!$C$4,AD6<='2026 Calendar'!$E$107),LOOKUP(AD6,'2026 Calendar'!$C$4:$C$107,'2026 Calendar'!$A$4:$A$107),YEAR(AD6-WEEKDAY(AD6,2)+4)&"/W"&TEXT(WEEKNUM(AD6,21),"00")),IF(IFERROR(ISNUMBER(SEARCH("/W",AD6)),FALSE),IF(IFERROR(ISNUMBER(SEARCH("-",AD6)),FALSE),LEFT(AD6,SEARCH("-",AD6)-1),AD6),AD6))) -> 2026/W22 | AG6: =IF(AE6="","",IF(ISNUMBER(AE6),IF(AND(AE6>='2026 Calendar'!$C$4,AE6<='2026 Calendar'!$E$107),LOOKUP(AE6,'2026 Calendar'!$C$4:$C$107,'2026 Calendar'!$A$4:$A$107),YEAR(AE6-WEEKDAY(AE6,2)+4)&"/W"&TEXT(WEEKNUM(AE6,21),"00")),IF(IFERROR(ISNUMBER(SEARCH("/W",AE6)),FALSE),IF(IFERROR(ISNUMBER(SEARCH("-",AE6)),FALSE),MID(AE6,SEARCH("-",AE6)+1,100),AE6),AE6))) -> 2026/W34 | AH6: Approved | AK6: Approved | AN6: Approved | AQ6: Approved | AT6: N/A | AW6: Approved | AZ6: COM Received | BC6: =IF(J6="","",IF(OR(J6="OB",J6="NOR",J6="FC",J6="PIPELINE"),"Active","Complete")) -> Complete | BD6: Yes | BE6: =IF(UPPER(TRIM(J6))="SHIPPED","READY",_xlfn.LET(_xlpm.stage,IF(B6="","",B6&": "),_xlpm.ip,_xlfn.TEXTJOIN(", ",TRUE,IF(LOWER(AH6)="in progress","Drawing",""),IF(LOWER(AK6)="in progress","Veneer/Wood",""),IF(LOWER(AN6)="in progress","Marble",""),IF(LOWER(AQ6)="in progress","Metal",""),IF(LOWER(AT6)="in progress","Mirror",""),IF(LOWER(AW6)="in progress","Electrical",""),IF(LOWER(AZ6)="in progress","Fabric","")),_xlpm.pa,_xlfn.TEXTJOIN(", ",TRUE,IF(LOWER(AH6)="pending approval","Drawing",""),IF(LOWER(AK6)="pending approval","Veneer/Wood",""),IF(LOWER(AN6)="pending approval","Marble",""),IF(LOWER(AQ6)="pending approval","Metal",""),IF(LOWER(AT6)="pending approval","Mirror",""),IF(LOWER(AW6)="pending approval","Electrical",""),IF(LOWER(AZ6)="pending approval","Fabric","")),_xlpm.ns,_xlfn.TEXTJOIN(", ",TRUE,IF(LOWER(AH6)="not started","Drawing",""),IF(LOWER(AK6)="not started","Veneer/Wood",""),IF(LOWER(AN6)="not started","Marble",""),IF(LOWER(AQ6)="not started","Metal",""),IF(LOWER(AT6)="not started","Mirror",""),IF(LOWER(AW6)="not started","Electrical",""),IF(LOWER(AZ6)="not started","Fabric","")),_xlpm.fab,IF(OR(LOWER(AZ6)="com",LOWER(AZ6)="com pending",LOWER(AZ6)="com received"),"Fabric is "&LOWER(AZ6),""),_xlpm.parts,_xlfn.TEXTJOIN("; ",TRUE,IF(_xlpm.ip<>"","In progress: "&_xlpm.ip,""),IF(_xlpm.pa<>"","Pending approval: "&_xlpm.pa,""),IF(_xlpm.ns<>"","Not started: "&_xlpm.ns,""),_xlpm.fab),_xlpm.deadline,MIN(IF(AND(AH6<>"",LOWER(AH6)<>"approved",LOWER(AH6)<>"n/a",ISNUMBER(AI6)),AI6,1E+99),IF(AND(AK6<>"",LOWER(AK6)<>"approved",LOWER(AK6)<>"n/a",ISNUMBER(AL6)),AL6,1E+99),IF(AND(AN6<>"",LOWER(AN6)<>"approved",LOWER(AN6)<>"n/a",ISNUMBER(AO6)),AO6,1E+99),IF(AND(AQ6<>"",LOWER(AQ6)<>"approved",LOWER(AQ6)<>"n/a",ISNUMBER(AR6)),AR6,1E+99),IF(AND(AT6<>"",LOWER(AT6)<>"approved",LOWER(AT6)<>"n/a",ISNUMBER(AU6)),AU6,1E+99),IF(AND(AW6<>"",LOWER(AW6)<>"approved",LOWER(AW6)<>"n/a",ISNUMBER(AX6)),AX6,1E+99),IF(AND(AZ6<>"",LOWER(AZ6)<>"approved",LOWER(AZ6)<>"n/a",ISNUMBER(BA6)),BA6,1E+99)),_xlpm.sw,IF(AG6="","",IFERROR("SW"&MID(AG6,FIND("/W",AG6)+2,99),"SW "&AG6)),_xlpm.stage&IF(_xlpm.parts="","All development items approved/closed",_xlpm.parts)&IF(AND(_xlpm.parts<>"",_xlpm.deadline<1E+99),"; need approval by "&TEXT(_xlpm.deadline,"d-mmm-yy"),"")&IF(_xlpm.sw<>""," for "&_xlpm.sw,""))) -> READY
A7: =IFERROR(VLOOKUP(E7,'Customer '!$A$4:$D$23,3,FALSE),"") -> RH | B7: NPI | C7: TRINH | D7: Sue Bilstad | E7: RESTORATION HARDWARE_HS | F7: =IFERROR(VLOOKUP(E7,'Customer '!$A$4:$D$28,2,FALSE),"") -> RH | G7: GRAND HYATT BAHA MAR | H7: =IF(OR(DetailTracker[[#This Row],[PROJECT NAME (SHORT)]]="",DetailTracker[[#This Row],[CUSTOMER SHORTEN NAME]]=""),"",IF(ISNUMBER(DetailTracker[[#This Row],[BOQ DATE]]),YEAR(DetailTracker[[#This Row],[BOQ DATE]])&"-"&DetailTracker[[#This Row],[CUSTOMER SHORTEN NAME]]&"-"&DetailTracker[[#This Row],[PROJECT NAME (SHORT)]],IF(OR(DetailTracker[[#This Row],[SHIP MONTH FC]]="TBC",DetailTracker[[#This Row],[SHIP MONTH FC]]="Removed"),DetailTracker[[#This Row],[SHIP MONTH FC]]&"-"&DetailTracker[[#This Row],[CUSTOMER SHORTEN NAME]]&"-"&DetailTracker[[#This Row],[PROJECT NAME (SHORT)]],YEAR(TODAY())&"-"&DetailTracker[[#This Row],[CUSTOMER SHORTEN NAME]]&"-"&DetailTracker[[#This Row],[PROJECT NAME (SHORT)]]))) -> 2026-RH-GRAND HYATT BAHA MAR | I7: =IF(OR($H7="",$B7=""),0,--(COUNTIFS($H$3:$H7,$H7,$B$3:$B7,$B7)=1)) -> 0 | J7: SHIPPED | K7: NEW | L7: 8. Shipment | M7: 46033 | N7: 46098 | P7: BS | Q7: Bahamas | R7: 0 | S7: 0 | V7: 26 | X7: 2454228 | Y7: 18067 | Z7: 2026/M08 | AA7: =IF(Z7="","",IF(OR(Z7="TBC",Z7="Removed"),Z7,LEFT(Z7,4))) -> 2026 | AB7: 46167 | AC7: 46201 | AD7: 46173 | AE7: 46257 | AF7: =IF(AD7="","",IF(ISNUMBER(AD7),IF(AND(AD7>='2026 Calendar'!$C$4,AD7<='2026 Calendar'!$E$107),LOOKUP(AD7,'2026 Calendar'!$C$4:$C$107,'2026 Calendar'!$A$4:$A$107),YEAR(AD7-WEEKDAY(AD7,2)+4)&"/W"&TEXT(WEEKNUM(AD7,21),"00")),IF(IFERROR(ISNUMBER(SEARCH("/W",AD7)),FALSE),IF(IFERROR(ISNUMBER(SEARCH("-",AD7)),FALSE),LEFT(AD7,SEARCH("-",AD7)-1),AD7),AD7))) -> 2026/W22 | AG7: =IF(AE7="","",IF(ISNUMBER(AE7),IF(AND(AE7>='2026 Calendar'!$C$4,AE7<='2026 Calendar'!$E$107),LOOKUP(AE7,'2026 Calendar'!$C$4:$C$107,'2026 Calendar'!$A$4:$A$107),YEAR(AE7-WEEKDAY(AE7,2)+4)&"/W"&TEXT(WEEKNUM(AE7,21),"00")),IF(IFERROR(ISNUMBER(SEARCH("/W",AE7)),FALSE),IF(IFERROR(ISNUMBER(SEARCH("-",AE7)),FALSE),MID(AE7,SEARCH("-",AE7)+1,100),AE7),AE7))) -> 2026/W34 | AH7: Approved | AK7: Approved | AN7: Approved | AQ7: Approved | AT7: N/A | AW7: Approved | AZ7: COM Received | BC7: =IF(J7="","",IF(OR(J7="OB",J7="NOR",J7="FC",J7="PIPELINE"),"Active","Complete")) -> Complete | BD7: Yes | BE7: =IF(UPPER(TRIM(J7))="SHIPPED","READY",_xlfn.LET(_xlpm.stage,IF(B7="","",B7&": "),_xlpm.ip,_xlfn.TEXTJOIN(", ",TRUE,IF(LOWER(AH7)="in progress","Drawing",""),IF(LOWER(AK7)="in progress","Veneer/Wood",""),IF(LOWER(AN7)="in progress","Marble",""),IF(LOWER(AQ7)="in progress","Metal",""),IF(LOWER(AT7)="in progress","Mirror",""),IF(LOWER(AW7)="in progress","Electrical",""),IF(LOWER(AZ7)="in progress","Fabric","")),_xlpm.pa,_xlfn.TEXTJOIN(", ",TRUE,IF(LOWER(AH7)="pending approval","Drawing",""),IF(LOWER(AK7)="pending approval","Veneer/Wood",""),IF(LOWER(AN7)="pending approval","Marble",""),IF(LOWER(AQ7)="pending approval","Metal",""),IF(LOWER(AT7)="pending approval","Mirror",""),IF(LOWER(AW7)="pending approval","Electrical",""),IF(LOWER(AZ7)="pending approval","Fabric","")),_xlpm.ns,_xlfn.TEXTJOIN(", ",TRUE,IF(LOWER(AH7)="not started","Drawing",""),IF(LOWER(AK7)="not started","Veneer/Wood",""),IF(LOWER(AN7)="not started","Marble",""),IF(LOWER(AQ7)="not started","Metal",""),IF(LOWER(AT7)="not started","Mirror",""),IF(LOWER(AW7)="not started","Electrical",""),IF(LOWER(AZ7)="not started","Fabric","")),_xlpm.fab,IF(OR(LOWER(AZ7)="com",LOWER(AZ7)="com pending",LOWER(AZ7)="com received"),"Fabric is "&LOWER(AZ7),""),_xlpm.parts,_xlfn.TEXTJOIN("; ",TRUE,IF(_xlpm.ip<>"","In progress: "&_xlpm.ip,""),IF(_xlpm.pa<>"","Pending approval: "&_xlpm.pa,""),IF(_xlpm.ns<>"","Not started: "&_xlpm.ns,""),_xlpm.fab),_xlpm.deadline,MIN(IF(AND(AH7<>"",LOWER(AH7)<>"approved",LOWER(AH7)<>"n/a",ISNUMBER(AI7)),AI7,1E+99),IF(AND(AK7<>"",LOWER(AK7)<>"approved",LOWER(AK7)<>"n/a",ISNUMBER(AL7)),AL7,1E+99),IF(AND(AN7<>"",LOWER(AN7)<>"approved",LOWER(AN7)<>"n/a",ISNUMBER(AO7)),AO7,1E+99),IF(AND(AQ7<>"",LOWER(AQ7)<>"approved",LOWER(AQ7)<>"n/a",ISNUMBER(AR7)),AR7,1E+99),IF(AND(AT7<>"",LOWER(AT7)<>"approved",LOWER(AT7)<>"n/a",ISNUMBER(AU7)),AU7,1E+99),IF(AND(AW7<>"",LOWER(AW7)<>"approved",LOWER(AW7)<>"n/a",ISNUMBER(AX7)),AX7,1E+99),IF(AND(AZ7<>"",LOWER(AZ7)<>"approved",LOWER(AZ7)<>"n/a",ISNUMBER(BA7)),BA7,1E+99)),_xlpm.sw,IF(AG7="","",IFERROR("SW"&MID(AG7,FIND("/W",AG7)+2,99),"SW "&AG7)),_xlpm.stage&IF(_xlpm.parts="","All development items approved/closed",_xlpm.parts)&IF(AND(_xlpm.parts<>"",_xlpm.deadline<1E+99),"; need approval by "&TEXT(_xlpm.deadline,"d-mmm-yy"),"")&IF(_xlpm.sw<>""," for "&_xlpm.sw,""))) -> READY
A8: =IFERROR(VLOOKUP(E8,'Customer '!$A$4:$D$23,3,FALSE),"") -> RH | B8: NPI | C8: BIEN | D8: Sue Bilstad | E8: RESTORATION HARDWARE_HS | F8: =IFERROR(VLOOKUP(E8,'Customer '!$A$4:$D$28,2,FALSE),"") -> RH | G8: GRAND HYATT BAHA MAR-PHASE 2 | H8: =IF(OR(DetailTracker[[#This Row],[PROJECT NAME (SHORT)]]="",DetailTracker[[#This Row],[CUSTOMER SHORTEN NAME]]=""),"",IF(ISNUMBER(DetailTracker[[#This Row],[BOQ DATE]]),YEAR(DetailTracker[[#This Row],[BOQ DATE]])&"-"&DetailTracker[[#This Row],[CUSTOMER SHORTEN NAME]]&"-"&DetailTracker[[#This Row],[PROJECT NAME (SHORT)]],IF(OR(DetailTracker[[#This Row],[SHIP MONTH FC]]="TBC",DetailTracker[[#This Row],[SHIP MONTH FC]]="Removed"),DetailTracker[[#This Row],[SHIP MONTH FC]]&"-"&DetailTracker[[#This Row],[CUSTOMER SHORTEN NAME]]&"-"&DetailTracker[[#This Row],[PROJECT NAME (SHORT)]],YEAR(TODAY())&"-"&DetailTracker[[#This Row],[CUSTOMER SHORTEN NAME]]&"-"&DetailTracker[[#This Row],[PROJECT NAME (SHORT)]]))) -> 2026-RH-GRAND HYATT BAHA MAR-PHASE 2 | I8: =IF(OR($H8="",$B8=""),0,--(COUNTIFS($H$3:$H8,$H8,$B$3:$B8,$B8)=1)) -> 1 | J8: FC | K8: NEW | L8: 1. Preliminary Design | P8: BS | Q8: Bahamas | R8: 0 | S8: 0 | V8: 27 | X8: 2936224.5 | Y8: 1000000 | Z8: 2027/M06 | AA8: =IF(Z8="","",IF(OR(Z8="TBC",Z8="Removed"),Z8,LEFT(Z8,4))) -> 2027 | AD8: 46549 | AE8: 46626 | AF8: =IF(AD8="","",IF(ISNUMBER(AD8),IF(AND(AD8>='2026 Calendar'!$C$4,AD8<='2026 Calendar'!$E$107),LOOKUP(AD8,'2026 Calendar'!$C$4:$C$107,'2026 Calendar'!$A$4:$A$107),YEAR(AD8-WEEKDAY(AD8,2)+4)&"/W"&TEXT(WEEKNUM(AD8,21),"00")),IF(IFERROR(ISNUMBER(SEARCH("/W",AD8)),FALSE),IF(IFERROR(ISNUMBER(SEARCH("-",AD8)),FALSE),LEFT(AD8,SEARCH("-",AD8)-1),AD8),AD8))) -> 2027/W24 | AG8: =IF(AE8="","",IF(ISNUMBER(AE8),IF(AND(AE8>='2026 Calendar'!$C$4,AE8<='2026 Calendar'!$E$107),LOOKUP(AE8,'2026 Calendar'!$C$4:$C$107,'2026 Calendar'!$A$4:$A$107),YEAR(AE8-WEEKDAY(AE8,2)+4)&"/W"&TEXT(WEEKNUM(AE8,21),"00")),IF(IFERROR(ISNUMBER(SEARCH("/W",AE8)),FALSE),IF(IFERROR(ISNUMBER(SEARCH("-",AE8)),FALSE),MID(AE8,SEARCH("-",AE8)+1,100),AE8),AE8))) -> 2027/W35 | AH8: Not Started | AK8: Not Started | AN8: Not Started | AQ8: Not Started | AT8: N/A | AW8: Not Started | AZ8: Not Started | BC8: =IF(J8="","",IF(OR(J8="OB",J8="NOR",J8="FC",J8="PIPELINE"),"Active","Complete")) -> Active | BD8: Yes | BE8: =IF(UPPER(TRIM(J8))="SHIPPED","READY",_xlfn.LET(_xlpm.stage,IF(B8="","",B8&": "),_xlpm.ip,_xlfn.TEXTJOIN(", ",TRUE,IF(LOWER(AH8)="in progress","Drawing",""),IF(LOWER(AK8)="in progress","Veneer/Wood",""),IF(LOWER(AN8)="in progress","Marble",""),IF(LOWER(AQ8)="in progress","Metal",""),IF(LOWER(AT8)="in progress","Mirror",""),IF(LOWER(AW8)="in progress","Electrical",""),IF(LOWER(AZ8)="in progress","Fabric","")),_xlpm.pa,_xlfn.TEXTJOIN(", ",TRUE,IF(LOWER(AH8)="pending approval","Drawing",""),IF(LOWER(AK8)="pending approval","Veneer/Wood",""),IF(LOWER(AN8)="pending approval","Marble",""),IF(LOWER(AQ8)="pending approval","Metal",""),IF(LOWER(AT8)="pending approval","Mirror",""),IF(LOWER(AW8)="pending approval","Electrical",""),IF(LOWER(AZ8)="pending approval","Fabric","")),_xlpm.ns,_xlfn.TEXTJOIN(", ",TRUE,IF(LOWER(AH8)="not started","Drawing",""),IF(LOWER(AK8)="not started","Veneer/Wood",""),IF(LOWER(AN8)="not started","Marble",""),IF(LOWER(AQ8)="not started","Metal",""),IF(LOWER(AT8)="not started","Mirror",""),IF(LOWER(AW8)="not started","Electrical",""),IF(LOWER(AZ8)="not started","Fabric","")),_xlpm.fab,IF(OR(LOWER(AZ8)="com",LOWER(AZ8)="com pending",LOWER(AZ8)="com received"),"Fabric is "&LOWER(AZ8),""),_xlpm.parts,_xlfn.TEXTJOIN("; ",TRUE,IF(_xlpm.ip<>"","In progress: "&_xlpm.ip,""),IF(_xlpm.pa<>"","Pending approval: "&_xlpm.pa,""),IF(_xlpm.ns<>"","Not started: "&_xlpm.ns,""),_xlpm.fab),_xlpm.deadline,MIN(IF(AND(AH8<>"",LOWER(AH8)<>"approved",LOWER(AH8)<>"n/a",ISNUMBER(AI8)),AI8,1E+99),IF(AND(AK8<>"",LOWER(AK8)<>"approved",LOWER(AK8)<>"n/a",ISNUMBER(AL8)),AL8,1E+99),IF(AND(AN8<>"",LOWER(AN8)<>"approved",LOWER(AN8)<>"n/a",ISNUMBER(AO8)),AO8,1E+99),IF(AND(AQ8<>"",LOWER(AQ8)<>"approved",LOWER(AQ8)<>"n/a",ISNUMBER(AR8)),AR8,1E+99),IF(AND(AT8<>"",LOWER(AT8)<>"approved",LOWER(AT8)<>"n/a",ISNUMBER(AU8)),AU8,1E+99),IF(AND(AW8<>"",LOWER(AW8)<>"approved",LOWER(AW8)<>"n/a",ISNUMBER(AX8)),AX8,1E+99),IF(AND(AZ8<>"",LOWER(AZ8)<>"approved",LOWER(AZ8)<>"n/a",ISNUMBER(BA8)),BA8,1E+99)),_xlpm.sw,IF(AG8="","",IFERROR("SW"&MID(AG8,FIND("/W",AG8)+2,99),"SW "&AG8)),_xlpm.stage&IF(_xlpm.parts="","All development items approved/closed",_xlpm.parts)&IF(AND(_xlpm.parts<>"",_xlpm.deadline<1E+99),"; need approval by "&TEXT(_xlpm.deadline,"d-mmm-yy"),"")&IF(_xlpm.sw<>""," for "&_xlpm.sw,""))) -> NPI: Not started: Drawing, Veneer/Wood, Marble, Metal, Electrical, Fabric for SW35
A9: =IFERROR(VLOOKUP(E9,'Customer '!$A$4:$D$23,3,FALSE),"") -> RH | B9: NPI | C9: BIEN | D9: Sue Bilstad | E9: RESTORATION HARDWARE_HS | F9: =IFERROR(VLOOKUP(E9,'Customer '!$A$4:$D$28,2,FALSE),"") -> RH | G9: GRAND HYATT BAHA MAR-PHASE 2 | H9: =IF(OR(DetailTracker[[#This Row],[PROJECT NAME (SHORT)]]="",DetailTracker[[#This Row],[CUSTOMER SHORTEN NAME]]=""),"",IF(ISNUMBER(DetailTracker[[#This Row],[BOQ DATE]]),YEAR(DetailTracker[[#This Row],[BOQ DATE]])&"-"&DetailTracker[[#This Row],[CUSTOMER SHORTEN NAME]]&"-"&DetailTracker[[#This Row],[PROJECT NAME (SHORT)]],IF(OR(DetailTracker[[#This Row],[SHIP MONTH FC]]="TBC",DetailTracker[[#This Row],[SHIP MONTH FC]]="Removed"),DetailTracker[[#This Row],[SHIP MONTH FC]]&"-"&DetailTracker[[#This Row],[CUSTOMER SHORTEN NAME]]&"-"&DetailTracker[[#This Row],[PROJECT NAME (SHORT)]],YEAR(TODAY())&"-"&DetailTracker[[#This Row],[CUSTOMER SHORTEN NAME]]&"-"&DetailTracker[[#This Row],[PROJECT NAME (SHORT)]]))) -> 2026-RH-GRAND HYATT BAHA MAR-PHASE 2 | I9: =IF(OR($H9="",$B9=""),0,--(COUNTIFS($H$3:$H9,$H9,$B$3:$B9,$B9)=1)) -> 0 | J9: FC | K9: NEW | L9: 1. Preliminary Design | P9: BS | Q9: Bahamas | R9: 0 | S9: 0 | V9: 27 | X9: 2936224.5 | Y9: 1000000 | Z9: 2027/M07 | AA9: =IF(Z9="","",IF(OR(Z9="TBC",Z9="Removed"),Z9,LEFT(Z9,4))) -> 2027 | AD9: 46549 | AE9: 46626 | AF9: =IF(AD9="","",IF(ISNUMBER(AD9),IF(AND(AD9>='2026 Calendar'!$C$4,AD9<='2026 Calendar'!$E$107),LOOKUP(AD9,'2026 Calendar'!$C$4:$C$107,'2026 Calendar'!$A$4:$A$107),YEAR(AD9-WEEKDAY(AD9,2)+4)&"/W"&TEXT(WEEKNUM(AD9,21),"00")),IF(IFERROR(ISNUMBER(SEARCH("/W",AD9)),FALSE),IF(IFERROR(ISNUMBER(SEARCH("-",AD9)),FALSE),LEFT(AD9,SEARCH("-",AD9)-1),AD9),AD9))) -> 2027/W24 | AG9: =IF(AE9="","",IF(ISNUMBER(AE9),IF(AND(AE9>='2026 Calendar'!$C$4,AE9<='2026 Calendar'!$E$107),LOOKUP(AE9,'2026 Calendar'!$C$4:$C$107,'2026 Calendar'!$A$4:$A$107),YEAR(AE9-WEEKDAY(AE9,2)+4)&"/W"&TEXT(WEEKNUM(AE9,21),"00")),IF(IFERROR(ISNUMBER(SEARCH("/W",AE9)),FALSE),IF(IFERROR(ISNUMBER(SEARCH("-",AE9)),FALSE),MID(AE9,SEARCH("-",AE9)+1,100),AE9),AE9))) -> 2027/W35 | AH9: Not Started | AK9: Not Started | AN9: Not Started | AQ9: Not Started | AT9: N/A | AW9: Not Started | AZ9: Not Started | BC9: =IF(J9="","",IF(OR(J9="OB",J9="NOR",J9="FC",J9="PIPELINE"),"Active","Complete")) -> Active | BD9: Yes | BE9: =IF(UPPER(TRIM(J9))="SHIPPED","READY",_xlfn.LET(_xlpm.stage,IF(B9="","",B9&": "),_xlpm.ip,_xlfn.TEXTJOIN(", ",TRUE,IF(LOWER(AH9)="in progress","Drawing",""),IF(LOWER(AK9)="in progress","Veneer/Wood",""),IF(LOWER(AN9)="in progress","Marble",""),IF(LOWER(AQ9)="in progress","Metal",""),IF(LOWER(AT9)="in progress","Mirror",""),IF(LOWER(AW9)="in progress","Electrical",""),IF(LOWER(AZ9)="in progress","Fabric","")),_xlpm.pa,_xlfn.TEXTJOIN(", ",TRUE,IF(LOWER(AH9)="pending approval","Drawing",""),IF(LOWER(AK9)="pending approval","Veneer/Wood",""),IF(LOWER(AN9)="pending approval","Marble",""),IF(LOWER(AQ9)="pending approval","Metal",""),IF(LOWER(AT9)="pending approval","Mirror",""),IF(LOWER(AW9)="pending approval","Electrical",""),IF(LOWER(AZ9)="pending approval","Fabric","")),_xlpm.ns,_xlfn.TEXTJOIN(", ",TRUE,IF(LOWER(AH9)="not started","Drawing",""),IF(LOWER(AK9)="not started","Veneer/Wood",""),IF(LOWER(AN9)="not started","Marble",""),IF(LOWER(AQ9)="not started","Metal",""),IF(LOWER(AT9)="not started","Mirror",""),IF(LOWER(AW9)="not started","Electrical",""),IF(LOWER(AZ9)="not started","Fabric","")),_xlpm.fab,IF(OR(LOWER(AZ9)="com",LOWER(AZ9)="com pending",LOWER(AZ9)="com received"),"Fabric is "&LOWER(AZ9),""),_xlpm.parts,_xlfn.TEXTJOIN("; ",TRUE,IF(_xlpm.ip<>"","In progress: "&_xlpm.ip,""),IF(_xlpm.pa<>"","Pending approval: "&_xlpm.pa,""),IF(_xlpm.ns<>"","Not started: "&_xlpm.ns,""),_xlpm.fab),_xlpm.deadline,MIN(IF(AND(AH9<>"",LOWER(AH9)<>"approved",LOWER(AH9)<>"n/a",ISNUMBER(AI9)),AI9,1E+99),IF(AND(AK9<>"",LOWER(AK9)<>"approved",LOWER(AK9)<>"n/a",ISNUMBER(AL9)),AL9,1E+99),IF(AND(AN9<>"",LOWER(AN9)<>"approved",LOWER(AN9)<>"n/a",ISNUMBER(AO9)),AO9,1E+99),IF(AND(AQ9<>"",LOWER(AQ9)<>"approved",LOWER(AQ9)<>"n/a",ISNUMBER(AR9)),AR9,1E+99),IF(AND(AT9<>"",LOWER(AT9)<>"approved",LOWER(AT9)<>"n/a",ISNUMBER(AU9)),AU9,1E+99),IF(AND(AW9<>"",LOWER(AW9)<>"approved",LOWER(AW9)<>"n/a",ISNUMBER(AX9)),AX9,1E+99),IF(AND(AZ9<>"",LOWER(AZ9)<>"approved",LOWER(AZ9)<>"n/a",ISNUMBER(BA9)),BA9,1E+99)),_xlpm.sw,IF(AG9="","",IFERROR("SW"&MID(AG9,FIND("/W",AG9)+2,99),"SW "&AG9)),_xlpm.stage&IF(_xlpm.parts="","All development items approved/closed",_xlpm.parts)&IF(AND(_xlpm.parts<>"",_xlpm.deadline<1E+99),"; need approval by "&TEXT(_xlpm.deadline,"d-mmm-yy"),"")&IF(_xlpm.sw<>""," for "&_xlpm.sw,""))) -> NPI: Not started: Drawing, Veneer/Wood, Marble, Metal, Electrical, Fabric for SW35
A10: =IFERROR(VLOOKUP(E10,'Customer '!$A$4:$D$23,3,FALSE),"") -> RH | B10: NPI | C10: BIEN | D10: Sue Bilstad | E10: RESTORATION HARDWARE_HS | F10: =IFERROR(VLOOKUP(E10,'Customer '!$A$4:$D$28,2,FALSE),"") -> RH | G10: GRAND HYATT BAHA MAR-PHASE 2 | H10: =IF(OR(DetailTracker[[#This Row],[PROJECT NAME (SHORT)]]="",DetailTracker[[#This Row],[CUSTOMER SHORTEN NAME]]=""),"",IF(ISNUMBER(DetailTracker[[#This Row],[BOQ DATE]]),YEAR(DetailTracker[[#This Row],[BOQ DATE]])&"-"&DetailTracker[[#This Row],[CUSTOMER SHORTEN NAME]]&"-"&DetailTracker[[#This Row],[PROJECT NAME (SHORT)]],IF(OR(DetailTracker[[#This Row],[SHIP MONTH FC]]="TBC",DetailTracker[[#This Row],[SHIP MONTH FC]]="Removed"),DetailTracker[[#This Row],[SHIP MONTH FC]]&"-"&DetailTracker[[#This Row],[CUSTOMER SHORTEN NAME]]&"-"&DetailTracker[[#This Row],[PROJECT NAME (SHORT)]],YEAR(TODAY())&"-"&DetailTracker[[#This Row],[CUSTOMER SHORTEN NAME]]&"-"&DetailTracker[[#This Row],[PROJECT NAME (SHORT)]]))) -> 2026-RH-GRAND HYATT BAHA MAR-PHASE 2 | I10: =IF(OR($H10="",$B10=""),0,--(COUNTIFS($H$3:$H10,$H10,$B$3:$B10,$B10)=1)) -> 0 | J10: FC | K10: NEW | L10: 1. Preliminary Design | P10: BS | Q10: Bahamas | R10: 0 | S10: 0 | V10: 27 | X10: 2936224.5 | Y10: =X8-Y8-Y9 -> 936224.52 | Z10: 2027/M08 | AA10: =IF(Z10="","",IF(OR(Z10="TBC",Z10="Removed"),Z10,LEFT(Z10,4))) -> 2027 | AD10: 46549 | AE10: 46626 | AF10: =IF(AD10="","",IF(ISNUMBER(AD10),IF(AND(AD10>='2026 Calendar'!$C$4,AD10<='2026 Calendar'!$E$107),LOOKUP(AD10,'2026 Calendar'!$C$4:$C$107,'2026 Calendar'!$A$4:$A$107),YEAR(AD10-WEEKDAY(AD10,2)+4)&"/W"&TEXT(WEEKNUM(AD10,21),"00")),IF(IFERROR(ISNUMBER(SEARCH("/W",AD10)),FALSE),IF(IFERROR(ISNUMBER(SEARCH("-",AD10)),FALSE),LEFT(AD10,SEARCH("-",AD10)-1),AD10),AD10))) -> 2027/W24 | AG10: =IF(AE10="","",IF(ISNUMBER(AE10),IF(AND(AE10>='2026 Calendar'!$C$4,AE10<='2026 Calendar'!$E$107),LOOKUP(AE10,'2026 Calendar'!$C$4:$C$107,'2026 Calendar'!$A$4:$A$107),YEAR(AE10-WEEKDAY(AE10,2)+4)&"/W"&TEXT(WEEKNUM(AE10,21),"00")),IF(IFERROR(ISNUMBER(SEARCH("/W",AE10)),FALSE),IF(IFERROR(ISNUMBER(SEARCH("-",AE10)),FALSE),MID(AE10,SEARCH("-",AE10)+1,100),AE10),AE10))) -> 2027/W35 | AH10: Not Started | AK10: Not Started | AN10: Not Started | AQ10: Not Started | AT10: N/A | AW10: Not Started | AZ10: Not Started | BC10: =IF(J10="","",IF(OR(J10="OB",J10="NOR",J10="FC",J10="PIPELINE"),"Active","Complete")) -> Active | BD10: Yes | BE10: =IF(UPPER(TRIM(J10))="SHIPPED","READY",_xlfn.LET(_xlpm.stage,IF(B10="","",B10&": "),_xlpm.ip,_xlfn.TEXTJOIN(", ",TRUE,IF(LOWER(AH10)="in progress","Drawing",""),IF(LOWER(AK10)="in progress","Veneer/Wood",""),IF(LOWER(AN10)="in progress","Marble",""),IF(LOWER(AQ10)="in progress","Metal",""),IF(LOWER(AT10)="in progress","Mirror",""),IF(LOWER(AW10)="in progress","Electrical",""),IF(LOWER(AZ10)="in progress","Fabric","")),_xlpm.pa,_xlfn.TEXTJOIN(", ",TRUE,IF(LOWER(AH10)="pending approval","Drawing",""),IF(LOWER(AK10)="pending approval","Veneer/Wood",""),IF(LOWER(AN10)="pending approval","Marble",""),IF(LOWER(AQ10)="pending approval","Metal",""),IF(LOWER(AT10)="pending approval","Mirror",""),IF(LOWER(AW10)="pending approval","Electrical",""),IF(LOWER(AZ10)="pending approval","Fabric","")),_xlpm.ns,_xlfn.TEXTJOIN(", ",TRUE,IF(LOWER(AH10)="not started","Drawing",""),IF(LOWER(AK10)="not started","Veneer/Wood",""),IF(LOWER(AN10)="not started","Marble",""),IF(LOWER(AQ10)="not started","Metal",""),IF(LOWER(AT10)="not started","Mirror",""),IF(LOWER(AW10)="not started","Electrical",""),IF(LOWER(AZ10)="not started","Fabric","")),_xlpm.fab,IF(OR(LOWER(AZ10)="com",LOWER(AZ10)="com pending",LOWER(AZ10)="com received"),"Fabric is "&LOWER(AZ10),""),_xlpm.parts,_xlfn.TEXTJOIN("; ",TRUE,IF(_xlpm.ip<>"","In progress: "&_xlpm.ip,""),IF(_xlpm.pa<>"","Pending approval: "&_xlpm.pa,""),IF(_xlpm.ns<>"","Not started: "&_xlpm.ns,""),_xlpm.fab),_xlpm.deadline,MIN(IF(AND(AH10<>"",LOWER(AH10)<>"approved",LOWER(AH10)<>"n/a",ISNUMBER(AI10)),AI10,1E+99),IF(AND(AK10<>"",LOWER(AK10)<>"approved",LOWER(AK10)<>"n/a",ISNUMBER(AL10)),AL10,1E+99),IF(AND(AN10<>"",LOWER(AN10)<>"approved",LOWER(AN10)<>"n/a",ISNUMBER(AO10)),AO10,1E+99),IF(AND(AQ10<>"",LOWER(AQ10)<>"approved",LOWER(AQ10)<>"n/a",ISNUMBER(AR10)),AR10,1E+99),IF(AND(AT10<>"",LOWER(AT10)<>"approved",LOWER(AT10)<>"n/a",ISNUMBER(AU10)),AU10,1E+99),IF(AND(AW10<>"",LOWER(AW10)<>"approved",LOWER(AW10)<>"n/a",ISNUMBER(AX10)),AX10,1E+99),IF(AND(AZ10<>"",LOWER(AZ10)<>"approved",LOWER(AZ10)<>"n/a",ISNUMBER(BA10)),BA10,1E+99)),_xlpm.sw,IF(AG10="","",IFERROR("SW"&MID(AG10,FIND("/W",AG10)+2,99),"SW "&AG10)),_xlpm.stage&IF(_xlpm.parts="","All development items approved/closed",_xlpm.parts)&IF(AND(_xlpm.parts<>"",_xlpm.deadline<1E+99),"; need approval by "&TEXT(_xlpm.deadline,"d-mmm-yy"),"")&IF(_xlpm.sw<>""," for "&_xlpm.sw,""))) -> NPI: Not started: Drawing, Veneer/Wood, Marble, Metal, Electrical, Fabric for SW35
A11: =IFERROR(VLOOKUP(E11,'Customer '!$A$4:$D$23,3,FALSE),"") -> RH | B11: NPI | C11: TUYET | D11: Sue Bilstad | E11: RESTORATION HARDWARE_HS | F11: =IFERROR(VLOOKUP(E11,'Customer '!$A$4:$D$28,2,FALSE),"") -> RH | G11: FOX HARBOR | H11: =IF(OR(DetailTracker[[#This Row],[PROJECT NAME (SHORT)]]="",DetailTracker[[#This Row],[CUSTOMER SHORTEN NAME]]=""),"",IF(ISNUMBER(DetailTracker[[#This Row],[BOQ DATE]]),YEAR(DetailTracker[[#This Row],[BOQ DATE]])&"-"&DetailTracker[[#This Row],[CUSTOMER SHORTEN NAME]]&"-"&DetailTracker[[#This Row],[PROJECT NAME (SHORT)]],IF(OR(DetailTracker[[#This Row],[SHIP MONTH FC]]="TBC",DetailTracker[[#This Row],[SHIP MONTH FC]]="Removed"),DetailTracker[[#This Row],[SHIP MONTH FC]]&"-"&DetailTracker[[#This Row],[CUSTOMER SHORTEN NAME]]&"-"&DetailTracker[[#This Row],[PROJECT NAME (SHORT)]],YEAR(TODAY())&"-"&DetailTracker[[#This Row],[CUSTOMER SHORTEN NAME]]&"-"&DetailTracker[[#This Row],[PROJECT NAME (SHORT)]]))) -> 2025-RH-FOX HARBOR | I11: =IF(OR($H11="",$B11=""),0,--(COUNTIFS($H$3:$H11,$H11,$B$3:$B11,$B11)=1)) -> 1 | J11: SHIPPED | K11: REO | L11: 8. Shipment | M11: 45917 | N11: - | P11: CA | Q11: Canada | V11: 26 | X11: 30383.55 | Y11: 30383.55 | Z11: 2026/M04 | AA11: =IF(Z11="","",IF(OR(Z11="TBC",Z11="Removed"),Z11,LEFT(Z11,4))) -> 2026 | AB11: - | AD11: 46116 | AE11: 46116 | AF11: =IF(AD11="","",IF(ISNUMBER(AD11),IF(AND(AD11>='2026 Calendar'!$C$4,AD11<='2026 Calendar'!$E$107),LOOKUP(AD11,'2026 Calendar'!$C$4:$C$107,'2026 Calendar'!$A$4:$A$107),YEAR(AD11-WEEKDAY(AD11,2)+4)&"/W"&TEXT(WEEKNUM(AD11,21),"00")),IF(IFERROR(ISNUMBER(SEARCH("/W",AD11)),FALSE),IF(IFERROR(ISNUMBER(SEARCH("-",AD11)),FALSE),LEFT(AD11,SEARCH("-",AD11)-1),AD11),AD11))) -> 2026/W14 | AG11: =IF(AE11="","",IF(ISNUMBER(AE11),IF(AND(AE11>='2026 Calendar'!$C$4,AE11<='2026 Calendar'!$E$107),LOOKUP(AE11,'2026 Calendar'!$C$4:$C$107,'2026 Calendar'!$A$4:$A$107),YEAR(AE11-WEEKDAY(AE11,2)+4)&"/W"&TEXT(WEEKNUM(AE11,21),"00")),IF(IFERROR(ISNUMBER(SEARCH("/W",AE11)),FALSE),IF(IFERROR(ISNUMBER(SEARCH("-",AE11)),FALSE),MID(AE11,SEARCH("-",AE11)+1,100),AE11),AE11))) -> 2026/W14 | AH11: Approved | AK11: Approved | AN11: N/A | AQ11: Approved | AT11: N/A | AW11: N/A | AZ11: COM | BC11: =IF(J11="","",IF(OR(J11="OB",J11="NOR",J11="FC",J11="PIPELINE"),"Active","Complete")) -> Complete | BD11: Yes | BE11: =IF(UPPER(TRIM(J11))="SHIPPED","READY",_xlfn.LET(_xlpm.stage,IF(B11="","",B11&": "),_xlpm.ip,_xlfn.TEXTJOIN(", ",TRUE,IF(LOWER(AH11)="in progress","Drawing",""),IF(LOWER(AK11)="in progress","Veneer/Wood",""),IF(LOWER(AN11)="in progress","Marble",""),IF(LOWER(AQ11)="in progress","Metal",""),IF(LOWER(AT11)="in progress","Mirror",""),IF(LOWER(AW11)="in progress","Electrical",""),IF(LOWER(AZ11)="in progress","Fabric","")),_xlpm.pa,_xlfn.TEXTJOIN(", ",TRUE,IF(LOWER(AH11)="pending approval","Drawing",""),IF(LOWER(AK11)="pending approval","Veneer/Wood",""),IF(LOWER(AN11)="pending approval","Marble",""),IF(LOWER(AQ11)="pending approval","Metal",""),IF(LOWER(AT11)="pending approval","Mirror",""),IF(LOWER(AW11)="pending approval","Electrical",""),IF(LOWER(AZ11)="pending approval","Fabric","")),_xlpm.ns,_xlfn.TEXTJOIN(", ",TRUE,IF(LOWER(AH11)="not started","Drawing",""),IF(LOWER(AK11)="not started","Veneer/Wood",""),IF(LOWER(AN11)="not started","Marble",""),IF(LOWER(AQ11)="not started","Metal",""),IF(LOWER(AT11)="not started","Mirror",""),IF(LOWER(AW11)="not started","Electrical",""),IF(LOWER(AZ11)="not started","Fabric","")),_xlpm.fab,IF(OR(LOWER(AZ11)="com",LOWER(AZ11)="com pending",LOWER(AZ11)="com received"),"Fabric is "&LOWER(AZ11),""),_xlpm.parts,_xlfn.TEXTJOIN("; ",TRUE,IF(_xlpm.ip<>"","In progress: "&_xlpm.ip,""),IF(_xlpm.pa<>"","Pending approval: "&_xlpm.pa,""),IF(_xlpm.ns<>"","Not started: "&_xlpm.ns,""),_xlpm.fab),_xlpm.deadline,MIN(IF(AND(AH11<>"",LOWER(AH11)<>"approved",LOWER(AH11)<>"n/a",ISNUMBER(AI11)),AI11,1E+99),IF(AND(AK11<>"",LOWER(AK11)<>"approved",LOWER(AK11)<>"n/a",ISNUMBER(AL11)),AL11,1E+99),IF(AND(AN11<>"",LOWER(AN11)<>"approved",LOWER(AN11)<>"n/a",ISNUMBER(AO11)),AO11,1E+99),IF(AND(AQ11<>"",LOWER(AQ11)<>"approved",LOWER(AQ11)<>"n/a",ISNUMBER(AR11)),AR11,1E+99),IF(AND(AT11<>"",LOWER(AT11)<>"approved",LOWER(AT11)<>"n/a",ISNUMBER(AU11)),AU11,1E+99),IF(AND(AW11<>"",LOWER(AW11)<>"approved",LOWER(AW11)<>"n/a",ISNUMBER(AX11)),AX11,1E+99),IF(AND(AZ11<>"",LOWER(AZ11)<>"approved",LOWER(AZ11)<>"n/a",ISNUMBER(BA11)),BA11,1E+99)),_xlpm.sw,IF(AG11="","",IFERROR("SW"&MID(AG11,FIND("/W",AG11)+2,99),"SW "&AG11)),_xlpm.stage&IF(_xlpm.parts="","All development items approved/closed",_xlpm.parts)&IF(AND(_xlpm.parts<>"",_xlpm.deadline<1E+99),"; need approval by "&TEXT(_xlpm.deadline,"d-mmm-yy"),"")&IF(_xlpm.sw<>""," for "&_xlpm.sw,""))) -> READY
A12: =IFERROR(VLOOKUP(E12,'Customer '!$A$4:$D$23,3,FALSE),"") -> RH | B12: NPI | C12: TRINH | D12: Sue Bilstad | E12: RESTORATION HARDWARE_HS | F12: =IFERROR(VLOOKUP(E12,'Customer '!$A$4:$D$28,2,FALSE),"") -> RH | G12: RH CASSIA CONDO | H12: =IF(OR(DetailTracker[[#This Row],[PROJECT NAME (SHORT)]]="",DetailTracker[[#This Row],[CUSTOMER SHORTEN NAME]]=""),"",IF(ISNUMBER(DetailTracker[[#This Row],[BOQ DATE]]),YEAR(DetailTracker[[#This Row],[BOQ DATE]])&"-"&DetailTracker[[#This Row],[CUSTOMER SHORTEN NAME]]&"-"&DetailTracker[[#This Row],[PROJECT NAME (SHORT)]],IF(OR(DetailTracker[[#This Row],[SHIP MONTH FC]]="TBC",DetailTracker[[#This Row],[SHIP MONTH FC]]="Removed"),DetailTracker[[#This Row],[SHIP MONTH FC]]&"-"&DetailTracker[[#This Row],[CUSTOMER SHORTEN NAME]]&"-"&DetailTracker[[#This Row],[PROJECT NAME (SHORT)]],YEAR(TODAY())&"-"&DetailTracker[[#This Row],[CUSTOMER SHORTEN NAME]]&"-"&DetailTracker[[#This Row],[PROJECT NAME (SHORT)]]))) -> 2025-RH-RH CASSIA CONDO | I12: =IF(OR($H12="",$B12=""),0,--(COUNTIFS($H$3:$H12,$H12,$B$3:$B12,$B12)=1)) -> 1 | J12: SHIPPED | K12: NEW | L12: 8. Shipment | M12: 46020 | N12: 46101 | P12: US | Q12: FL | V12: 50 | X12: 1161167 | Y12: 269518 | Z12: 2026/M07 | AA12: =IF(Z12="","",IF(OR(Z12="TBC",Z12="Removed"),Z12,LEFT(Z12,4))) -> 2026 | AB12: 46234 | AC12: 46241 | AD12: 46223 | AE12: 46269 | AF12: =IF(AD12="","",IF(ISNUMBER(AD12),IF(AND(AD12>='2026 Calendar'!$C$4,AD12<='2026 Calendar'!$E$107),LOOKUP(AD12,'2026 Calendar'!$C$4:$C$107,'2026 Calendar'!$A$4:$A$107),YEAR(AD12-WEEKDAY(AD12,2)+4)&"/W"&TEXT(WEEKNUM(AD12,21),"00")),IF(IFERROR(ISNUMBER(SEARCH("/W",AD12)),FALSE),IF(IFERROR(ISNUMBER(SEARCH("-",AD12)),FALSE),LEFT(AD12,SEARCH("-",AD12)-1),AD12),AD12))) -> 2026/W30 | AG12: =IF(AE12="","",IF(ISNUMBER(AE12),IF(AND(AE12>='2026 Calendar'!$C$4,AE12<='2026 Calendar'!$E$107),LOOKUP(AE12,'2026 Calendar'!$C$4:$C$107,'2026 Calendar'!$A$4:$A$107),YEAR(AE12-WEEKDAY(AE12,2)+4)&"/W"&TEXT(WEEKNUM(AE12,21),"00")),IF(IFERROR(ISNUMBER(SEARCH("/W",AE12)),FALSE),IF(IFERROR(ISNUMBER(SEARCH("-",AE12)),FALSE),MID(AE12,SEARCH("-",AE12)+1,100),AE12),AE12))) -> 2026/W36 | AH12: Approved | AK12: Approved | AN12: N/A | AQ12: Approved | AT12: N/A | AW12: N/A | AZ12: COM | BB12: 13/6/2026 | BC12: =IF(J12="","",IF(OR(J12="OB",J12="NOR",J12="FC",J12="PIPELINE"),"Active","Complete")) -> Complete | BD12: Yes | BE12: =IF(UPPER(TRIM(J12))="SHIPPED","READY",_xlfn.LET(_xlpm.stage,IF(B12="","",B12&": "),_xlpm.ip,_xlfn.TEXTJOIN(", ",TRUE,IF(LOWER(AH12)="in progress","Drawing",""),IF(LOWER(AK12)="in progress","Veneer/Wood",""),IF(LOWER(AN12)="in progress","Marble",""),IF(LOWER(AQ12)="in progress","Metal",""),IF(LOWER(AT12)="in progress","Mirror",""),IF(LOWER(AW12)="in progress","Electrical",""),IF(LOWER(AZ12)="in progress","Fabric","")),_xlpm.pa,_xlfn.TEXTJOIN(", ",TRUE,IF(LOWER(AH12)="pending approval","Drawing",""),IF(LOWER(AK12)="pending approval","Veneer/Wood",""),IF(LOWER(AN12)="pending approval","Marble",""),IF(LOWER(AQ12)="pending approval","Metal",""),IF(LOWER(AT12)="pending approval","Mirror",""),IF(LOWER(AW12)="pending approval","Electrical",""),IF(LOWER(AZ12)="pending approval","Fabric","")),_xlpm.ns,_xlfn.TEXTJOIN(", ",TRUE,IF(LOWER(AH12)="not started","Drawing",""),IF(LOWER(AK12)="not started","Veneer/Wood",""),IF(LOWER(AN12)="not started","Marble",""),IF(LOWER(AQ12)="not started","Metal",""),IF(LOWER(AT12)="not started","Mirror",""),IF(LOWER(AW12)="not started","Electrical",""),IF(LOWER(AZ12)="not started","Fabric","")),_xlpm.fab,IF(OR(LOWER(AZ12)="com",LOWER(AZ12)="com pending",LOWER(AZ12)="com received"),"Fabric is "&LOWER(AZ12),""),_xlpm.parts,_xlfn.TEXTJOIN("; ",TRUE,IF(_xlpm.ip<>"","In progress: "&_xlpm.ip,""),IF(_xlpm.pa<>"","Pending approval: "&_xlpm.pa,""),IF(_xlpm.ns<>"","Not started: "&_xlpm.ns,""),_xlpm.fab),_xlpm.deadline,MIN(IF(AND(AH12<>"",LOWER(AH12)<>"approved",LOWER(AH12)<>"n/a",ISNUMBER(AI12)),AI12,1E+99),IF(AND(AK12<>"",LOWER(AK12)<>"approved",LOWER(AK12)<>"n/a",ISNUMBER(AL12)),AL12,1E+99),IF(AND(AN12<>"",LOWER(AN12)<>"approved",LOWER(AN12)<>"n/a",ISNUMBER(AO12)),AO12,1E+99),IF(AND(AQ12<>"",LOWER(AQ12)<>"approved",LOWER(AQ12)<>"n/a",ISNUMBER(AR12)),AR12,1E+99),IF(AND(AT12<>"",LOWER(AT12)<>"approved",LOWER(AT12)<>"n/a",ISNUMBER(AU12)),AU12,1E+99),IF(AND(AW12<>"",LOWER(AW12)<>"approved",LOWER(AW12)<>"n/a",ISNUMBER(AX12)),AX12,1E+99),IF(AND(AZ12<>"",LOWER(AZ12)<>"approved",LOWER(AZ12)<>"n/a",ISNUMBER(BA12)),BA12,1E+99)),_xlpm.sw,IF(AG12="","",IFERROR("SW"&MID(AG12,FIND("/W",AG12)+2,99),"SW "&AG12)),_xlpm.stage&IF(_xlpm.parts="","All development items approved/closed",_xlpm.parts)&IF(AND(_xlpm.parts<>"",_xlpm.deadline<1E+99),"; need approval by "&TEXT(_xlpm.deadline,"d-mmm-yy"),"")&IF(_xlpm.sw<>""," for "&_xlpm.sw,""))) -> READY
A13: =IFERROR(VLOOKUP(E13,'Customer '!$A$4:$D$23,3,FALSE),"") -> RH | B13: NPI | C13: TRINH | D13: Sue Bilstad | E13: RESTORATION HARDWARE_HS | F13: =IFERROR(VLOOKUP(E13,'Customer '!$A$4:$D$28,2,FALSE),"") -> RH | G13: RH CASSIA CONDO | H13: =IF(OR(DetailTracker[[#This Row],[PROJECT NAME (SHORT)]]="",DetailTracker[[#This Row],[CUSTOMER SHORTEN NAME]]=""),"",IF(ISNUMBER(DetailTracker[[#This Row],[BOQ DATE]]),YEAR(DetailTracker[[#This Row],[BOQ DATE]])&"-"&DetailTracker[[#This Row],[CUSTOMER SHORTEN NAME]]&"-"&DetailTracker[[#This Row],[PROJECT NAME (SHORT)]],IF(OR(DetailTracker[[#This Row],[SHIP MONTH FC]]="TBC",DetailTracker[[#This Row],[SHIP MONTH FC]]="Removed"),DetailTracker[[#This Row],[SHIP MONTH FC]]&"-"&DetailTracker[[#This Row],[CUSTOMER SHORTEN NAME]]&"-"&DetailTracker[[#This Row],[PROJECT NAME (SHORT)]],YEAR(TODAY())&"-"&DetailTracker[[#This Row],[CUSTOMER SHORTEN NAME]]&"-"&DetailTracker[[#This Row],[PROJECT NAME (SHORT)]]))) -> 2025-RH-RH CASSIA CONDO | I13: =IF(OR($H13="",$B13=""),0,--(COUNTIFS($H$3:$H13,$H13,$B$3:$B13,$B13)=1)) -> 0 | J13: SHIPPED | K13: NEW | L13: 8. Shipment | M13: 46020 | N13: 46101 | P13: US | Q13: FL | V13: 50 | X13: 1161167 | Y13: 760037 | Z13: 2026/M08 | AA13: =IF(Z13="","",IF(OR(Z13="TBC",Z13="Removed"),Z13,LEFT(Z13,4))) -> 2026 | AB13: 46234 | AC13: 46241 | AD13: 46223 | AE13: 46269 | AF13: =IF(AD13="","",IF(ISNUMBER(AD13),IF(AND(AD13>='2026 Calendar'!$C$4,AD13<='2026 Calendar'!$E$107),LOOKUP(AD13,'2026 Calendar'!$C$4:$C$107,'2026 Calendar'!$A$4:$A$107),YEAR(AD13-WEEKDAY(AD13,2)+4)&"/W"&TEXT(WEEKNUM(AD13,21),"00")),IF(IFERROR(ISNUMBER(SEARCH("/W",AD13)),FALSE),IF(IFERROR(ISNUMBER(SEARCH("-",AD13)),FALSE),LEFT(AD13,SEARCH("-",AD13)-1),AD13),AD13))) -> 2026/W30 | AG13: =IF(AE13="","",IF(ISNUMBER(AE13),IF(AND(AE13>='2026 Calendar'!$C$4,AE13<='2026 Calendar'!$E$107),LOOKUP(AE13,'2026 Calendar'!$C$4:$C$107,'2026 Calendar'!$A$4:$A$107),YEAR(AE13-WEEKDAY(AE13,2)+4)&"/W"&TEXT(WEEKNUM(AE13,21),"00")),IF(IFERROR(ISNUMBER(SEARCH("/W",AE13)),FALSE),IF(IFERROR(ISNUMBER(SEARCH("-",AE13)),FALSE),MID(AE13,SEARCH("-",AE13)+1,100),AE13),AE13))) -> 2026/W36 | AH13: Approved | AK13: Approved | AN13: N/A | AQ13: Approved | AT13: N/A | AW13: N/A | AZ13: COM Received | BB13: 13/6/2026 | BC13: =IF(J13="","",IF(OR(J13="OB",J13="NOR",J13="FC",J13="PIPELINE"),"Active","Complete")) -> Complete | BD13: Yes | BE13: =IF(UPPER(TRIM(J13))="SHIPPED","READY",_xlfn.LET(_xlpm.stage,IF(B13="","",B13&": "),_xlpm.ip,_xlfn.TEXTJOIN(", ",TRUE,IF(LOWER(AH13)="in progress","Drawing",""),IF(LOWER(AK13)="in progress","Veneer/Wood",""),IF(LOWER(AN13)="in progress","Marble",""),IF(LOWER(AQ13)="in progress","Metal",""),IF(LOWER(AT13)="in progress","Mirror",""),IF(LOWER(AW13)="in progress","Electrical",""),IF(LOWER(AZ13)="in progress","Fabric","")),_xlpm.pa,_xlfn.TEXTJOIN(", ",TRUE,IF(LOWER(AH13)="pending approval","Drawing",""),IF(LOWER(AK13)="pending approval","Veneer/Wood",""),IF(LOWER(AN13)="pending approval","Marble",""),IF(LOWER(AQ13)="pending approval","Metal",""),IF(LOWER(AT13)="pending approval","Mirror",""),IF(LOWER(AW13)="pending approval","Electrical",""),IF(LOWER(AZ13)="pending approval","Fabric","")),_xlpm.ns,_xlfn.TEXTJOIN(", ",TRUE,IF(LOWER(AH13)="not started","Drawing",""),IF(LOWER(AK13)="not started","Veneer/Wood",""),IF(LOWER(AN13)="not started","Marble",""),IF(LOWER(AQ13)="not started","Metal",""),IF(LOWER(AT13)="not started","Mirror",""),IF(LOWER(AW13)="not started","Electrical",""),IF(LOWER(AZ13)="not started","Fabric","")),_xlpm.fab,IF(OR(LOWER(AZ13)="com",LOWER(AZ13)="com pending",LOWER(AZ13)="com received"),"Fabric is "&LOWER(AZ13),""),_xlpm.parts,_xlfn.TEXTJOIN("; ",TRUE,IF(_xlpm.ip<>"","In progress: "&_xlpm.ip,""),IF(_xlpm.pa<>"","Pending approval: "&_xlpm.pa,""),IF(_xlpm.ns<>"","Not started: "&_xlpm.ns,""),_xlpm.fab),_xlpm.deadline,MIN(IF(AND(AH13<>"",LOWER(AH13)<>"approved",LOWER(AH13)<>"n/a",ISNUMBER(AI13)),AI13,1E+99),IF(AND(AK13<>"",LOWER(AK13)<>"approved",LOWER(AK13)<>"n/a",ISNUMBER(AL13)),AL13,1E+99),IF(AND(AN13<>"",LOWER(AN13)<>"approved",LOWER(AN13)<>"n/a",ISNUMBER(AO13)),AO13,1E+99),IF(AND(AQ13<>"",LOWER(AQ13)<>"approved",LOWER(AQ13)<>"n/a",ISNUMBER(AR13)),AR13,1E+99),IF(AND(AT13<>"",LOWER(AT13)<>"approved",LOWER(AT13)<>"n/a",ISNUMBER(AU13)),AU13,1E+99),IF(AND(AW13<>"",LOWER(AW13)<>"approved",LOWER(AW13)<>"n/a",ISNUMBER(AX13)),AX13,1E+99),IF(AND(AZ13<>"",LOWER(AZ13)<>"approved",LOWER(AZ13)<>"n/a",ISNUMBER(BA13)),BA13,1E+99)),_xlpm.sw,IF(AG13="","",IFERROR("SW"&MID(AG13,FIND("/W",AG13)+2,99),"SW "&AG13)),_xlpm.stage&IF(_xlpm.parts="","All development items approved/closed",_xlpm.parts)&IF(AND(_xlpm.parts<>"",_xlpm.deadline<1E+99),"; need approval by "&TEXT(_xlpm.deadline,"d-mmm-yy"),"")&IF(_xlpm.sw<>""," for "&_xlpm.sw,""))) -> READY
A14: =IFERROR(VLOOKUP(E14,'Customer '!$A$4:$D$23,3,FALSE),"") -> RH | B14: NPI | C14: TRINH | D14: Sue Bilstad | E14: RESTORATION HARDWARE_HS | F14: =IFERROR(VLOOKUP(E14,'Customer '!$A$4:$D$28,2,FALSE),"") -> RH | G14: RH CASSIA CONDO | H14: =IF(OR(DetailTracker[[#This Row],[PROJECT NAME (SHORT)]]="",DetailTracker[[#This Row],[CUSTOMER SHORTEN NAME]]=""),"",IF(ISNUMBER(DetailTracker[[#This Row],[BOQ DATE]]),YEAR(DetailTracker[[#This Row],[BOQ DATE]])&"-"&DetailTracker[[#This Row],[CUSTOMER SHORTEN NAME]]&"-"&DetailTracker[[#This Row],[PROJECT NAME (SHORT)]],IF(OR(DetailTracker[[#This Row],[SHIP MONTH FC]]="TBC",DetailTracker[[#This Row],[SHIP MONTH FC]]="Removed"),DetailTracker[[#This Row],[SHIP MONTH FC]]&"-"&DetailTracker[[#This Row],[CUSTOMER SHORTEN NAME]]&"-"&DetailTracker[[#This Row],[PROJECT NAME (SHORT)]],YEAR(TODAY())&"-"&DetailTracker[[#This Row],[CUSTOMER SHORTEN NAME]]&"-"&DetailTracker[[#This Row],[PROJECT NAME (SHORT)]]))) -> 2025-RH-RH CASSIA CONDO | I14: =IF(OR($H14="",$B14=""),0,--(COUNTIFS($H$3:$H14,$H14,$B$3:$B14,$B14)=1)) -> 0 | J14: SHIPPED | K14: NEW | L14: 8. Shipment | M14: 46020 | N14: 46101 | P14: US | Q14: FL | R14: 0 | S14: 0 | V14: 50 | X14: 1161167 | Y14: 131612 | Z14: 2026/M09 | AA14: =IF(Z14="","",IF(OR(Z14="TBC",Z14="Removed"),Z14,LEFT(Z14,4))) -> 2026 | AB14: 46234 | AC14: 46241 | AD14: 46223 | AE14: 46269 | AF14: =IF(AD14="","",IF(ISNUMBER(AD14),IF(AND(AD14>='2026 Calendar'!$C$4,AD14<='2026 Calendar'!$E$107),LOOKUP(AD14,'2026 Calendar'!$C$4:$C$107,'2026 Calendar'!$A$4:$A$107),YEAR(AD14-WEEKDAY(AD14,2)+4)&"/W"&TEXT(WEEKNUM(AD14,21),"00")),IF(IFERROR(ISNUMBER(SEARCH("/W",AD14)),FALSE),IF(IFERROR(ISNUMBER(SEARCH("-",AD14)),FALSE),LEFT(AD14,SEARCH("-",AD14)-1),AD14),AD14))) -> 2026/W30 | AG14: =IF(AE14="","",IF(ISNUMBER(AE14),IF(AND(AE14>='2026 Calendar'!$C$4,AE14<='2026 Calendar'!$E$107),LOOKUP(AE14,'2026 Calendar'!$C$4:$C$107,'2026 Calendar'!$A$4:$A$107),YEAR(AE14-WEEKDAY(AE14,2)+4)&"/W"&TEXT(WEEKNUM(AE14,21),"00")),IF(IFERROR(ISNUMBER(SEARCH("/W",AE14)),FALSE),IF(IFERROR(ISNUMBER(SEARCH("-",AE14)),FALSE),MID(AE14,SEARCH("-",AE14)+1,100),AE14),AE14))) -> 2026/W36 | AH14: Approved | AK14: Approved | AN14: N/A | AQ14: Approved | AT14: N/A | AW14: N/A | AZ14: COM Received | BB14: 13/6/2026 | BC14: =IF(J14="","",IF(OR(J14="OB",J14="NOR",J14="FC",J14="PIPELINE"),"Active","Complete")) -> Complete | BD14: Yes | BE14: =IF(UPPER(TRIM(J14))="SHIPPED","READY",_xlfn.LET(_xlpm.stage,IF(B14="","",B14&": "),_xlpm.ip,_xlfn.TEXTJOIN(", ",TRUE,IF(LOWER(AH14)="in progress","Drawing",""),IF(LOWER(AK14)="in progress","Veneer/Wood",""),IF(LOWER(AN14)="in progress","Marble",""),IF(LOWER(AQ14)="in progress","Metal",""),IF(LOWER(AT14)="in progress","Mirror",""),IF(LOWER(AW14)="in progress","Electrical",""),IF(LOWER(AZ14)="in progress","Fabric","")),_xlpm.pa,_xlfn.TEXTJOIN(", ",TRUE,IF(LOWER(AH14)="pending approval","Drawing",""),IF(LOWER(AK14)="pending approval","Veneer/Wood",""),IF(LOWER(AN14)="pending approval","Marble",""),IF(LOWER(AQ14)="pending approval","Metal",""),IF(LOWER(AT14)="pending approval","Mirror",""),IF(LOWER(AW14)="pending approval","Electrical",""),IF(LOWER(AZ14)="pending approval","Fabric","")),_xlpm.ns,_xlfn.TEXTJOIN(", ",TRUE,IF(LOWER(AH14)="not started","Drawing",""),IF(LOWER(AK14)="not started","Veneer/Wood",""),IF(LOWER(AN14)="not started","Marble",""),IF(LOWER(AQ14)="not started","Metal",""),IF(LOWER(AT14)="not started","Mirror",""),IF(LOWER(AW14)="not started","Electrical",""),IF(LOWER(AZ14)="not started","Fabric","")),_xlpm.fab,IF(OR(LOWER(AZ14)="com",LOWER(AZ14)="com pending",LOWER(AZ14)="com received"),"Fabric is "&LOWER(AZ14),""),_xlpm.parts,_xlfn.TEXTJOIN("; ",TRUE,IF(_xlpm.ip<>"","In progress: "&_xlpm.ip,""),IF(_xlpm.pa<>"","Pending approval: "&_xlpm.pa,""),IF(_xlpm.ns<>"","Not started: "&_xlpm.ns,""),_xlpm.fab),_xlpm.deadline,MIN(IF(AND(AH14<>"",LOWER(AH14)<>"approved",LOWER(AH14)<>"n/a",ISNUMBER(AI14)),AI14,1E+99),IF(AND(AK14<>"",LOWER(AK14)<>"approved",LOWER(AK14)<>"n/a",ISNUMBER(AL14)),AL14,1E+99),IF(AND(AN14<>"",LOWER(AN14)<>"approved",LOWER(AN14)<>"n/a",ISNUMBER(AO14)),AO14,1E+99),IF(AND(AQ14<>"",LOWER(AQ14)<>"approved",LOWER(AQ14)<>"n/a",ISNUMBER(AR14)),AR14,1E+99),IF(AND(AT14<>"",LOWER(AT14)<>"approved",LOWER(AT14)<>"n/a",ISNUMBER(AU14)),AU14,1E+99),IF(AND(AW14<>"",LOWER(AW14)<>"approved",LOWER(AW14)<>"n/a",ISNUMBER(AX14)),AX14,1E+99),IF(AND(AZ14<>"",LOWER(AZ14)<>"approved",LOWER(AZ14)<>"n/a",ISNUMBER(BA14)),BA14,1E+99)),_xlpm.sw,IF(AG14="","",IFERROR("SW"&MID(AG14,FIND("/W",AG14)+2,99),"SW "&AG14)),_xlpm.stage&IF(_xlpm.parts="","All development items approved/closed",_xlpm.parts)&IF(AND(_xlpm.parts<>"",_xlpm.deadline<1E+99),"; need approval by "&TEXT(_xlpm.deadline,"d-mmm-yy"),"")&IF(_xlpm.sw<>""," for "&_xlpm.sw,""))) -> READY
A15: =IFERROR(VLOOKUP(E15,'Customer '!$A$4:$D$23,3,FALSE),"") -> RH | B15: NPI | C15: DUNG | D15: Sue Bilstad | E15: RESTORATION HARDWARE_HS | F15: =IFERROR(VLOOKUP(E15,'Customer '!$A$4:$D$28,2,FALSE),"") -> RH | G15: MAIN STREET BOUTIQUE HOTEL | H15: =IF(OR(DetailTracker[[#This Row],[PROJECT NAME (SHORT)]]="",DetailTracker[[#This Row],[CUSTOMER SHORTEN NAME]]=""),"",IF(ISNUMBER(DetailTracker[[#This Row],[BOQ DATE]]),YEAR(DetailTracker[[#This Row],[BOQ DATE]])&"-"&DetailTracker[[#This Row],[CUSTOMER SHORTEN NAME]]&"-"&DetailTracker[[#This Row],[PROJECT NAME (SHORT)]],IF(OR(DetailTracker[[#This Row],[SHIP MONTH FC]]="TBC",DetailTracker[[#This Row],[SHIP MONTH FC]]="Removed"),DetailTracker[[#This Row],[SHIP MONTH FC]]&"-"&DetailTracker[[#This Row],[CUSTOMER SHORTEN NAME]]&"-"&DetailTracker[[#This Row],[PROJECT NAME (SHORT)]],YEAR(TODAY())&"-"&DetailTracker[[#This Row],[CUSTOMER SHORTEN NAME]]&"-"&DetailTracker[[#This Row],[PROJECT NAME (SHORT)]]))) -> 2025-RH-MAIN STREET BOUTIQUE HOTEL | I15: =IF(OR($H15="",$B15=""),0,--(COUNTIFS($H$3:$H15,$H15,$B$3:$B15,$B15)=1)) -> 1 | J15: SHIPPED | K15: NEW | L15: 8. Shipment | M15: 45953 | N15: 45964 | P15: US | Q15: CA | V15: 9 | X15: 54061.6 | Y15: 54061.6 | Z15: 2026/M04 | AA15: =IF(Z15="","",IF(OR(Z15="TBC",Z15="Removed"),Z15,LEFT(Z15,4))) -> 2026 | AB15: - | AD15: 46116 | AE15: 46116 | AF15: =IF(AD15="","",IF(ISNUMBER(AD15),IF(AND(AD15>='2026 Calendar'!$C$4,AD15<='2026 Calendar'!$E$107),LOOKUP(AD15,'2026 Calendar'!$C$4:$C$107,'2026 Calendar'!$A$4:$A$107),YEAR(AD15-WEEKDAY(AD15,2)+4)&"/W"&TEXT(WEEKNUM(AD15,21),"00")),IF(IFERROR(ISNUMBER(SEARCH("/W",AD15)),FALSE),IF(IFERROR(ISNUMBER(SEARCH("-",AD15)),FALSE),LEFT(AD15,SEARCH("-",AD15)-1),AD15),AD15))) -> 2026/W14 | AG15: =IF(AE15="","",IF(ISNUMBER(AE15),IF(AND(AE15>='2026 Calendar'!$C$4,AE15<='2026 Calendar'!$E$107),LOOKUP(AE15,'2026 Calendar'!$C$4:$C$107,'2026 Calendar'!$A$4:$A$107),YEAR(AE15-WEEKDAY(AE15,2)+4)&"/W"&TEXT(WEEKNUM(AE15,21),"00")),IF(IFERROR(ISNUMBER(SEARCH("/W",AE15)),FALSE),IF(IFERROR(ISNUMBER(SEARCH("-",AE15)),FALSE),MID(AE15,SEARCH("-",AE15)+1,100),AE15),AE15))) -> 2026/W14 | AH15: Approved | AK15: Approved | AN15: N/A | AQ15: Approved | AT15: Approved | AW15: Approved | AZ15: COM | BC15: =IF(J15="","",IF(OR(J15="OB",J15="NOR",J15="FC",J15="PIPELINE"),"Active","Complete")) -> Complete | BD15: Yes | BE15: =IF(UPPER(TRIM(J15))="SHIPPED","READY",_xlfn.LET(_xlpm.stage,IF(B15="","",B15&": "),_xlpm.ip,_xlfn.TEXTJOIN(", ",TRUE,IF(LOWER(AH15)="in progress","Drawing",""),IF(LOWER(AK15)="in progress","Veneer/Wood",""),IF(LOWER(AN15)="in progress","Marble",""),IF(LOWER(AQ15)="in progress","Metal",""),IF(LOWER(AT15)="in progress","Mirror",""),IF(LOWER(AW15)="in progress","Electrical",""),IF(LOWER(AZ15)="in progress","Fabric","")),_xlpm.pa,_xlfn.TEXTJOIN(", ",TRUE,IF(LOWER(AH15)="pending approval","Drawing",""),IF(LOWER(AK15)="pending approval","Veneer/Wood",""),IF(LOWER(AN15)="pending approval","Marble",""),IF(LOWER(AQ15)="pending approval","Metal",""),IF(LOWER(AT15)="pending approval","Mirror",""),IF(LOWER(AW15)="pending approval","Electrical",""),IF(LOWER(AZ15)="pending approval","Fabric","")),_xlpm.ns,_xlfn.TEXTJOIN(", ",TRUE,IF(LOWER(AH15)="not started","Drawing",""),IF(LOWER(AK15)="not started","Veneer/Wood",""),IF(LOWER(AN15)="not started","Marble",""),IF(LOWER(AQ15)="not started","Metal",""),IF(LOWER(AT15)="not started","Mirror",""),IF(LOWER(AW15)="not started","Electrical",""),IF(LOWER(AZ15)="not started","Fabric","")),_xlpm.fab,IF(OR(LOWER(AZ15)="com",LOWER(AZ15)="com pending",LOWER(AZ15)="com received"),"Fabric is "&LOWER(AZ15),""),_xlpm.parts,_xlfn.TEXTJOIN("; ",TRUE,IF(_xlpm.ip<>"","In progress: "&_xlpm.ip,""),IF(_xlpm.pa<>"","Pending approval: "&_xlpm.pa,""),IF(_xlpm.ns<>"","Not started: "&_xlpm.ns,""),_xlpm.fab),_xlpm.deadline,MIN(IF(AND(AH15<>"",LOWER(AH15)<>"approved",LOWER(AH15)<>"n/a",ISNUMBER(AI15)),AI15,1E+99),IF(AND(AK15<>"",LOWER(AK15)<>"approved",LOWER(AK15)<>"n/a",ISNUMBER(AL15)),AL15,1E+99),IF(AND(AN15<>"",LOWER(AN15)<>"approved",LOWER(AN15)<>"n/a",ISNUMBER(AO15)),AO15,1E+99),IF(AND(AQ15<>"",LOWER(AQ15)<>"approved",LOWER(AQ15)<>"n/a",ISNUMBER(AR15)),AR15,1E+99),IF(AND(AT15<>"",LOWER(AT15)<>"approved",LOWER(AT15)<>"n/a",ISNUMBER(AU15)),AU15,1E+99),IF(AND(AW15<>"",LOWER(AW15)<>"approved",LOWER(AW15)<>"n/a",ISNUMBER(AX15)),AX15,1E+99),IF(AND(AZ15<>"",LOWER(AZ15)<>"approved",LOWER(AZ15)<>"n/a",ISNUMBER(BA15)),BA15,1E+99)),_xlpm.sw,IF(AG15="","",IFERROR("SW"&MID(AG15,FIND("/W",AG15)+2,99),"SW "&AG15)),_xlpm.stage&IF(_xlpm.parts="","All development items approved/closed",_xlpm.parts)&IF(AND(_xlpm.parts<>"",_xlpm.deadline<1E+99),"; need approval by "&TEXT(_xlpm.deadline,"d-mmm-yy"),"")&IF(_xlpm.sw<>""," for "&_xlpm.sw,""))) -> READY
A16: =IFERROR(VLOOKUP(E16,'Customer '!$A$4:$D$23,3,FALSE),"") -> RH | B16: NPI | C16: DUNG | E16: RESTORATION HARDWARE_HS | F16: =IFERROR(VLOOKUP(E16,'Customer '!$A$4:$D$28,2,FALSE),"") -> RH | G16: CHICAGO PENDRY | H16: =IF(OR(DetailTracker[[#This Row],[PROJECT NAME (SHORT)]]="",DetailTracker[[#This Row],[CUSTOMER SHORTEN NAME]]=""),"",IF(ISNUMBER(DetailTracker[[#This Row],[BOQ DATE]]),YEAR(DetailTracker[[#This Row],[BOQ DATE]])&"-"&DetailTracker[[#This Row],[CUSTOMER SHORTEN NAME]]&"-"&DetailTracker[[#This Row],[PROJECT NAME (SHORT)]],IF(OR(DetailTracker[[#This Row],[SHIP MONTH FC]]="TBC",DetailTracker[[#This Row],[SHIP MONTH FC]]="Removed"),DetailTracker[[#This Row],[SHIP MONTH FC]]&"-"&DetailTracker[[#This Row],[CUSTOMER SHORTEN NAME]]&"-"&DetailTracker[[#This Row],[PROJECT NAME (SHORT)]],YEAR(TODAY())&"-"&DetailTracker[[#This Row],[CUSTOMER SHORTEN NAME]]&"-"&DetailTracker[[#This Row],[PROJECT NAME (SHORT)]]))) -> 2025-RH-CHICAGO PENDRY | I16: =IF(OR($H16="",$B16=""),0,--(COUNTIFS($H$3:$H16,$H16,$B$3:$B16,$B16)=1)) -> 1 | J16: REMOVED | K16: NEW | L16: 4. Prototype Build | M16: 45828 | P16: US | Q16: IL | V16: 2 | X16: 135705 | Y16: 135705 | Z16: 2026/M10 | AA16: =IF(Z16="","",IF(OR(Z16="TBC",Z16="Removed"),Z16,LEFT(Z16,4))) -> 2026 | AB16: - | AD16: 46116 | AE16: 46116 | AF16: =IF(AD16="","",IF(ISNUMBER(AD16),IF(AND(AD16>='2026 Calendar'!$C$4,AD16<='2026 Calendar'!$E$107),LOOKUP(AD16,'2026 Calendar'!$C$4:$C$107,'2026 Calendar'!$A$4:$A$107),YEAR(AD16-WEEKDAY(AD16,2)+4)&"/W"&TEXT(WEEKNUM(AD16,21),"00")),IF(IFERROR(ISNUMBER(SEARCH("/W",AD16)),FALSE),IF(IFERROR(ISNUMBER(SEARCH("-",AD16)),FALSE),LEFT(AD16,SEARCH("-",AD16)-1),AD16),AD16))) -> 2026/W14 | AG16: =IF(AE16="","",IF(ISNUMBER(AE16),IF(AND(AE16>='2026 Calendar'!$C$4,AE16<='2026 Calendar'!$E$107),LOOKUP(AE16,'2026 Calendar'!$C$4:$C$107,'2026 Calendar'!$A$4:$A$107),YEAR(AE16-WEEKDAY(AE16,2)+4)&"/W"&TEXT(WEEKNUM(AE16,21),"00")),IF(IFERROR(ISNUMBER(SEARCH("/W",AE16)),FALSE),IF(IFERROR(ISNUMBER(SEARCH("-",AE16)),FALSE),MID(AE16,SEARCH("-",AE16)+1,100),AE16),AE16))) -> 2026/W14 | AH16: In Progress | BC16: =IF(J16="","",IF(OR(J16="OB",J16="NOR",J16="FC",J16="PIPELINE"),"Active","Complete")) -> Complete | BD16: Yes | BE16: =IF(UPPER(TRIM(J16))="SHIPPED","READY",_xlfn.LET(_xlpm.stage,IF(B16="","",B16&": "),_xlpm.ip,_xlfn.TEXTJOIN(", ",TRUE,IF(LOWER(AH16)="in progress","Drawing",""),IF(LOWER(AK16)="in progress","Veneer/Wood",""),IF(LOWER(AN16)="in progress","Marble",""),IF(LOWER(AQ16)="in progress","Metal",""),IF(LOWER(AT16)="in progress","Mirror",""),IF(LOWER(AW16)="in progress","Electrical",""),IF(LOWER(AZ16)="in progress","Fabric","")),_xlpm.pa,_xlfn.TEXTJOIN(", ",TRUE,IF(LOWER(AH16)="pending approval","Drawing",""),IF(LOWER(AK16)="pending approval","Veneer/Wood",""),IF(LOWER(AN16)="pending approval","Marble",""),IF(LOWER(AQ16)="pending approval","Metal",""),IF(LOWER(AT16)="pending approval","Mirror",""),IF(LOWER(AW16)="pending approval","Electrical",""),IF(LOWER(AZ16)="pending approval","Fabric","")),_xlpm.ns,_xlfn.TEXTJOIN(", ",TRUE,IF(LOWER(AH16)="not started","Drawing",""),IF(LOWER(AK16)="not started","Veneer/Wood",""),IF(LOWER(AN16)="not started","Marble",""),IF(LOWER(AQ16)="not started","Metal",""),IF(LOWER(AT16)="not started","Mirror",""),IF(LOWER(AW16)="not started","Electrical",""),IF(LOWER(AZ16)="not started","Fabric","")),_xlpm.fab,IF(OR(LOWER(AZ16)="com",LOWER(AZ16)="com pending",LOWER(AZ16)="com received"),"Fabric is "&LOWER(AZ16),""),_xlpm.parts,_xlfn.TEXTJOIN("; ",TRUE,IF(_xlpm.ip<>"","In progress: "&_xlpm.ip,""),IF(_xlpm.pa<>"","Pending approval: "&_xlpm.pa,""),IF(_xlpm.ns<>"","Not started: "&_xlpm.ns,""),_xlpm.fab),_xlpm.deadline,MIN(IF(AND(AH16<>"",LOWER(AH16)<>"approved",LOWER(AH16)<>"n/a",ISNUMBER(AI16)),AI16,1E+99),IF(AND(AK16<>"",LOWER(AK16)<>"approved",LOWER(AK16)<>"n/a",ISNUMBER(AL16)),AL16,1E+99),IF(AND(AN16<>"",LOWER(AN16)<>"approved",LOWER(AN16)<>"n/a",ISNUMBER(AO16)),AO16,1E+99),IF(AND(AQ16<>"",LOWER(AQ16)<>"approved",LOWER(AQ16)<>"n/a",ISNUMBER(AR16)),AR16,1E+99),IF(AND(AT16<>"",LOWER(AT16)<>"approved",LOWER(AT16)<>"n/a",ISNUMBER(AU16)),AU16,1E+99),IF(AND(AW16<>"",LOWER(AW16)<>"approved",LOWER(AW16)<>"n/a",ISNUMBER(AX16)),AX16,1E+99),IF(AND(AZ16<>"",LOWER(AZ16)<>"approved",LOWER(AZ16)<>"n/a",ISNUMBER(BA16)),BA16,1E+99)),_xlpm.sw,IF(AG16="","",IFERROR("SW"&MID(AG16,FIND("/W",AG16)+2,99),"SW "&AG16)),_xlpm.stage&IF(_xlpm.parts="","All development items approved/closed",_xlpm.parts)&IF(AND(_xlpm.parts<>"",_xlpm.deadline<1E+99),"; need approval by "&TEXT(_xlpm.deadline,"d-mmm-yy"),"")&IF(_xlpm.sw<>""," for "&_xlpm.sw,""))) -> NPI: In progress: Drawing for SW14
A17: =IFERROR(VLOOKUP(E17,'Customer '!$A$4:$D$23,3,FALSE),"") -> RH | B17: NPI | C17: DUNG | D17: Sue Bilstad | E17: RESTORATION HARDWARE_HS | F17: =IFERROR(VLOOKUP(E17,'Customer '!$A$4:$D$28,2,FALSE),"") -> RH | G17: CIA O&O GUESTROOMS | H17: =IF(OR(DetailTracker[[#This Row],[PROJECT NAME (SHORT)]]="",DetailTracker[[#This Row],[CUSTOMER SHORTEN NAME]]=""),"",IF(ISNUMBER(DetailTracker[[#This Row],[BOQ DATE]]),YEAR(DetailTracker[[#This Row],[BOQ DATE]])&"-"&DetailTracker[[#This Row],[CUSTOMER SHORTEN NAME]]&"-"&DetailTracker[[#This Row],[PROJECT NAME (SHORT)]],IF(OR(DetailTracker[[#This Row],[SHIP MONTH FC]]="TBC",DetailTracker[[#This Row],[SHIP MONTH FC]]="Removed"),DetailTracker[[#This Row],[SHIP MONTH FC]]&"-"&DetailTracker[[#This Row],[CUSTOMER SHORTEN NAME]]&"-"&DetailTracker[[#This Row],[PROJECT NAME (SHORT)]],YEAR(TODAY())&"-"&DetailTracker[[#This Row],[CUSTOMER SHORTEN NAME]]&"-"&DetailTracker[[#This Row],[PROJECT NAME (SHORT)]]))) -> 2026-RH-CIA O&O GUESTROOMS | I17: =IF(OR($H17="",$B17=""),0,--(COUNTIFS($H$3:$H17,$H17,$B$3:$B17,$B17)=1)) -> 1 | J17: FC | K17: NEW | L17: 4. Prototype Build | P17: US | Q17: CA | R17: 0 | S17: 0 | V17: 12 | X17: 143556.09 | Y17: 143556.09 | Z17: 2027/M07 | AA17: =IF(Z17="","",IF(OR(Z17="TBC",Z17="Removed"),Z17,LEFT(Z17,4))) -> 2027 | AB17: - | AD17: 46206 | AE17: 46213 | AF17: =IF(AD17="","",IF(ISNUMBER(AD17),IF(AND(AD17>='2026 Calendar'!$C$4,AD17<='2026 Calendar'!$E$107),LOOKUP(AD17,'2026 Calendar'!$C$4:$C$107,'2026 Calendar'!$A$4:$A$107),YEAR(AD17-WEEKDAY(AD17,2)+4)&"/W"&TEXT(WEEKNUM(AD17,21),"00")),IF(IFERROR(ISNUMBER(SEARCH("/W",AD17)),FALSE),IF(IFERROR(ISNUMBER(SEARCH("-",AD17)),FALSE),LEFT(AD17,SEARCH("-",AD17)-1),AD17),AD17))) -> 2026/W27 | AG17: =IF(AE17="","",IF(ISNUMBER(AE17),IF(AND(AE17>='2026 Calendar'!$C$4,AE17<='2026 Calendar'!$E$107),LOOKUP(AE17,'2026 Calendar'!$C$4:$C$107,'2026 Calendar'!$A$4:$A$107),YEAR(AE17-WEEKDAY(AE17,2)+4)&"/W"&TEXT(WEEKNUM(AE17,21),"00")),IF(IFERROR(ISNUMBER(SEARCH("/W",AE17)),FALSE),IF(IFERROR(ISNUMBER(SEARCH("-",AE17)),FALSE),MID(AE17,SEARCH("-",AE17)+1,100),AE17),AE17))) -> 2026/W28 | AH17: Approved | AK17: Approved | AN17: Approved | AQ17: Approved | AT17: Approved | AW17: N/A | AZ17: COM | BC17: =IF(J17="","",IF(OR(J17="OB",J17="NOR",J17="FC",J17="PIPELINE"),"Active","Complete")) -> Active | BD17: Yes | BE17: =IF(UPPER(TRIM(J17))="SHIPPED","READY",_xlfn.LET(_xlpm.stage,IF(B17="","",B17&": "),_xlpm.ip,_xlfn.TEXTJOIN(", ",TRUE,IF(LOWER(AH17)="in progress","Drawing",""),IF(LOWER(AK17)="in progress","Veneer/Wood",""),IF(LOWER(AN17)="in progress","Marble",""),IF(LOWER(AQ17)="in progress","Metal",""),IF(LOWER(AT17)="in progress","Mirror",""),IF(LOWER(AW17)="in progress","Electrical",""),IF(LOWER(AZ17)="in progress","Fabric","")),_xlpm.pa,_xlfn.TEXTJOIN(", ",TRUE,IF(LOWER(AH17)="pending approval","Drawing",""),IF(LOWER(AK17)="pending approval","Veneer/Wood",""),IF(LOWER(AN17)="pending approval","Marble",""),IF(LOWER(AQ17)="pending approval","Metal",""),IF(LOWER(AT17)="pending approval","Mirror",""),IF(LOWER(AW17)="pending approval","Electrical",""),IF(LOWER(AZ17)="pending approval","Fabric","")),_xlpm.ns,_xlfn.TEXTJOIN(", ",TRUE,IF(LOWER(AH17)="not started","Drawing",""),IF(LOWER(AK17)="not started","Veneer/Wood",""),IF(LOWER(AN17)="not started","Marble",""),IF(LOWER(AQ17)="not started","Metal",""),IF(LOWER(AT17)="not started","Mirror",""),IF(LOWER(AW17)="not started","Electrical",""),IF(LOWER(AZ17)="not started","Fabric","")),_xlpm.fab,IF(OR(LOWER(AZ17)="com",LOWER(AZ17)="com pending",LOWER(AZ17)="com received"),"Fabric is "&LOWER(AZ17),""),_xlpm.parts,_xlfn.TEXTJOIN("; ",TRUE,IF(_xlpm.ip<>"","In progress: "&_xlpm.ip,""),IF(_xlpm.pa<>"","Pending approval: "&_xlpm.pa,""),IF(_xlpm.ns<>"","Not started: "&_xlpm.ns,""),_xlpm.fab),_xlpm.deadline,MIN(IF(AND(AH17<>"",LOWER(AH17)<>"approved",LOWER(AH17)<>"n/a",ISNUMBER(AI17)),AI17,1E+99),IF(AND(AK17<>"",LOWER(AK17)<>"approved",LOWER(AK17)<>"n/a",ISNUMBER(AL17)),AL17,1E+99),IF(AND(AN17<>"",LOWER(AN17)<>"approved",LOWER(AN17)<>"n/a",ISNUMBER(AO17)),AO17,1E+99),IF(AND(AQ17<>"",LOWER(AQ17)<>"approved",LOWER(AQ17)<>"n/a",ISNUMBER(AR17)),AR17,1E+99),IF(AND(AT17<>"",LOWER(AT17)<>"approved",LOWER(AT17)<>"n/a",ISNUMBER(AU17)),AU17,1E+99),IF(AND(AW17<>"",LOWER(AW17)<>"approved",LOWER(AW17)<>"n/a",ISNUMBER(AX17)),AX17,1E+99),IF(AND(AZ17<>"",LOWER(AZ17)<>"approved",LOWER(AZ17)<>"n/a",ISNUMBER(BA17)),BA17,1E+99)),_xlpm.sw,IF(AG17="","",IFERROR("SW"&MID(AG17,FIND("/W",AG17)+2,99),"SW "&AG17)),_xlpm.stage&IF(_xlpm.parts="","All development items approved/closed",_xlpm.parts)&IF(AND(_xlpm.parts<>"",_xlpm.deadline<1E+99),"; need approval by "&TEXT(_xlpm.deadline,"d-mmm-yy"),"")&IF(_xlpm.sw<>""," for "&_xlpm.sw,""))) -> NPI: Fabric is com for SW28 | BF17: Prototype shipped. Awaiting for PO for mass production
A18: =IFERROR(VLOOKUP(E18,'Customer '!$A$4:$D$23,3,FALSE),"") -> RH | B18: NPI | C18: TU ANH | D18: Sue Bilstad | E18: RESTORATION HARDWARE_HS | F18: =IFERROR(VLOOKUP(E18,'Customer '!$A$4:$D$28,2,FALSE),"") -> RH | G18: HA STUDIO PICO/WILKINS | H18: =IF(OR(DetailTracker[[#This Row],[PROJECT NAME (SHORT)]]="",DetailTracker[[#This Row],[CUSTOMER SHORTEN NAME]]=""),"",IF(ISNUMBER(DetailTracker[[#This Row],[BOQ DATE]]),YEAR(DetailTracker[[#This Row],[BOQ DATE]])&"-"&DetailTracker[[#This Row],[CUSTOMER SHORTEN NAME]]&"-"&DetailTracker[[#This Row],[PROJECT NAME (SHORT)]],IF(OR(DetailTracker[[#This Row],[SHIP MONTH FC]]="TBC",DetailTracker[[#This Row],[SHIP MONTH FC]]="Removed"),DetailTracker[[#This Row],[SHIP MONTH FC]]&"-"&DetailTracker[[#This Row],[CUSTOMER SHORTEN NAME]]&"-"&DetailTracker[[#This Row],[PROJECT NAME (SHORT)]],YEAR(TODAY())&"-"&DetailTracker[[#This Row],[CUSTOMER SHORTEN NAME]]&"-"&DetailTracker[[#This Row],[PROJECT NAME (SHORT)]]))) -> 2026-RH-HA STUDIO PICO/WILKINS | I18: =IF(OR($H18="",$B18=""),0,--(COUNTIFS($H$3:$H18,$H18,$B$3:$B18,$B18)=1)) -> 1 | J18: SHIPPED | K18: NEW | L18: 1. Preliminary Design | M18: 46027 | N18: 46048 | P18: US | Q18: CA | V18: 1 | X18: 12309 | Y18: 12309 | Z18: 2026/M06 | AA18: =IF(Z18="","",IF(OR(Z18="TBC",Z18="Removed"),Z18,LEFT(Z18,4))) -> 2026 | AB18: 46171 | AC18: 46189 | AD18: 46116 | AE18: 46116 | AF18: =IF(AD18="","",IF(ISNUMBER(AD18),IF(AND(AD18>='2026 Calendar'!$C$4,AD18<='2026 Calendar'!$E$107),LOOKUP(AD18,'2026 Calendar'!$C$4:$C$107,'2026 Calendar'!$A$4:$A$107),YEAR(AD18-WEEKDAY(AD18,2)+4)&"/W"&TEXT(WEEKNUM(AD18,21),"00")),IF(IFERROR(ISNUMBER(SEARCH("/W",AD18)),FALSE),IF(IFERROR(ISNUMBER(SEARCH("-",AD18)),FALSE),LEFT(AD18,SEARCH("-",AD18)-1),AD18),AD18))) -> 2026/W14 | AG18: =IF(AE18="","",IF(ISNUMBER(AE18),IF(AND(AE18>='2026 Calendar'!$C$4,AE18<='2026 Calendar'!$E$107),LOOKUP(AE18,'2026 Calendar'!$C$4:$C$107,'2026 Calendar'!$A$4:$A$107),YEAR(AE18-WEEKDAY(AE18,2)+4)&"/W"&TEXT(WEEKNUM(AE18,21),"00")),IF(IFERROR(ISNUMBER(SEARCH("/W",AE18)),FALSE),IF(IFERROR(ISNUMBER(SEARCH("-",AE18)),FALSE),MID(AE18,SEARCH("-",AE18)+1,100),AE18),AE18))) -> 2026/W14 | AH18: Approved | AJ18: 46058 | AK18: Approved | AM18: 46058 | AN18: N/A | AQ18: Approved | AS18: 46058 | AT18: N/A | AW18: N/A | AZ18: N/A | BC18: =IF(J18="","",IF(OR(J18="OB",J18="NOR",J18="FC",J18="PIPELINE"),"Active","Complete")) -> Complete | BD18: Yes | BE18: =IF(UPPER(TRIM(J18))="SHIPPED","READY",_xlfn.LET(_xlpm.stage,IF(B18="","",B18&": "),_xlpm.ip,_xlfn.TEXTJOIN(", ",TRUE,IF(LOWER(AH18)="in progress","Drawing",""),IF(LOWER(AK18)="in progress","Veneer/Wood",""),IF(LOWER(AN18)="in progress","Marble",""),IF(LOWER(AQ18)="in progress","Metal",""),IF(LOWER(AT18)="in progress","Mirror",""),IF(LOWER(AW18)="in progress","Electrical",""),IF(LOWER(AZ18)="in progress","Fabric","")),_xlpm.pa,_xlfn.TEXTJOIN(", ",TRUE,IF(LOWER(AH18)="pending approval","Drawing",""),IF(LOWER(AK18)="pending approval","Veneer/Wood",""),IF(LOWER(AN18)="pending approval","Marble",""),IF(LOWER(AQ18)="pending approval","Metal",""),IF(LOWER(AT18)="pending approval","Mirror",""),IF(LOWER(AW18)="pending approval","Electrical",""),IF(LOWER(AZ18)="pending approval","Fabric","")),_xlpm.ns,_xlfn.TEXTJOIN(", ",TRUE,IF(LOWER(AH18)="not started","Drawing",""),IF(LOWER(AK18)="not started","Veneer/Wood",""),IF(LOWER(AN18)="not started","Marble",""),IF(LOWER(AQ18)="not started","Metal",""),IF(LOWER(AT18)="not started","Mirror",""),IF(LOWER(AW18)="not started","Electrical",""),IF(LOWER(AZ18)="not started","Fabric","")),_xlpm.fab,IF(OR(LOWER(AZ18)="com",LOWER(AZ18)="com pending",LOWER(AZ18)="com received"),"Fabric is "&LOWER(AZ18),""),_xlpm.parts,_xlfn.TEXTJOIN("; ",TRUE,IF(_xlpm.ip<>"","In progress: "&_xlpm.ip,""),IF(_xlpm.pa<>"","Pending approval: "&_xlpm.pa,""),IF(_xlpm.ns<>"","Not started: "&_xlpm.ns,""),_xlpm.fab),_xlpm.deadline,MIN(IF(AND(AH18<>"",LOWER(AH18)<>"approved",LOWER(AH18)<>"n/a",ISNUMBER(AI18)),AI18,1E+99),IF(AND(AK18<>"",LOWER(AK18)<>"approved",LOWER(AK18)<>"n/a",ISNUMBER(AL18)),AL18,1E+99),IF(AND(AN18<>"",LOWER(AN18)<>"approved",LOWER(AN18)<>"n/a",ISNUMBER(AO18)),AO18,1E+99),IF(AND(AQ18<>"",LOWER(AQ18)<>"approved",LOWER(AQ18)<>"n/a",ISNUMBER(AR18)),AR18,1E+99),IF(AND(AT18<>"",LOWER(AT18)<>"approved",LOWER(AT18)<>"n/a",ISNUMBER(AU18)),AU18,1E+99),IF(AND(AW18<>"",LOWER(AW18)<>"approved",LOWER(AW18)<>"n/a",ISNUMBER(AX18)),AX18,1E+99),IF(AND(AZ18<>"",LOWER(AZ18)<>"approved",LOWER(AZ18)<>"n/a",ISNUMBER(BA18)),BA18,1E+99)),_xlpm.sw,IF(AG18="","",IFERROR("SW"&MID(AG18,FIND("/W",AG18)+2,99),"SW "&AG18)),_xlpm.stage&IF(_xlpm.parts="","All development items approved/closed",_xlpm.parts)&IF(AND(_xlpm.parts<>"",_xlpm.deadline<1E+99),"; need approval by "&TEXT(_xlpm.deadline,"d-mmm-yy"),"")&IF(_xlpm.sw<>""," for "&_xlpm.sw,""))) -> READY
A19: =IFERROR(VLOOKUP(E19,'Customer '!$A$4:$D$23,3,FALSE),"") -> RH | B19: NPI | C19: DUY | D19: Sue Bilstad | E19: RESTORATION HARDWARE_HS | F19: =IFERROR(VLOOKUP(E19,'Customer '!$A$4:$D$28,2,FALSE),"") -> RH | G19: HA STUDIO PICO/WILKINS-REODER | H19: =IF(OR(DetailTracker[[#This Row],[PROJECT NAME (SHORT)]]="",DetailTracker[[#This Row],[CUSTOMER SHORTEN NAME]]=""),"",IF(ISNUMBER(DetailTracker[[#This Row],[BOQ DATE]]),YEAR(DetailTracker[[#This Row],[BOQ DATE]])&"-"&DetailTracker[[#This Row],[CUSTOMER SHORTEN NAME]]&"-"&DetailTracker[[#This Row],[PROJECT NAME (SHORT)]],IF(OR(DetailTracker[[#This Row],[SHIP MONTH FC]]="TBC",DetailTracker[[#This Row],[SHIP MONTH FC]]="Removed"),DetailTracker[[#This Row],[SHIP MONTH FC]]&"-"&DetailTracker[[#This Row],[CUSTOMER SHORTEN NAME]]&"-"&DetailTracker[[#This Row],[PROJECT NAME (SHORT)]],YEAR(TODAY())&"-"&DetailTracker[[#This Row],[CUSTOMER SHORTEN NAME]]&"-"&DetailTracker[[#This Row],[PROJECT NAME (SHORT)]]))) -> 2026-RH-HA STUDIO PICO/WILKINS-REODER | I19: =IF(OR($H19="",$B19=""),0,--(COUNTIFS($H$3:$H19,$H19,$B$3:$B19,$B19)=1)) -> 1 | J19: OB | K19: REO | L19: 7. Mass Production | M19: 46227 | N19: 46230 | P19: US | Q19: CA | R19: 0 | S19: 0 | V19: 1 | W19: 20 | X19: 3454 | Y19: 3454 | Z19: 2026/M11 | AA19: =IF(Z19="","",IF(OR(Z19="TBC",Z19="Removed"),Z19,LEFT(Z19,4))) -> 2026 | AD19: 46346 | AE19: 46346 | AF19: =IF(AD19="","",IF(ISNUMBER(AD19),IF(AND(AD19>='2026 Calendar'!$C$4,AD19<='2026 Calendar'!$E$107),LOOKUP(AD19,'2026 Calendar'!$C$4:$C$107,'2026 Calendar'!$A$4:$A$107),YEAR(AD19-WEEKDAY(AD19,2)+4)&"/W"&TEXT(WEEKNUM(AD19,21),"00")),IF(IFERROR(ISNUMBER(SEARCH("/W",AD19)),FALSE),IF(IFERROR(ISNUMBER(SEARCH("-",AD19)),FALSE),LEFT(AD19,SEARCH("-",AD19)-1),AD19),AD19))) -> 2026/W47 | AG19: =IF(AE19="","",IF(ISNUMBER(AE19),IF(AND(AE19>='2026 Calendar'!$C$4,AE19<='2026 Calendar'!$E$107),LOOKUP(AE19,'2026 Calendar'!$C$4:$C$107,'2026 Calendar'!$A$4:$A$107),YEAR(AE19-WEEKDAY(AE19,2)+4)&"/W"&TEXT(WEEKNUM(AE19,21),"00")),IF(IFERROR(ISNUMBER(SEARCH("/W",AE19)),FALSE),IF(IFERROR(ISNUMBER(SEARCH("-",AE19)),FALSE),MID(AE19,SEARCH("-",AE19)+1,100),AE19),AE19))) -> 2026/W47 | AH19: Approved | AJ19: 46058 | AK19: Approved | AM19: 46058 | AN19: N/A | AQ19: Approved | AS19: 46058 | AT19: N/A | AW19: N/A | AZ19: N/A | BC19: =IF(J19="","",IF(OR(J19="OB",J19="NOR",J19="FC",J19="PIPELINE"),"Active","Complete")) -> Active | BD19: Yes | BE19: =IF(UPPER(TRIM(J19))="SHIPPED","READY",_xlfn.LET(_xlpm.stage,IF(B19="","",B19&": "),_xlpm.ip,_xlfn.TEXTJOIN(", ",TRUE,IF(LOWER(AH19)="in progress","Drawing",""),IF(LOWER(AK19)="in progress","Veneer/Wood",""),IF(LOWER(AN19)="in progress","Marble",""),IF(LOWER(AQ19)="in progress","Metal",""),IF(LOWER(AT19)="in progress","Mirror",""),IF(LOWER(AW19)="in progress","Electrical",""),IF(LOWER(AZ19)="in progress","Fabric","")),_xlpm.pa,_xlfn.TEXTJOIN(", ",TRUE,IF(LOWER(AH19)="pending approval","Drawing",""),IF(LOWER(AK19)="pending approval","Veneer/Wood",""),IF(LOWER(AN19)="pending approval","Marble",""),IF(LOWER(AQ19)="pending approval","Metal",""),IF(LOWER(AT19)="pending approval","Mirror",""),IF(LOWER(AW19)="pending approval","Electrical",""),IF(LOWER(AZ19)="pending approval","Fabric","")),_xlpm.ns,_xlfn.TEXTJOIN(", ",TRUE,IF(LOWER(AH19)="not started","Drawing",""),IF(LOWER(AK19)="not started","Veneer/Wood",""),IF(LOWER(AN19)="not started","Marble",""),IF(LOWER(AQ19)="not started","Metal",""),IF(LOWER(AT19)="not started","Mirror",""),IF(LOWER(AW19)="not started","Electrical",""),IF(LOWER(AZ19)="not started","Fabric","")),_xlpm.fab,IF(OR(LOWER(AZ19)="com",LOWER(AZ19)="com pending",LOWER(AZ19)="com received"),"Fabric is "&LOWER(AZ19),""),_xlpm.parts,_xlfn.TEXTJOIN("; ",TRUE,IF(_xlpm.ip<>"","In progress: "&_xlpm.ip,""),IF(_xlpm.pa<>"","Pending approval: "&_xlpm.pa,""),IF(_xlpm.ns<>"","Not started: "&_xlpm.ns,""),_xlpm.fab),_xlpm.deadline,MIN(IF(AND(AH19<>"",LOWER(AH19)<>"approved",LOWER(AH19)<>"n/a",ISNUMBER(AI19)),AI19,1E+99),IF(AND(AK19<>"",LOWER(AK19)<>"approved",LOWER(AK19)<>"n/a",ISNUMBER(AL19)),AL19,1E+99),IF(AND(AN19<>"",LOWER(AN19)<>"approved",LOWER(AN19)<>"n/a",ISNUMBER(AO19)),AO19,1E+99),IF(AND(AQ19<>"",LOWER(AQ19)<>"approved",LOWER(AQ19)<>"n/a",ISNUMBER(AR19)),AR19,1E+99),IF(AND(AT19<>"",LOWER(AT19)<>"approved",LOWER(AT19)<>"n/a",ISNUMBER(AU19)),AU19,1E+99),IF(AND(AW19<>"",LOWER(AW19)<>"approved",LOWER(AW19)<>"n/a",ISNUMBER(AX19)),AX19,1E+99),IF(AND(AZ19<>"",LOWER(AZ19)<>"approved",LOWER(AZ19)<>"n/a",ISNUMBER(BA19)),BA19,1E+99)),_xlpm.sw,IF(AG19="","",IFERROR("SW"&MID(AG19,FIND("/W",AG19)+2,99),"SW "&AG19)),_xlpm.stage&IF(_xlpm.parts="","All development items approved/closed",_xlpm.parts)&IF(AND(_xlpm.parts<>"",_xlpm.deadline<1E+99),"; need approval by "&TEXT(_xlpm.deadline,"d-mmm-yy"),"")&IF(_xlpm.sw<>""," for "&_xlpm.sw,""))) -> NPI: All development items approved/closed for SW47
A20: =IFERROR(VLOOKUP(E20,'Customer '!$A$4:$D$23,3,FALSE),"") -> RH | B20: NPI | C20: DUY | D20: Madison Lay | E20: RESTORATION HARDWARE_HS | F20: =IFERROR(VLOOKUP(E20,'Customer '!$A$4:$D$28,2,FALSE),"") -> RH | G20: NAMA LISBON | H20: =IF(OR(DetailTracker[[#This Row],[PROJECT NAME (SHORT)]]="",DetailTracker[[#This Row],[CUSTOMER SHORTEN NAME]]=""),"",IF(ISNUMBER(DetailTracker[[#This Row],[BOQ DATE]]),YEAR(DetailTracker[[#This Row],[BOQ DATE]])&"-"&DetailTracker[[#This Row],[CUSTOMER SHORTEN NAME]]&"-"&DetailTracker[[#This Row],[PROJECT NAME (SHORT)]],IF(OR(DetailTracker[[#This Row],[SHIP MONTH FC]]="TBC",DetailTracker[[#This Row],[SHIP MONTH FC]]="Removed"),DetailTracker[[#This Row],[SHIP MONTH FC]]&"-"&DetailTracker[[#This Row],[CUSTOMER SHORTEN NAME]]&"-"&DetailTracker[[#This Row],[PROJECT NAME (SHORT)]],YEAR(TODAY())&"-"&DetailTracker[[#This Row],[CUSTOMER SHORTEN NAME]]&"-"&DetailTracker[[#This Row],[PROJECT NAME (SHORT)]]))) -> 2026-RH-NAMA LISBON | I20: =IF(OR($H20="",$B20=""),0,--(COUNTIFS($H$3:$H20,$H20,$B$3:$B20,$B20)=1)) -> 1 | J20: SHIPPED | K20: NEW | L20: 7. Mass Production | M20: 46037 | N20: 46083 | P20: PT | Q20: Portugal | R20: 0 | S20: 0 | V20: 11 | W20: 191 | X20: 202175 | Y20: 74720 | Z20: 2026/M09 | AA20: =IF(Z20="","",IF(OR(Z20="TBC",Z20="Removed"),Z20,LEFT(Z20,4))) -> 2026 | AB20: 46163 | AC20: 46170 | AD20: 46278 | AE20: 46278 | AF20: =IF(AD20="","",IF(ISNUMBER(AD20),IF(AND(AD20>='2026 Calendar'!$C$4,AD20<='2026 Calendar'!$E$107),LOOKUP(AD20,'2026 Calendar'!$C$4:$C$107,'2026 Calendar'!$A$4:$A$107),YEAR(AD20-WEEKDAY(AD20,2)+4)&"/W"&TEXT(WEEKNUM(AD20,21),"00")),IF(IFERROR(ISNUMBER(SEARCH("/W",AD20)),FALSE),IF(IFERROR(ISNUMBER(SEARCH("-",AD20)),FALSE),LEFT(AD20,SEARCH("-",AD20)-1),AD20),AD20))) -> 2026/W37 | AG20: =IF(AE20="","",IF(ISNUMBER(AE20),IF(AND(AE20>='2026 Calendar'!$C$4,AE20<='2026 Calendar'!$E$107),LOOKUP(AE20,'2026 Calendar'!$C$4:$C$107,'2026 Calendar'!$A$4:$A$107),YEAR(AE20-WEEKDAY(AE20,2)+4)&"/W"&TEXT(WEEKNUM(AE20,21),"00")),IF(IFERROR(ISNUMBER(SEARCH("/W",AE20)),FALSE),IF(IFERROR(ISNUMBER(SEARCH("-",AE20)),FALSE),MID(AE20,SEARCH("-",AE20)+1,100),AE20),AE20))) -> 2026/W37 | AH20: Approved | AJ20: 46083 | AK20: Approved | AM20: 46083 | AN20: N/A | AQ20: Approved | AT20: N/A | AW20: N/A | AZ20: N/A | BC20: =IF(J20="","",IF(OR(J20="OB",J20="NOR",J20="FC",J20="PIPELINE"),"Active","Complete")) -> Complete | BD20: Yes | BE20: =IF(UPPER(TRIM(J20))="SHIPPED","READY",_xlfn.LET(_xlpm.stage,IF(B20="","",B20&": "),_xlpm.ip,_xlfn.TEXTJOIN(", ",TRUE,IF(LOWER(AH20)="in progress","Drawing",""),IF(LOWER(AK20)="in progress","Veneer/Wood",""),IF(LOWER(AN20)="in progress","Marble",""),IF(LOWER(AQ20)="in progress","Metal",""),IF(LOWER(AT20)="in progress","Mirror",""),IF(LOWER(AW20)="in progress","Electrical",""),IF(LOWER(AZ20)="in progress","Fabric","")),_xlpm.pa,_xlfn.TEXTJOIN(", ",TRUE,IF(LOWER(AH20)="pending approval","Drawing",""),IF(LOWER(AK20)="pending approval","Veneer/Wood",""),IF(LOWER(AN20)="pending approval","Marble",""),IF(LOWER(AQ20)="pending approval","Metal",""),IF(LOWER(AT20)="pending approval","Mirror",""),IF(LOWER(AW20)="pending approval","Electrical",""),IF(LOWER(AZ20)="pending approval","Fabric","")),_xlpm.ns,_xlfn.TEXTJOIN(", ",TRUE,IF(LOWER(AH20)="not started","Drawing",""),IF(LOWER(AK20)="not started","Veneer/Wood",""),IF(LOWER(AN20)="not started","Marble",""),IF(LOWER(AQ20)="not started","Metal",""),IF(LOWER(AT20)="not started","Mirror",""),IF(LOWER(AW20)="not started","Electrical",""),IF(LOWER(AZ20)="not started","Fabric","")),_xlpm.fab,IF(OR(LOWER(AZ20)="com",LOWER(AZ20)="com pending",LOWER(AZ20)="com received"),"Fabric is "&LOWER(AZ20),""),_xlpm.parts,_xlfn.TEXTJOIN("; ",TRUE,IF(_xlpm.ip<>"","In progress: "&_xlpm.ip,""),IF(_xlpm.pa<>"","Pending approval: "&_xlpm.pa,""),IF(_xlpm.ns<>"","Not started: "&_xlpm.ns,""),_xlpm.fab),_xlpm.deadline,MIN(IF(AND(AH20<>"",LOWER(AH20)<>"approved",LOWER(AH20)<>"n/a",ISNUMBER(AI20)),AI20,1E+99),IF(AND(AK20<>"",LOWER(AK20)<>"approved",LOWER(AK20)<>"n/a",ISNUMBER(AL20)),AL20,1E+99),IF(AND(AN20<>"",LOWER(AN20)<>"approved",LOWER(AN20)<>"n/a",ISNUMBER(AO20)),AO20,1E+99),IF(AND(AQ20<>"",LOWER(AQ20)<>"approved",LOWER(AQ20)<>"n/a",ISNUMBER(AR20)),AR20,1E+99),IF(AND(AT20<>"",LOWER(AT20)<>"approved",LOWER(AT20)<>"n/a",ISNUMBER(AU20)),AU20,1E+99),IF(AND(AW20<>"",LOWER(AW20)<>"approved",LOWER(AW20)<>"n/a",ISNUMBER(AX20)),AX20,1E+99),IF(AND(AZ20<>"",LOWER(AZ20)<>"approved",LOWER(AZ20)<>"n/a",ISNUMBER(BA20)),BA20,1E+99)),_xlpm.sw,IF(AG20="","",IFERROR("SW"&MID(AG20,FIND("/W",AG20)+2,99),"SW "&AG20)),_xlpm.stage&IF(_xlpm.parts="","All development items approved/closed",_xlpm.parts)&IF(AND(_xlpm.parts<>"",_xlpm.deadline<1E+99),"; need approval by "&TEXT(_xlpm.deadline,"d-mmm-yy"),"")&IF(_xlpm.sw<>""," for "&_xlpm.sw,""))) -> READY
A21: =IFERROR(VLOOKUP(E21,'Customer '!$A$4:$D$23,3,FALSE),"") -> RH | B21: NPI | C21: DUY | D21: Madison Lay | E21: RESTORATION HARDWARE_HS | F21: =IFERROR(VLOOKUP(E21,'Customer '!$A$4:$D$28,2,FALSE),"") -> RH | G21: NAMA LISBON | H21: =IF(OR(DetailTracker[[#This Row],[PROJECT NAME (SHORT)]]="",DetailTracker[[#This Row],[CUSTOMER SHORTEN NAME]]=""),"",IF(ISNUMBER(DetailTracker[[#This Row],[BOQ DATE]]),YEAR(DetailTracker[[#This Row],[BOQ DATE]])&"-"&DetailTracker[[#This Row],[CUSTOMER SHORTEN NAME]]&"-"&DetailTracker[[#This Row],[PROJECT NAME (SHORT)]],IF(OR(DetailTracker[[#This Row],[SHIP MONTH FC]]="TBC",DetailTracker[[#This Row],[SHIP MONTH FC]]="Removed"),DetailTracker[[#This Row],[SHIP MONTH FC]]&"-"&DetailTracker[[#This Row],[CUSTOMER SHORTEN NAME]]&"-"&DetailTracker[[#This Row],[PROJECT NAME (SHORT)]],YEAR(TODAY())&"-"&DetailTracker[[#This Row],[CUSTOMER SHORTEN NAME]]&"-"&DetailTracker[[#This Row],[PROJECT NAME (SHORT)]]))) -> 2026-RH-NAMA LISBON | I21: =IF(OR($H21="",$B21=""),0,--(COUNTIFS($H$3:$H21,$H21,$B$3:$B21,$B21)=1)) -> 0 | J21: OB | K21: NEW | L21: 7. Mass Production | M21: 46037 | N21: 46083 | P21: PT | Q21: Portugal | R21: 0 | S21: 0 | V21: 11 | W21: 271 | X21: 202175 | Y21: 127455 | Z21: 2026/M10 | AA21: =IF(Z21="","",IF(OR(Z21="TBC",Z21="Removed"),Z21,LEFT(Z21,4))) -> 2026 | AB21: 46163 | AC21: 46170 | AD21: 46325 | AE21: 46325 | AF21: =IF(AD21="","",IF(ISNUMBER(AD21),IF(AND(AD21>='2026 Calendar'!$C$4,AD21<='2026 Calendar'!$E$107),LOOKUP(AD21,'2026 Calendar'!$C$4:$C$107,'2026 Calendar'!$A$4:$A$107),YEAR(AD21-WEEKDAY(AD21,2)+4)&"/W"&TEXT(WEEKNUM(AD21,21),"00")),IF(IFERROR(ISNUMBER(SEARCH("/W",AD21)),FALSE),IF(IFERROR(ISNUMBER(SEARCH("-",AD21)),FALSE),LEFT(AD21,SEARCH("-",AD21)-1),AD21),AD21))) -> 2026/W44 | AG21: =IF(AE21="","",IF(ISNUMBER(AE21),IF(AND(AE21>='2026 Calendar'!$C$4,AE21<='2026 Calendar'!$E$107),LOOKUP(AE21,'2026 Calendar'!$C$4:$C$107,'2026 Calendar'!$A$4:$A$107),YEAR(AE21-WEEKDAY(AE21,2)+4)&"/W"&TEXT(WEEKNUM(AE21,21),"00")),IF(IFERROR(ISNUMBER(SEARCH("/W",AE21)),FALSE),IF(IFERROR(ISNUMBER(SEARCH("-",AE21)),FALSE),MID(AE21,SEARCH("-",AE21)+1,100),AE21),AE21))) -> 2026/W44 | AH21: Approved | AJ21: 46083 | AK21: Approved | AM21: 46083 | AN21: N/A | AQ21: Approved | AT21: N/A | AW21: N/A | AZ21: N/A | BC21: =IF(J21="","",IF(OR(J21="OB",J21="NOR",J21="FC",J21="PIPELINE"),"Active","Complete")) -> Active | BD21: Yes | BE21: =IF(UPPER(TRIM(J21))="SHIPPED","READY",_xlfn.LET(_xlpm.stage,IF(B21="","",B21&": "),_xlpm.ip,_xlfn.TEXTJOIN(", ",TRUE,IF(LOWER(AH21)="in progress","Drawing",""),IF(LOWER(AK21)="in progress","Veneer/Wood",""),IF(LOWER(AN21)="in progress","Marble",""),IF(LOWER(AQ21)="in progress","Metal",""),IF(LOWER(AT21)="in progress","Mirror",""),IF(LOWER(AW21)="in progress","Electrical",""),IF(LOWER(AZ21)="in progress","Fabric","")),_xlpm.pa,_xlfn.TEXTJOIN(", ",TRUE,IF(LOWER(AH21)="pending approval","Drawing",""),IF(LOWER(AK21)="pending approval","Veneer/Wood",""),IF(LOWER(AN21)="pending approval","Marble",""),IF(LOWER(AQ21)="pending approval","Metal",""),IF(LOWER(AT21)="pending approval","Mirror",""),IF(LOWER(AW21)="pending approval","Electrical",""),IF(LOWER(AZ21)="pending approval","Fabric","")),_xlpm.ns,_xlfn.TEXTJOIN(", ",TRUE,IF(LOWER(AH21)="not started","Drawing",""),IF(LOWER(AK21)="not started","Veneer/Wood",""),IF(LOWER(AN21)="not started","Marble",""),IF(LOWER(AQ21)="not started","Metal",""),IF(LOWER(AT21)="not started","Mirror",""),IF(LOWER(AW21)="not started","Electrical",""),IF(LOWER(AZ21)="not started","Fabric","")),_xlpm.fab,IF(OR(LOWER(AZ21)="com",LOWER(AZ21)="com pending",LOWER(AZ21)="com received"),"Fabric is "&LOWER(AZ21),""),_xlpm.parts,_xlfn.TEXTJOIN("; ",TRUE,IF(_xlpm.ip<>"","In progress: "&_xlpm.ip,""),IF(_xlpm.pa<>"","Pending approval: "&_xlpm.pa,""),IF(_xlpm.ns<>"","Not started: "&_xlpm.ns,""),_xlpm.fab),_xlpm.deadline,MIN(IF(AND(AH21<>"",LOWER(AH21)<>"approved",LOWER(AH21)<>"n/a",ISNUMBER(AI21)),AI21,1E+99),IF(AND(AK21<>"",LOWER(AK21)<>"approved",LOWER(AK21)<>"n/a",ISNUMBER(AL21)),AL21,1E+99),IF(AND(AN21<>"",LOWER(AN21)<>"approved",LOWER(AN21)<>"n/a",ISNUMBER(AO21)),AO21,1E+99),IF(AND(AQ21<>"",LOWER(AQ21)<>"approved",LOWER(AQ21)<>"n/a",ISNUMBER(AR21)),AR21,1E+99),IF(AND(AT21<>"",LOWER(AT21)<>"approved",LOWER(AT21)<>"n/a",ISNUMBER(AU21)),AU21,1E+99),IF(AND(AW21<>"",LOWER(AW21)<>"approved",LOWER(AW21)<>"n/a",ISNUMBER(AX21)),AX21,1E+99),IF(AND(AZ21<>"",LOWER(AZ21)<>"approved",LOWER(AZ21)<>"n/a",ISNUMBER(BA21)),BA21,1E+99)),_xlpm.sw,IF(AG21="","",IFERROR("SW"&MID(AG21,FIND("/W",AG21)+2,99),"SW "&AG21)),_xlpm.stage&IF(_xlpm.parts="","All development items approved/closed",_xlpm.parts)&IF(AND(_xlpm.parts<>"",_xlpm.deadline<1E+99),"; need approval by "&TEXT(_xlpm.deadline,"d-mmm-yy"),"")&IF(_xlpm.sw<>""," for "&_xlpm.sw,""))) -> NPI: All development items approved/closed for SW44
A22: =IFERROR(VLOOKUP(E22,'Customer '!$A$4:$D$23,3,FALSE),"") -> RH | B22: NPI | C22: DUY | D22: Madison Lay | E22: RESTORATION HARDWARE_HS | F22: =IFERROR(VLOOKUP(E22,'Customer '!$A$4:$D$28,2,FALSE),"") -> RH | G22: NAMA LISBON-PUBLIC SPACE | H22: =IF(OR(DetailTracker[[#This Row],[PROJECT NAME (SHORT)]]="",DetailTracker[[#This Row],[CUSTOMER SHORTEN NAME]]=""),"",IF(ISNUMBER(DetailTracker[[#This Row],[BOQ DATE]]),YEAR(DetailTracker[[#This Row],[BOQ DATE]])&"-"&DetailTracker[[#This Row],[CUSTOMER SHORTEN NAME]]&"-"&DetailTracker[[#This Row],[PROJECT NAME (SHORT)]],IF(OR(DetailTracker[[#This Row],[SHIP MONTH FC]]="TBC",DetailTracker[[#This Row],[SHIP MONTH FC]]="Removed"),DetailTracker[[#This Row],[SHIP MONTH FC]]&"-"&DetailTracker[[#This Row],[CUSTOMER SHORTEN NAME]]&"-"&DetailTracker[[#This Row],[PROJECT NAME (SHORT)]],YEAR(TODAY())&"-"&DetailTracker[[#This Row],[CUSTOMER SHORTEN NAME]]&"-"&DetailTracker[[#This Row],[PROJECT NAME (SHORT)]]))) -> 2026-RH-NAMA LISBON-PUBLIC SPACE | I22: =IF(OR($H22="",$B22=""),0,--(COUNTIFS($H$3:$H22,$H22,$B$3:$B22,$B22)=1)) -> 1 | J22: NOR | K22: NEW | L22: 2. Product & Process Dev | M22: 46297 | N22: Pending PO | P22: PT | Q22: Portugal | R22: 1 | S22: 1 | V22: 1 | W22: 1 | X22: 2190.15 | Y22: 2190.15 | Z22: 2027/M01 | AA22: =IF(Z22="","",IF(OR(Z22="TBC",Z22="Removed"),Z22,LEFT(Z22,4))) -> 2027 | AB22: 46163 | AC22: 46170 | AD22: 46409 | AE22: 46409 | AF22: =IF(AD22="","",IF(ISNUMBER(AD22),IF(AND(AD22>='2026 Calendar'!$C$4,AD22<='2026 Calendar'!$E$107),LOOKUP(AD22,'2026 Calendar'!$C$4:$C$107,'2026 Calendar'!$A$4:$A$107),YEAR(AD22-WEEKDAY(AD22,2)+4)&"/W"&TEXT(WEEKNUM(AD22,21),"00")),IF(IFERROR(ISNUMBER(SEARCH("/W",AD22)),FALSE),IF(IFERROR(ISNUMBER(SEARCH("-",AD22)),FALSE),LEFT(AD22,SEARCH("-",AD22)-1),AD22),AD22))) -> 2027/W04 | AG22: =IF(AE22="","",IF(ISNUMBER(AE22),IF(AND(AE22>='2026 Calendar'!$C$4,AE22<='2026 Calendar'!$E$107),LOOKUP(AE22,'2026 Calendar'!$C$4:$C$107,'2026 Calendar'!$A$4:$A$107),YEAR(AE22-WEEKDAY(AE22,2)+4)&"/W"&TEXT(WEEKNUM(AE22,21),"00")),IF(IFERROR(ISNUMBER(SEARCH("/W",AE22)),FALSE),IF(IFERROR(ISNUMBER(SEARCH("-",AE22)),FALSE),MID(AE22,SEARCH("-",AE22)+1,100),AE22),AE22))) -> 2027/W04 | AH22: Pending Approval | AI22: 46311 | AK22: Pending Approval | AL22: 46311 | AN22: N/A | AQ22: N/A | AT22: N/A | AW22: In Progress | AZ22: N/A | BC22: =IF(J22="","",IF(OR(J22="OB",J22="NOR",J22="FC",J22="PIPELINE"),"Active","Complete")) -> Active | BD22: Yes | BE22: =IF(UPPER(TRIM(J22))="SHIPPED","READY",_xlfn.LET(_xlpm.stage,IF(B22="","",B22&": "),_xlpm.ip,_xlfn.TEXTJOIN(", ",TRUE,IF(LOWER(AH22)="in progress","Drawing",""),IF(LOWER(AK22)="in progress","Veneer/Wood",""),IF(LOWER(AN22)="in progress","Marble",""),IF(LOWER(AQ22)="in progress","Metal",""),IF(LOWER(AT22)="in progress","Mirror",""),IF(LOWER(AW22)="in progress","Electrical",""),IF(LOWER(AZ22)="in progress","Fabric","")),_xlpm.pa,_xlfn.TEXTJOIN(", ",TRUE,IF(LOWER(AH22)="pending approval","Drawing",""),IF(LOWER(AK22)="pending approval","Veneer/Wood",""),IF(LOWER(AN22)="pending approval","Marble",""),IF(LOWER(AQ22)="pending approval","Metal",""),IF(LOWER(AT22)="pending approval","Mirror",""),IF(LOWER(AW22)="pending approval","Electrical",""),IF(LOWER(AZ22)="pending approval","Fabric","")),_xlpm.ns,_xlfn.TEXTJOIN(", ",TRUE,IF(LOWER(AH22)="not started","Drawing",""),IF(LOWER(AK22)="not started","Veneer/Wood",""),IF(LOWER(AN22)="not started","Marble",""),IF(LOWER(AQ22)="not started","Metal",""),IF(LOWER(AT22)="not started","Mirror",""),IF(LOWER(AW22)="not started","Electrical",""),IF(LOWER(AZ22)="not started","Fabric","")),_xlpm.fab,IF(OR(LOWER(AZ22)="com",LOWER(AZ22)="com pending",LOWER(AZ22)="com received"),"Fabric is "&LOWER(AZ22),""),_xlpm.parts,_xlfn.TEXTJOIN("; ",TRUE,IF(_xlpm.ip<>"","In progress: "&_xlpm.ip,""),IF(_xlpm.pa<>"","Pending approval: "&_xlpm.pa,""),IF(_xlpm.ns<>"","Not started: "&_xlpm.ns,""),_xlpm.fab),_xlpm.deadline,MIN(IF(AND(AH22<>"",LOWER(AH22)<>"approved",LOWER(AH22)<>"n/a",ISNUMBER(AI22)),AI22,1E+99),IF(AND(AK22<>"",LOWER(AK22)<>"approved",LOWER(AK22)<>"n/a",ISNUMBER(AL22)),AL22,1E+99),IF(AND(AN22<>"",LOWER(AN22)<>"approved",LOWER(AN22)<>"n/a",ISNUMBER(AO22)),AO22,1E+99),IF(AND(AQ22<>"",LOWER(AQ22)<>"approved",LOWER(AQ22)<>"n/a",ISNUMBER(AR22)),AR22,1E+99),IF(AND(AT22<>"",LOWER(AT22)<>"approved",LOWER(AT22)<>"n/a",ISNUMBER(AU22)),AU22,1E+99),IF(AND(AW22<>"",LOWER(AW22)<>"approved",LOWER(AW22)<>"n/a",ISNUMBER(AX22)),AX22,1E+99),IF(AND(AZ22<>"",LOWER(AZ22)<>"approved",LOWER(AZ22)<>"n/a",ISNUMBER(BA22)),BA22,1E+99)),_xlpm.sw,IF(AG22="","",IFERROR("SW"&MID(AG22,FIND("/W",AG22)+2,99),"SW "&AG22)),_xlpm.stage&IF(_xlpm.parts="","All development items approved/closed",_xlpm.parts)&IF(AND(_xlpm.parts<>"",_xlpm.deadline<1E+99),"; need approval by "&TEXT(_xlpm.deadline,"d-mmm-yy"),"")&IF(_xlpm.sw<>""," for "&_xlpm.sw,""))) -> NPI: In progress: Electrical; Pending approval: Drawing, Veneer/Wood; need approval by 16-Oct-26 for SW04 | BF22: Need PO this week WK42
A23: =IFERROR(VLOOKUP(E23,'Customer '!$A$4:$D$23,3,FALSE),"") -> RH | B23: NPI | C23: TRINH | E23: RESTORATION HARDWARE_HS | F23: =IFERROR(VLOOKUP(E23,'Customer '!$A$4:$D$28,2,FALSE),"") -> RH | G23: RANCHO VALENCIA | H23: =IF(OR(DetailTracker[[#This Row],[PROJECT NAME (SHORT)]]="",DetailTracker[[#This Row],[CUSTOMER SHORTEN NAME]]=""),"",IF(ISNUMBER(DetailTracker[[#This Row],[BOQ DATE]]),YEAR(DetailTracker[[#This Row],[BOQ DATE]])&"-"&DetailTracker[[#This Row],[CUSTOMER SHORTEN NAME]]&"-"&DetailTracker[[#This Row],[PROJECT NAME (SHORT)]],IF(OR(DetailTracker[[#This Row],[SHIP MONTH FC]]="TBC",DetailTracker[[#This Row],[SHIP MONTH FC]]="Removed"),DetailTracker[[#This Row],[SHIP MONTH FC]]&"-"&DetailTracker[[#This Row],[CUSTOMER SHORTEN NAME]]&"-"&DetailTracker[[#This Row],[PROJECT NAME (SHORT)]],YEAR(TODAY())&"-"&DetailTracker[[#This Row],[CUSTOMER SHORTEN NAME]]&"-"&DetailTracker[[#This Row],[PROJECT NAME (SHORT)]]))) -> 2026-RH-RANCHO VALENCIA | I23: =IF(OR($H23="",$B23=""),0,--(COUNTIFS($H$3:$H23,$H23,$B$3:$B23,$B23)=1)) -> 1 | J23: PIPELINE | K23: NEW | L23: 2. Product & Process Dev | M23: 46029 | N23: - | P23: US | Q23: CA | R23: TBC | S23: TBC | V23: 1 | X23: 14520 | Y23: 14520 | Z23: TBC | AA23: =IF(Z23="","",IF(OR(Z23="TBC",Z23="Removed"),Z23,LEFT(Z23,4))) -> TBC | AB23: - | AD23: TBC | AE23: TBC | AF23: =IF(AD23="","",IF(ISNUMBER(AD23),IF(AND(AD23>='2026 Calendar'!$C$4,AD23<='2026 Calendar'!$E$107),LOOKUP(AD23,'2026 Calendar'!$C$4:$C$107,'2026 Calendar'!$A$4:$A$107),YEAR(AD23-WEEKDAY(AD23,2)+4)&"/W"&TEXT(WEEKNUM(AD23,21),"00")),IF(IFERROR(ISNUMBER(SEARCH("/W",AD23)),FALSE),IF(IFERROR(ISNUMBER(SEARCH("-",AD23)),FALSE),LEFT(AD23,SEARCH("-",AD23)-1),AD23),AD23))) -> TBC | AG23: =IF(AE23="","",IF(ISNUMBER(AE23),IF(AND(AE23>='2026 Calendar'!$C$4,AE23<='2026 Calendar'!$E$107),LOOKUP(AE23,'2026 Calendar'!$C$4:$C$107,'2026 Calendar'!$A$4:$A$107),YEAR(AE23-WEEKDAY(AE23,2)+4)&"/W"&TEXT(WEEKNUM(AE23,21),"00")),IF(IFERROR(ISNUMBER(SEARCH("/W",AE23)),FALSE),IF(IFERROR(ISNUMBER(SEARCH("-",AE23)),FALSE),MID(AE23,SEARCH("-",AE23)+1,100),AE23),AE23))) -> TBC | AH23: Pending Approval | AK23: Approved | AN23: N/A | AQ23: N/A | AT23: N/A | AW23: N/A | AZ23: COM | BC23: =IF(J23="","",IF(OR(J23="OB",J23="NOR",J23="FC",J23="PIPELINE"),"Active","Complete")) -> Active | BD23: Yes | BE23: =IF(UPPER(TRIM(J23))="SHIPPED","READY",_xlfn.LET(_xlpm.stage,IF(B23="","",B23&": "),_xlpm.ip,_xlfn.TEXTJOIN(", ",TRUE,IF(LOWER(AH23)="in progress","Drawing",""),IF(LOWER(AK23)="in progress","Veneer/Wood",""),IF(LOWER(AN23)="in progress","Marble",""),IF(LOWER(AQ23)="in progress","Metal",""),IF(LOWER(AT23)="in progress","Mirror",""),IF(LOWER(AW23)="in progress","Electrical",""),IF(LOWER(AZ23)="in progress","Fabric","")),_xlpm.pa,_xlfn.TEXTJOIN(", ",TRUE,IF(LOWER(AH23)="pending approval","Drawing",""),IF(LOWER(AK23)="pending approval","Veneer/Wood",""),IF(LOWER(AN23)="pending approval","Marble",""),IF(LOWER(AQ23)="pending approval","Metal",""),IF(LOWER(AT23)="pending approval","Mirror",""),IF(LOWER(AW23)="pending approval","Electrical",""),IF(LOWER(AZ23)="pending approval","Fabric","")),_xlpm.ns,_xlfn.TEXTJOIN(", ",TRUE,IF(LOWER(AH23)="not started","Drawing",""),IF(LOWER(AK23)="not started","Veneer/Wood",""),IF(LOWER(AN23)="not started","Marble",""),IF(LOWER(AQ23)="not started","Metal",""),IF(LOWER(AT23)="not started","Mirror",""),IF(LOWER(AW23)="not started","Electrical",""),IF(LOWER(AZ23)="not started","Fabric","")),_xlpm.fab,IF(OR(LOWER(AZ23)="com",LOWER(AZ23)="com pending",LOWER(AZ23)="com received"),"Fabric is "&LOWER(AZ23),""),_xlpm.parts,_xlfn.TEXTJOIN("; ",TRUE,IF(_xlpm.ip<>"","In progress: "&_xlpm.ip,""),IF(_xlpm.pa<>"","Pending approval: "&_xlpm.pa,""),IF(_xlpm.ns<>"","Not started: "&_xlpm.ns,""),_xlpm.fab),_xlpm.deadline,MIN(IF(AND(AH23<>"",LOWER(AH23)<>"approved",LOWER(AH23)<>"n/a",ISNUMBER(AI23)),AI23,1E+99),IF(AND(AK23<>"",LOWER(AK23)<>"approved",LOWER(AK23)<>"n/a",ISNUMBER(AL23)),AL23,1E+99),IF(AND(AN23<>"",LOWER(AN23)<>"approved",LOWER(AN23)<>"n/a",ISNUMBER(AO23)),AO23,1E+99),IF(AND(AQ23<>"",LOWER(AQ23)<>"approved",LOWER(AQ23)<>"n/a",ISNUMBER(AR23)),AR23,1E+99),IF(AND(AT23<>"",LOWER(AT23)<>"approved",LOWER(AT23)<>"n/a",ISNUMBER(AU23)),AU23,1E+99),IF(AND(AW23<>"",LOWER(AW23)<>"approved",LOWER(AW23)<>"n/a",ISNUMBER(AX23)),AX23,1E+99),IF(AND(AZ23<>"",LOWER(AZ23)<>"approved",LOWER(AZ23)<>"n/a",ISNUMBER(BA23)),BA23,1E+99)),_xlpm.sw,IF(AG23="","",IFERROR("SW"&MID(AG23,FIND("/W",AG23)+2,99),"SW "&AG23)),_xlpm.stage&IF(_xlpm.parts="","All development items approved/closed",_xlpm.parts)&IF(AND(_xlpm.parts<>"",_xlpm.deadline<1E+99),"; need approval by "&TEXT(_xlpm.deadline,"d-mmm-yy"),"")&IF(_xlpm.sw<>""," for "&_xlpm.sw,""))) -> NPI: Pending approval: Drawing; Fabric is com for SW TBC
A24: =IFERROR(VLOOKUP(E24,'Customer '!$A$4:$D$23,3,FALSE),"") -> RH | B24: NPI | C24: THU | D24: Sue Bilstad | E24: RESTORATION HARDWARE_HS | F24: =IFERROR(VLOOKUP(E24,'Customer '!$A$4:$D$28,2,FALSE),"") -> RH | G24: RH CONTRACT (LARA CHAIR 25) | H24: =IF(OR(DetailTracker[[#This Row],[PROJECT NAME (SHORT)]]="",DetailTracker[[#This Row],[CUSTOMER SHORTEN NAME]]=""),"",IF(ISNUMBER(DetailTracker[[#This Row],[BOQ DATE]]),YEAR(DetailTracker[[#This Row],[BOQ DATE]])&"-"&DetailTracker[[#This Row],[CUSTOMER SHORTEN NAME]]&"-"&DetailTracker[[#This Row],[PROJECT NAME (SHORT)]],IF(OR(DetailTracker[[#This Row],[SHIP MONTH FC]]="TBC",DetailTracker[[#This Row],[SHIP MONTH FC]]="Removed"),DetailTracker[[#This Row],[SHIP MONTH FC]]&"-"&DetailTracker[[#This Row],[CUSTOMER SHORTEN NAME]]&"-"&DetailTracker[[#This Row],[PROJECT NAME (SHORT)]],YEAR(TODAY())&"-"&DetailTracker[[#This Row],[CUSTOMER SHORTEN NAME]]&"-"&DetailTracker[[#This Row],[PROJECT NAME (SHORT)]]))) -> 2026-RH-RH CONTRACT (LARA CHAIR 25) | I24: =IF(OR($H24="",$B24=""),0,--(COUNTIFS($H$3:$H24,$H24,$B$3:$B24,$B24)=1)) -> 1 | J24: SHIPPED | K24: REO | L24: 8. Shipment | N24: 46034 | P24: US | Q24: CA | V24: 1 | X24: 4200 | Y24: 4200 | Z24: 2026/M03 | AA24: =IF(Z24="","",IF(OR(Z24="TBC",Z24="Removed"),Z24,LEFT(Z24,4))) -> 2026 | AB24: 2026/W13 | AD24: 46116 | AE24: 46116 | AF24: =IF(AD24="","",IF(ISNUMBER(AD24),IF(AND(AD24>='2026 Calendar'!$C$4,AD24<='2026 Calendar'!$E$107),LOOKUP(AD24,'2026 Calendar'!$C$4:$C$107,'2026 Calendar'!$A$4:$A$107),YEAR(AD24-WEEKDAY(AD24,2)+4)&"/W"&TEXT(WEEKNUM(AD24,21),"00")),IF(IFERROR(ISNUMBER(SEARCH("/W",AD24)),FALSE),IF(IFERROR(ISNUMBER(SEARCH("-",AD24)),FALSE),LEFT(AD24,SEARCH("-",AD24)-1),AD24),AD24))) -> 2026/W14 | AG24: =IF(AE24="","",IF(ISNUMBER(AE24),IF(AND(AE24>='2026 Calendar'!$C$4,AE24<='2026 Calendar'!$E$107),LOOKUP(AE24,'2026 Calendar'!$C$4:$C$107,'2026 Calendar'!$A$4:$A$107),YEAR(AE24-WEEKDAY(AE24,2)+4)&"/W"&TEXT(WEEKNUM(AE24,21),"00")),IF(IFERROR(ISNUMBER(SEARCH("/W",AE24)),FALSE),IF(IFERROR(ISNUMBER(SEARCH("-",AE24)),FALSE),MID(AE24,SEARCH("-",AE24)+1,100),AE24),AE24))) -> 2026/W14 | AH24: Approved | AK24: Approved | AN24: N/A | AQ24: N/A | AT24: N/A | AW24: N/A | AZ24: COM | BC24: =IF(J24="","",IF(OR(J24="OB",J24="NOR",J24="FC",J24="PIPELINE"),"Active","Complete")) -> Complete | BD24: Yes | BE24: =IF(UPPER(TRIM(J24))="SHIPPED","READY",_xlfn.LET(_xlpm.stage,IF(B24="","",B24&": "),_xlpm.ip,_xlfn.TEXTJOIN(", ",TRUE,IF(LOWER(AH24)="in progress","Drawing",""),IF(LOWER(AK24)="in progress","Veneer/Wood",""),IF(LOWER(AN24)="in progress","Marble",""),IF(LOWER(AQ24)="in progress","Metal",""),IF(LOWER(AT24)="in progress","Mirror",""),IF(LOWER(AW24)="in progress","Electrical",""),IF(LOWER(AZ24)="in progress","Fabric","")),_xlpm.pa,_xlfn.TEXTJOIN(", ",TRUE,IF(LOWER(AH24)="pending approval","Drawing",""),IF(LOWER(AK24)="pending approval","Veneer/Wood",""),IF(LOWER(AN24)="pending approval","Marble",""),IF(LOWER(AQ24)="pending approval","Metal",""),IF(LOWER(AT24)="pending approval","Mirror",""),IF(LOWER(AW24)="pending approval","Electrical",""),IF(LOWER(AZ24)="pending approval","Fabric","")),_xlpm.ns,_xlfn.TEXTJOIN(", ",TRUE,IF(LOWER(AH24)="not started","Drawing",""),IF(LOWER(AK24)="not started","Veneer/Wood",""),IF(LOWER(AN24)="not started","Marble",""),IF(LOWER(AQ24)="not started","Metal",""),IF(LOWER(AT24)="not started","Mirror",""),IF(LOWER(AW24)="not started","Electrical",""),IF(LOWER(AZ24)="not started","Fabric","")),_xlpm.fab,IF(OR(LOWER(AZ24)="com",LOWER(AZ24)="com pending",LOWER(AZ24)="com received"),"Fabric is "&LOWER(AZ24),""),_xlpm.parts,_xlfn.TEXTJOIN("; ",TRUE,IF(_xlpm.ip<>"","In progress: "&_xlpm.ip,""),IF(_xlpm.pa<>"","Pending approval: "&_xlpm.pa,""),IF(_xlpm.ns<>"","Not started: "&_xlpm.ns,""),_xlpm.fab),_xlpm.deadline,MIN(IF(AND(AH24<>"",LOWER(AH24)<>"approved",LOWER(AH24)<>"n/a",ISNUMBER(AI24)),AI24,1E+99),IF(AND(AK24<>"",LOWER(AK24)<>"approved",LOWER(AK24)<>"n/a",ISNUMBER(AL24)),AL24,1E+99),IF(AND(AN24<>"",LOWER(AN24)<>"approved",LOWER(AN24)<>"n/a",ISNUMBER(AO24)),AO24,1E+99),IF(AND(AQ24<>"",LOWER(AQ24)<>"approved",LOWER(AQ24)<>"n/a",ISNUMBER(AR24)),AR24,1E+99),IF(AND(AT24<>"",LOWER(AT24)<>"approved",LOWER(AT24)<>"n/a",ISNUMBER(AU24)),AU24,1E+99),IF(AND(AW24<>"",LOWER(AW24)<>"approved",LOWER(AW24)<>"n/a",ISNUMBER(AX24)),AX24,1E+99),IF(AND(AZ24<>"",LOWER(AZ24)<>"approved",LOWER(AZ24)<>"n/a",ISNUMBER(BA24)),BA24,1E+99)),_xlpm.sw,IF(AG24="","",IFERROR("SW"&MID(AG24,FIND("/W",AG24)+2,99),"SW "&AG24)),_xlpm.stage&IF(_xlpm.parts="","All development items approved/closed",_xlpm.parts)&IF(AND(_xlpm.parts<>"",_xlpm.deadline<1E+99),"; need approval by "&TEXT(_xlpm.deadline,"d-mmm-yy"),"")&IF(_xlpm.sw<>""," for "&_xlpm.sw,""))) -> READY
A25: =IFERROR(VLOOKUP(E25,'Customer '!$A$4:$D$23,3,FALSE),"") -> RH | B25: NPD | C25: DUONG | D25: Sue Bilstad | E25: RESTORATION HARDWARE_HS | F25: =IFERROR(VLOOKUP(E25,'Customer '!$A$4:$D$28,2,FALSE),"") -> RH | G25: RH TRUMP SUITES NYC | H25: =IF(OR(DetailTracker[[#This Row],[PROJECT NAME (SHORT)]]="",DetailTracker[[#This Row],[CUSTOMER SHORTEN NAME]]=""),"",IF(ISNUMBER(DetailTracker[[#This Row],[BOQ DATE]]),YEAR(DetailTracker[[#This Row],[BOQ DATE]])&"-"&DetailTracker[[#This Row],[CUSTOMER SHORTEN NAME]]&"-"&DetailTracker[[#This Row],[PROJECT NAME (SHORT)]],IF(OR(DetailTracker[[#This Row],[SHIP MONTH FC]]="TBC",DetailTracker[[#This Row],[SHIP MONTH FC]]="Removed"),DetailTracker[[#This Row],[SHIP MONTH FC]]&"-"&DetailTracker[[#This Row],[CUSTOMER SHORTEN NAME]]&"-"&DetailTracker[[#This Row],[PROJECT NAME (SHORT)]],YEAR(TODAY())&"-"&DetailTracker[[#This Row],[CUSTOMER SHORTEN NAME]]&"-"&DetailTracker[[#This Row],[PROJECT NAME (SHORT)]]))) -> 2025-RH-RH TRUMP SUITES NYC | I25: =IF(OR($H25="",$B25=""),0,--(COUNTIFS($H$3:$H25,$H25,$B$3:$B25,$B25)=1)) -> 1 | J25: SHIPPED | K25: NEW | L25: 8. Shipment | M25: 45831 | N25: 46078 | P25: US | Q25: NY | V25: 1 | X25: 1234.86 | Y25: 1234.86 | Z25: 2026/M06 | AA25: =IF(Z25="","",IF(OR(Z25="TBC",Z25="Removed"),Z25,LEFT(Z25,4))) -> 2026 | AB25: 46192 | AC25: 46192 | AD25: 46116 | AE25: 46116 | AF25: =IF(AD25="","",IF(ISNUMBER(AD25),IF(AND(AD25>='2026 Calendar'!$C$4,AD25<='2026 Calendar'!$E$107),LOOKUP(AD25,'2026 Calendar'!$C$4:$C$107,'2026 Calendar'!$A$4:$A$107),YEAR(AD25-WEEKDAY(AD25,2)+4)&"/W"&TEXT(WEEKNUM(AD25,21),"00")),IF(IFERROR(ISNUMBER(SEARCH("/W",AD25)),FALSE),IF(IFERROR(ISNUMBER(SEARCH("-",AD25)),FALSE),LEFT(AD25,SEARCH("-",AD25)-1),AD25),AD25))) -> 2026/W14 | AG25: =IF(AE25="","",IF(ISNUMBER(AE25),IF(AND(AE25>='2026 Calendar'!$C$4,AE25<='2026 Calendar'!$E$107),LOOKUP(AE25,'2026 Calendar'!$C$4:$C$107,'2026 Calendar'!$A$4:$A$107),YEAR(AE25-WEEKDAY(AE25,2)+4)&"/W"&TEXT(WEEKNUM(AE25,21),"00")),IF(IFERROR(ISNUMBER(SEARCH("/W",AE25)),FALSE),IF(IFERROR(ISNUMBER(SEARCH("-",AE25)),FALSE),MID(AE25,SEARCH("-",AE25)+1,100),AE25),AE25))) -> 2026/W14 | AH25: Approved | AK25: Approved | AN25: N/A | AQ25: Approved | AT25: N/A | AW25: N/A | AZ25: N/A | BC25: =IF(J25="","",IF(OR(J25="OB",J25="NOR",J25="FC",J25="PIPELINE"),"Active","Complete")) -> Complete | BD25: Yes | BE25: =IF(UPPER(TRIM(J25))="SHIPPED","READY",_xlfn.LET(_xlpm.stage,IF(B25="","",B25&": "),_xlpm.ip,_xlfn.TEXTJOIN(", ",TRUE,IF(LOWER(AH25)="in progress","Drawing",""),IF(LOWER(AK25)="in progress","Veneer/Wood",""),IF(LOWER(AN25)="in progress","Marble",""),IF(LOWER(AQ25)="in progress","Metal",""),IF(LOWER(AT25)="in progress","Mirror",""),IF(LOWER(AW25)="in progress","Electrical",""),IF(LOWER(AZ25)="in progress","Fabric","")),_xlpm.pa,_xlfn.TEXTJOIN(", ",TRUE,IF(LOWER(AH25)="pending approval","Drawing",""),IF(LOWER(AK25)="pending approval","Veneer/Wood",""),IF(LOWER(AN25)="pending approval","Marble",""),IF(LOWER(AQ25)="pending approval","Metal",""),IF(LOWER(AT25)="pending approval","Mirror",""),IF(LOWER(AW25)="pending approval","Electrical",""),IF(LOWER(AZ25)="pending approval","Fabric","")),_xlpm.ns,_xlfn.TEXTJOIN(", ",TRUE,IF(LOWER(AH25)="not started","Drawing",""),IF(LOWER(AK25)="not started","Veneer/Wood",""),IF(LOWER(AN25)="not started","Marble",""),IF(LOWER(AQ25)="not started","Metal",""),IF(LOWER(AT25)="not started","Mirror",""),IF(LOWER(AW25)="not started","Electrical",""),IF(LOWER(AZ25)="not started","Fabric","")),_xlpm.fab,IF(OR(LOWER(AZ25)="com",LOWER(AZ25)="com pending",LOWER(AZ25)="com received"),"Fabric is "&LOWER(AZ25),""),_xlpm.parts,_xlfn.TEXTJOIN("; ",TRUE,IF(_xlpm.ip<>"","In progress: "&_xlpm.ip,""),IF(_xlpm.pa<>"","Pending approval: "&_xlpm.pa,""),IF(_xlpm.ns<>"","Not started: "&_xlpm.ns,""),_xlpm.fab),_xlpm.deadline,MIN(IF(AND(AH25<>"",LOWER(AH25)<>"approved",LOWER(AH25)<>"n/a",ISNUMBER(AI25)),AI25,1E+99),IF(AND(AK25<>"",LOWER(AK25)<>"approved",LOWER(AK25)<>"n/a",ISNUMBER(AL25)),AL25,1E+99),IF(AND(AN25<>"",LOWER(AN25)<>"approved",LOWER(AN25)<>"n/a",ISNUMBER(AO25)),AO25,1E+99),IF(AND(AQ25<>"",LOWER(AQ25)<>"approved",LOWER(AQ25)<>"n/a",ISNUMBER(AR25)),AR25,1E+99),IF(AND(AT25<>"",LOWER(AT25)<>"approved",LOWER(AT25)<>"n/a",ISNUMBER(AU25)),AU25,1E+99),IF(AND(AW25<>"",LOWER(AW25)<>"approved",LOWER(AW25)<>"n/a",ISNUMBER(AX25)),AX25,1E+99),IF(AND(AZ25<>"",LOWER(AZ25)<>"approved",LOWER(AZ25)<>"n/a",ISNUMBER(BA25)),BA25,1E+99)),_xlpm.sw,IF(AG25="","",IFERROR("SW"&MID(AG25,FIND("/W",AG25)+2,99),"SW "&AG25)),_xlpm.stage&IF(_xlpm.parts="","All development items approved/closed",_xlpm.parts)&IF(AND(_xlpm.parts<>"",_xlpm.deadline<1E+99),"; need approval by "&TEXT(_xlpm.deadline,"d-mmm-yy"),"")&IF(_xlpm.sw<>""," for "&_xlpm.sw,""))) -> READY
A26: =IFERROR(VLOOKUP(E26,'Customer '!$A$4:$D$23,3,FALSE),"") -> RH | B26: NPI | C26: TUYET | D26: Madison Lay | E26: RESTORATION HARDWARE_HS | F26: =IFERROR(VLOOKUP(E26,'Customer '!$A$4:$D$28,2,FALSE),"") -> RH | G26: TRUMP DORAL | H26: =IF(OR(DetailTracker[[#This Row],[PROJECT NAME (SHORT)]]="",DetailTracker[[#This Row],[CUSTOMER SHORTEN NAME]]=""),"",IF(ISNUMBER(DetailTracker[[#This Row],[BOQ DATE]]),YEAR(DetailTracker[[#This Row],[BOQ DATE]])&"-"&DetailTracker[[#This Row],[CUSTOMER SHORTEN NAME]]&"-"&DetailTracker[[#This Row],[PROJECT NAME (SHORT)]],IF(OR(DetailTracker[[#This Row],[SHIP MONTH FC]]="TBC",DetailTracker[[#This Row],[SHIP MONTH FC]]="Removed"),DetailTracker[[#This Row],[SHIP MONTH FC]]&"-"&DetailTracker[[#This Row],[CUSTOMER SHORTEN NAME]]&"-"&DetailTracker[[#This Row],[PROJECT NAME (SHORT)]],YEAR(TODAY())&"-"&DetailTracker[[#This Row],[CUSTOMER SHORTEN NAME]]&"-"&DetailTracker[[#This Row],[PROJECT NAME (SHORT)]]))) -> 2024-RH-TRUMP DORAL | I26: =IF(OR($H26="",$B26=""),0,--(COUNTIFS($H$3:$H26,$H26,$B$3:$B26,$B26)=1)) -> 1 | J26: SHIPPED | K26: REO | L26: 8. Shipment | M26: 45597 | N26: 46120 | P26: US | Q26: FL | V26: 1 | X26: 1375.5 | Y26: 1375.5 | Z26: 2026/M07 | AA26: =IF(Z26="","",IF(OR(Z26="TBC",Z26="Removed"),Z26,LEFT(Z26,4))) -> 2026 | AB26: 46192 | AC26: 46192 | AD26: 46116 | AE26: 46116 | AF26: =IF(AD26="","",IF(ISNUMBER(AD26),IF(AND(AD26>='2026 Calendar'!$C$4,AD26<='2026 Calendar'!$E$107),LOOKUP(AD26,'2026 Calendar'!$C$4:$C$107,'2026 Calendar'!$A$4:$A$107),YEAR(AD26-WEEKDAY(AD26,2)+4)&"/W"&TEXT(WEEKNUM(AD26,21),"00")),IF(IFERROR(ISNUMBER(SEARCH("/W",AD26)),FALSE),IF(IFERROR(ISNUMBER(SEARCH("-",AD26)),FALSE),LEFT(AD26,SEARCH("-",AD26)-1),AD26),AD26))) -> 2026/W14 | AG26: =IF(AE26="","",IF(ISNUMBER(AE26),IF(AND(AE26>='2026 Calendar'!$C$4,AE26<='2026 Calendar'!$E$107),LOOKUP(AE26,'2026 Calendar'!$C$4:$C$107,'2026 Calendar'!$A$4:$A$107),YEAR(AE26-WEEKDAY(AE26,2)+4)&"/W"&TEXT(WEEKNUM(AE26,21),"00")),IF(IFERROR(ISNUMBER(SEARCH("/W",AE26)),FALSE),IF(IFERROR(ISNUMBER(SEARCH("-",AE26)),FALSE),MID(AE26,SEARCH("-",AE26)+1,100),AE26),AE26))) -> 2026/W14 | AH26: Approved | AK26: Approved | AN26: N/A | AQ26: Approved | AT26: N/A | AW26: N/A | AZ26: COM | BC26: =IF(J26="","",IF(OR(J26="OB",J26="NOR",J26="FC",J26="PIPELINE"),"Active","Complete")) -> Complete | BD26: Yes | BE26: =IF(UPPER(TRIM(J26))="SHIPPED","READY",_xlfn.LET(_xlpm.stage,IF(B26="","",B26&": "),_xlpm.ip,_xlfn.TEXTJOIN(", ",TRUE,IF(LOWER(AH26)="in progress","Drawing",""),IF(LOWER(AK26)="in progress","Veneer/Wood",""),IF(LOWER(AN26)="in progress","Marble",""),IF(LOWER(AQ26)="in progress","Metal",""),IF(LOWER(AT26)="in progress","Mirror",""),IF(LOWER(AW26)="in progress","Electrical",""),IF(LOWER(AZ26)="in progress","Fabric","")),_xlpm.pa,_xlfn.TEXTJOIN(", ",TRUE,IF(LOWER(AH26)="pending approval","Drawing",""),IF(LOWER(AK26)="pending approval","Veneer/Wood",""),IF(LOWER(AN26)="pending approval","Marble",""),IF(LOWER(AQ26)="pending approval","Metal",""),IF(LOWER(AT26)="pending approval","Mirror",""),IF(LOWER(AW26)="pending approval","Electrical",""),IF(LOWER(AZ26)="pending approval","Fabric","")),_xlpm.ns,_xlfn.TEXTJOIN(", ",TRUE,IF(LOWER(AH26)="not started","Drawing",""),IF(LOWER(AK26)="not started","Veneer/Wood",""),IF(LOWER(AN26)="not started","Marble",""),IF(LOWER(AQ26)="not started","Metal",""),IF(LOWER(AT26)="not started","Mirror",""),IF(LOWER(AW26)="not started","Electrical",""),IF(LOWER(AZ26)="not started","Fabric","")),_xlpm.fab,IF(OR(LOWER(AZ26)="com",LOWER(AZ26)="com pending",LOWER(AZ26)="com received"),"Fabric is "&LOWER(AZ26),""),_xlpm.parts,_xlfn.TEXTJOIN("; ",TRUE,IF(_xlpm.ip<>"","In progress: "&_xlpm.ip,""),IF(_xlpm.pa<>"","Pending approval: "&_xlpm.pa,""),IF(_xlpm.ns<>"","Not started: "&_xlpm.ns,""),_xlpm.fab),_xlpm.deadline,MIN(IF(AND(AH26<>"",LOWER(AH26)<>"approved",LOWER(AH26)<>"n/a",ISNUMBER(AI26)),AI26,1E+99),IF(AND(AK26<>"",LOWER(AK26)<>"approved",LOWER(AK26)<>"n/a",ISNUMBER(AL26)),AL26,1E+99),IF(AND(AN26<>"",LOWER(AN26)<>"approved",LOWER(AN26)<>"n/a",ISNUMBER(AO26)),AO26,1E+99),IF(AND(AQ26<>"",LOWER(AQ26)<>"approved",LOWER(AQ26)<>"n/a",ISNUMBER(AR26)),AR26,1E+99),IF(AND(AT26<>"",LOWER(AT26)<>"approved",LOWER(AT26)<>"n/a",ISNUMBER(AU26)),AU26,1E+99),IF(AND(AW26<>"",LOWER(AW26)<>"approved",LOWER(AW26)<>"n/a",ISNUMBER(AX26)),AX26,1E+99),IF(AND(AZ26<>"",LOWER(AZ26)<>"approved",LOWER(AZ26)<>"n/a",ISNUMBER(BA26)),BA26,1E+99)),_xlpm.sw,IF(AG26="","",IFERROR("SW"&MID(AG26,FIND("/W",AG26)+2,99),"SW "&AG26)),_xlpm.stage&IF(_xlpm.parts="","All development items approved/closed",_xlpm.parts)&IF(AND(_xlpm.parts<>"",_xlpm.deadline<1E+99),"; need approval by "&TEXT(_xlpm.deadline,"d-mmm-yy"),"")&IF(_xlpm.sw<>""," for "&_xlpm.sw,""))) -> READY
A27: =IFERROR(VLOOKUP(E27,'Customer '!$A$4:$D$23,3,FALSE),"") -> RH | B27: NPI | C27: TBC | D27: Sue Bilstad | E27: RESTORATION HARDWARE_HS | F27: =IFERROR(VLOOKUP(E27,'Customer '!$A$4:$D$28,2,FALSE),"") -> RH | G27: RH TRUMP SUITES NYC | H27: =IF(OR(DetailTracker[[#This Row],[PROJECT NAME (SHORT)]]="",DetailTracker[[#This Row],[CUSTOMER SHORTEN NAME]]=""),"",IF(ISNUMBER(DetailTracker[[#This Row],[BOQ DATE]]),YEAR(DetailTracker[[#This Row],[BOQ DATE]])&"-"&DetailTracker[[#This Row],[CUSTOMER SHORTEN NAME]]&"-"&DetailTracker[[#This Row],[PROJECT NAME (SHORT)]],IF(OR(DetailTracker[[#This Row],[SHIP MONTH FC]]="TBC",DetailTracker[[#This Row],[SHIP MONTH FC]]="Removed"),DetailTracker[[#This Row],[SHIP MONTH FC]]&"-"&DetailTracker[[#This Row],[CUSTOMER SHORTEN NAME]]&"-"&DetailTracker[[#This Row],[PROJECT NAME (SHORT)]],YEAR(TODAY())&"-"&DetailTracker[[#This Row],[CUSTOMER SHORTEN NAME]]&"-"&DetailTracker[[#This Row],[PROJECT NAME (SHORT)]]))) -> 2026-RH-RH TRUMP SUITES NYC | I27: =IF(OR($H27="",$B27=""),0,--(COUNTIFS($H$3:$H27,$H27,$B$3:$B27,$B27)=1)) -> 1 | J27: FC | K27: NEW | L27: 3. Prototype Readiness | M27: 46136 | P27: US | Q27: NY | R27: 2 | S27: 4 | V27: 24 | X27: 1074318.5 | Y27: 537160 | Z27: 2027/M05 | AA27: =IF(Z27="","",IF(OR(Z27="TBC",Z27="Removed"),Z27,LEFT(Z27,4))) -> 2027 | AB27: - | AD27: 46515 | AE27: 46564 | AF27: =IF(AD27="","",IF(ISNUMBER(AD27),IF(AND(AD27>='2026 Calendar'!$C$4,AD27<='2026 Calendar'!$E$107),LOOKUP(AD27,'2026 Calendar'!$C$4:$C$107,'2026 Calendar'!$A$4:$A$107),YEAR(AD27-WEEKDAY(AD27,2)+4)&"/W"&TEXT(WEEKNUM(AD27,21),"00")),IF(IFERROR(ISNUMBER(SEARCH("/W",AD27)),FALSE),IF(IFERROR(ISNUMBER(SEARCH("-",AD27)),FALSE),LEFT(AD27,SEARCH("-",AD27)-1),AD27),AD27))) -> 2027/W19 | AG27: =IF(AE27="","",IF(ISNUMBER(AE27),IF(AND(AE27>='2026 Calendar'!$C$4,AE27<='2026 Calendar'!$E$107),LOOKUP(AE27,'2026 Calendar'!$C$4:$C$107,'2026 Calendar'!$A$4:$A$107),YEAR(AE27-WEEKDAY(AE27,2)+4)&"/W"&TEXT(WEEKNUM(AE27,21),"00")),IF(IFERROR(ISNUMBER(SEARCH("/W",AE27)),FALSE),IF(IFERROR(ISNUMBER(SEARCH("-",AE27)),FALSE),MID(AE27,SEARCH("-",AE27)+1,100),AE27),AE27))) -> 2027/W26 | AH27: Pending Approval | AK27: Approved | AN27: N/A | AQ27: Approved | AT27: N/A | AW27: In Progress | AZ27: COM | BC27: =IF(J27="","",IF(OR(J27="OB",J27="NOR",J27="FC",J27="PIPELINE"),"Active","Complete")) -> Active | BD27: Yes | BE27: =IF(UPPER(TRIM(J27))="SHIPPED","READY",_xlfn.LET(_xlpm.stage,IF(B27="","",B27&": "),_xlpm.ip,_xlfn.TEXTJOIN(", ",TRUE,IF(LOWER(AH27)="in progress","Drawing",""),IF(LOWER(AK27)="in progress","Veneer/Wood",""),IF(LOWER(AN27)="in progress","Marble",""),IF(LOWER(AQ27)="in progress","Metal",""),IF(LOWER(AT27)="in progress","Mirror",""),IF(LOWER(AW27)="in progress","Electrical",""),IF(LOWER(AZ27)="in progress","Fabric","")),_xlpm.pa,_xlfn.TEXTJOIN(", ",TRUE,IF(LOWER(AH27)="pending approval","Drawing",""),IF(LOWER(AK27)="pending approval","Veneer/Wood",""),IF(LOWER(AN27)="pending approval","Marble",""),IF(LOWER(AQ27)="pending approval","Metal",""),IF(LOWER(AT27)="pending approval","Mirror",""),IF(LOWER(AW27)="pending approval","Electrical",""),IF(LOWER(AZ27)="pending approval","Fabric","")),_xlpm.ns,_xlfn.TEXTJOIN(", ",TRUE,IF(LOWER(AH27)="not started","Drawing",""),IF(LOWER(AK27)="not started","Veneer/Wood",""),IF(LOWER(AN27)="not started","Marble",""),IF(LOWER(AQ27)="not started","Metal",""),IF(LOWER(AT27)="not started","Mirror",""),IF(LOWER(AW27)="not started","Electrical",""),IF(LOWER(AZ27)="not started","Fabric","")),_xlpm.fab,IF(OR(LOWER(AZ27)="com",LOWER(AZ27)="com pending",LOWER(AZ27)="com received"),"Fabric is "&LOWER(AZ27),""),_xlpm.parts,_xlfn.TEXTJOIN("; ",TRUE,IF(_xlpm.ip<>"","In progress: "&_xlpm.ip,""),IF(_xlpm.pa<>"","Pending approval: "&_xlpm.pa,""),IF(_xlpm.ns<>"","Not started: "&_xlpm.ns,""),_xlpm.fab),_xlpm.deadline,MIN(IF(AND(AH27<>"",LOWER(AH27)<>"approved",LOWER(AH27)<>"n/a",ISNUMBER(AI27)),AI27,1E+99),IF(AND(AK27<>"",LOWER(AK27)<>"approved",LOWER(AK27)<>"n/a",ISNUMBER(AL27)),AL27,1E+99),IF(AND(AN27<>"",LOWER(AN27)<>"approved",LOWER(AN27)<>"n/a",ISNUMBER(AO27)),AO27,1E+99),IF(AND(AQ27<>"",LOWER(AQ27)<>"approved",LOWER(AQ27)<>"n/a",ISNUMBER(AR27)),AR27,1E+99),IF(AND(AT27<>"",LOWER(AT27)<>"approved",LOWER(AT27)<>"n/a",ISNUMBER(AU27)),AU27,1E+99),IF(AND(AW27<>"",LOWER(AW27)<>"approved",LOWER(AW27)<>"n/a",ISNUMBER(AX27)),AX27,1E+99),IF(AND(AZ27<>"",LOWER(AZ27)<>"approved",LOWER(AZ27)<>"n/a",ISNUMBER(BA27)),BA27,1E+99)),_xlpm.sw,IF(AG27="","",IFERROR("SW"&MID(AG27,FIND("/W",AG27)+2,99),"SW "&AG27)),_xlpm.stage&IF(_xlpm.parts="","All development items approved/closed",_xlpm.parts)&IF(AND(_xlpm.parts<>"",_xlpm.deadline<1E+99),"; need approval by "&TEXT(_xlpm.deadline,"d-mmm-yy"),"")&IF(_xlpm.sw<>""," for "&_xlpm.sw,""))) -> NPI: In progress: Electrical; Pending approval: Drawing; Fabric is com for SW26
A28: =IFERROR(VLOOKUP(E28,'Customer '!$A$4:$D$23,3,FALSE),"") -> RH | B28: NPI | C28: TBC | D28: Sue Bilstad | E28: RESTORATION HARDWARE_HS | F28: =IFERROR(VLOOKUP(E28,'Customer '!$A$4:$D$28,2,FALSE),"") -> RH | G28: RH TRUMP SUITES NYC | H28: =IF(OR(DetailTracker[[#This Row],[PROJECT NAME (SHORT)]]="",DetailTracker[[#This Row],[CUSTOMER SHORTEN NAME]]=""),"",IF(ISNUMBER(DetailTracker[[#This Row],[BOQ DATE]]),YEAR(DetailTracker[[#This Row],[BOQ DATE]])&"-"&DetailTracker[[#This Row],[CUSTOMER SHORTEN NAME]]&"-"&DetailTracker[[#This Row],[PROJECT NAME (SHORT)]],IF(OR(DetailTracker[[#This Row],[SHIP MONTH FC]]="TBC",DetailTracker[[#This Row],[SHIP MONTH FC]]="Removed"),DetailTracker[[#This Row],[SHIP MONTH FC]]&"-"&DetailTracker[[#This Row],[CUSTOMER SHORTEN NAME]]&"-"&DetailTracker[[#This Row],[PROJECT NAME (SHORT)]],YEAR(TODAY())&"-"&DetailTracker[[#This Row],[CUSTOMER SHORTEN NAME]]&"-"&DetailTracker[[#This Row],[PROJECT NAME (SHORT)]]))) -> 2026-RH-RH TRUMP SUITES NYC | I28: =IF(OR($H28="",$B28=""),0,--(COUNTIFS($H$3:$H28,$H28,$B$3:$B28,$B28)=1)) -> 0 | J28: FC | K28: NEW | L28: 3. Prototype Readiness | M28: 46136 | P28: US | Q28: NY | R28: 2 | S28: 4 | V28: 24 | X28: 1074318.5 | Y28: =DetailTracker[[#This Row],[PROJECT VALUE $]]-Y27 -> 537158.51 | Z28: 2027/M06 | AA28: =IF(Z28="","",IF(OR(Z28="TBC",Z28="Removed"),Z28,LEFT(Z28,4))) -> 2027 | AB28: - | AD28: 46515 | AE28: 46564 | AF28: =IF(AD28="","",IF(ISNUMBER(AD28),IF(AND(AD28>='2026 Calendar'!$C$4,AD28<='2026 Calendar'!$E$107),LOOKUP(AD28,'2026 Calendar'!$C$4:$C$107,'2026 Calendar'!$A$4:$A$107),YEAR(AD28-WEEKDAY(AD28,2)+4)&"/W"&TEXT(WEEKNUM(AD28,21),"00")),IF(IFERROR(ISNUMBER(SEARCH("/W",AD28)),FALSE),IF(IFERROR(ISNUMBER(SEARCH("-",AD28)),FALSE),LEFT(AD28,SEARCH("-",AD28)-1),AD28),AD28))) -> 2027/W19 | AG28: =IF(AE28="","",IF(ISNUMBER(AE28),IF(AND(AE28>='2026 Calendar'!$C$4,AE28<='2026 Calendar'!$E$107),LOOKUP(AE28,'2026 Calendar'!$C$4:$C$107,'2026 Calendar'!$A$4:$A$107),YEAR(AE28-WEEKDAY(AE28,2)+4)&"/W"&TEXT(WEEKNUM(AE28,21),"00")),IF(IFERROR(ISNUMBER(SEARCH("/W",AE28)),FALSE),IF(IFERROR(ISNUMBER(SEARCH("-",AE28)),FALSE),MID(AE28,SEARCH("-",AE28)+1,100),AE28),AE28))) -> 2027/W26 | AH28: Pending Approval | AK28: Approved | AN28: N/A | AQ28: Approved | AT28: N/A | AW28: In Progress | AZ28: COM | BC28: =IF(J28="","",IF(OR(J28="OB",J28="NOR",J28="FC",J28="PIPELINE"),"Active","Complete")) -> Active | BD28: Yes | BE28: =IF(UPPER(TRIM(J28))="SHIPPED","READY",_xlfn.LET(_xlpm.stage,IF(B28="","",B28&": "),_xlpm.ip,_xlfn.TEXTJOIN(", ",TRUE,IF(LOWER(AH28)="in progress","Drawing",""),IF(LOWER(AK28)="in progress","Veneer/Wood",""),IF(LOWER(AN28)="in progress","Marble",""),IF(LOWER(AQ28)="in progress","Metal",""),IF(LOWER(AT28)="in progress","Mirror",""),IF(LOWER(AW28)="in progress","Electrical",""),IF(LOWER(AZ28)="in progress","Fabric","")),_xlpm.pa,_xlfn.TEXTJOIN(", ",TRUE,IF(LOWER(AH28)="pending approval","Drawing",""),IF(LOWER(AK28)="pending approval","Veneer/Wood",""),IF(LOWER(AN28)="pending approval","Marble",""),IF(LOWER(AQ28)="pending approval","Metal",""),IF(LOWER(AT28)="pending approval","Mirror",""),IF(LOWER(AW28)="pending approval","Electrical",""),IF(LOWER(AZ28)="pending approval","Fabric","")),_xlpm.ns,_xlfn.TEXTJOIN(", ",TRUE,IF(LOWER(AH28)="not started","Drawing",""),IF(LOWER(AK28)="not started","Veneer/Wood",""),IF(LOWER(AN28)="not started","Marble",""),IF(LOWER(AQ28)="not started","Metal",""),IF(LOWER(AT28)="not started","Mirror",""),IF(LOWER(AW28)="not started","Electrical",""),IF(LOWER(AZ28)="not started","Fabric","")),_xlpm.fab,IF(OR(LOWER(AZ28)="com",LOWER(AZ28)="com pending",LOWER(AZ28)="com received"),"Fabric is "&LOWER(AZ28),""),_xlpm.parts,_xlfn.TEXTJOIN("; ",TRUE,IF(_xlpm.ip<>"","In progress: "&_xlpm.ip,""),IF(_xlpm.pa<>"","Pending approval: "&_xlpm.pa,""),IF(_xlpm.ns<>"","Not started: "&_xlpm.ns,""),_xlpm.fab),_xlpm.deadline,MIN(IF(AND(AH28<>"",LOWER(AH28)<>"approved",LOWER(AH28)<>"n/a",ISNUMBER(AI28)),AI28,1E+99),IF(AND(AK28<>"",LOWER(AK28)<>"approved",LOWER(AK28)<>"n/a",ISNUMBER(AL28)),AL28,1E+99),IF(AND(AN28<>"",LOWER(AN28)<>"approved",LOWER(AN28)<>"n/a",ISNUMBER(AO28)),AO28,1E+99),IF(AND(AQ28<>"",LOWER(AQ28)<>"approved",LOWER(AQ28)<>"n/a",ISNUMBER(AR28)),AR28,1E+99),IF(AND(AT28<>"",LOWER(AT28)<>"approved",LOWER(AT28)<>"n/a",ISNUMBER(AU28)),AU28,1E+99),IF(AND(AW28<>"",LOWER(AW28)<>"approved",LOWER(AW28)<>"n/a",ISNUMBER(AX28)),AX28,1E+99),IF(AND(AZ28<>"",LOWER(AZ28)<>"approved",LOWER(AZ28)<>"n/a",ISNUMBER(BA28)),BA28,1E+99)),_xlpm.sw,IF(AG28="","",IFERROR("SW"&MID(AG28,FIND("/W",AG28)+2,99),"SW "&AG28)),_xlpm.stage&IF(_xlpm.parts="","All development items approved/closed",_xlpm.parts)&IF(AND(_xlpm.parts<>"",_xlpm.deadline<1E+99),"; need approval by "&TEXT(_xlpm.deadline,"d-mmm-yy"),"")&IF(_xlpm.sw<>""," for "&_xlpm.sw,""))) -> NPI: In progress: Electrical; Pending approval: Drawing; Fabric is com for SW26
A29: =IFERROR(VLOOKUP(E29,'Customer '!$A$4:$D$23,3,FALSE),"") -> RH | B29: NPD | C29: BIEN | D29: Sue Bilstad | E29: RESTORATION HARDWARE_HS | F29: =IFERROR(VLOOKUP(E29,'Customer '!$A$4:$D$28,2,FALSE),"") -> RH | G29: ROSEWOOD CALISTOGA | H29: =IF(OR(DetailTracker[[#This Row],[PROJECT NAME (SHORT)]]="",DetailTracker[[#This Row],[CUSTOMER SHORTEN NAME]]=""),"",IF(ISNUMBER(DetailTracker[[#This Row],[BOQ DATE]]),YEAR(DetailTracker[[#This Row],[BOQ DATE]])&"-"&DetailTracker[[#This Row],[CUSTOMER SHORTEN NAME]]&"-"&DetailTracker[[#This Row],[PROJECT NAME (SHORT)]],IF(OR(DetailTracker[[#This Row],[SHIP MONTH FC]]="TBC",DetailTracker[[#This Row],[SHIP MONTH FC]]="Removed"),DetailTracker[[#This Row],[SHIP MONTH FC]]&"-"&DetailTracker[[#This Row],[CUSTOMER SHORTEN NAME]]&"-"&DetailTracker[[#This Row],[PROJECT NAME (SHORT)]],YEAR(TODAY())&"-"&DetailTracker[[#This Row],[CUSTOMER SHORTEN NAME]]&"-"&DetailTracker[[#This Row],[PROJECT NAME (SHORT)]]))) -> 2026-RH-ROSEWOOD CALISTOGA | I29: =IF(OR($H29="",$B29=""),0,--(COUNTIFS($H$3:$H29,$H29,$B$3:$B29,$B29)=1)) -> 1 | J29: SHIPPED | K29: NEW | L29: 8. Shipment | M29: 46136 | N29: 46147 | P29: US | Q29: CA | V29: 6 | X29: 1046.75 | Y29: 1046.75 | Z29: 2026/M06 | AA29: =IF(Z29="","",IF(OR(Z29="TBC",Z29="Removed"),Z29,LEFT(Z29,4))) -> 2026 | AB29: 46183 | AC29: 46183 | AD29: 46116 | AE29: 46116 | AF29: =IF(AD29="","",IF(ISNUMBER(AD29),IF(AND(AD29>='2026 Calendar'!$C$4,AD29<='2026 Calendar'!$E$107),LOOKUP(AD29,'2026 Calendar'!$C$4:$C$107,'2026 Calendar'!$A$4:$A$107),YEAR(AD29-WEEKDAY(AD29,2)+4)&"/W"&TEXT(WEEKNUM(AD29,21),"00")),IF(IFERROR(ISNUMBER(SEARCH("/W",AD29)),FALSE),IF(IFERROR(ISNUMBER(SEARCH("-",AD29)),FALSE),LEFT(AD29,SEARCH("-",AD29)-1),AD29),AD29))) -> 2026/W14 | AG29: =IF(AE29="","",IF(ISNUMBER(AE29),IF(AND(AE29>='2026 Calendar'!$C$4,AE29<='2026 Calendar'!$E$107),LOOKUP(AE29,'2026 Calendar'!$C$4:$C$107,'2026 Calendar'!$A$4:$A$107),YEAR(AE29-WEEKDAY(AE29,2)+4)&"/W"&TEXT(WEEKNUM(AE29,21),"00")),IF(IFERROR(ISNUMBER(SEARCH("/W",AE29)),FALSE),IF(IFERROR(ISNUMBER(SEARCH("-",AE29)),FALSE),MID(AE29,SEARCH("-",AE29)+1,100),AE29),AE29))) -> 2026/W14 | AH29: Approved | AJ29: 46164 | AK29: Approved | AM29: 46199 | AN29: N/A | AQ29: Approved | AS29: 46191 | AT29: N/A | AW29: N/A | AZ29: COM | BB29: 46175 | BC29: =IF(J29="","",IF(OR(J29="OB",J29="NOR",J29="FC",J29="PIPELINE"),"Active","Complete")) -> Complete | BD29: Yes | BE29: =IF(UPPER(TRIM(J29))="SHIPPED","READY",_xlfn.LET(_xlpm.stage,IF(B29="","",B29&": "),_xlpm.ip,_xlfn.TEXTJOIN(", ",TRUE,IF(LOWER(AH29)="in progress","Drawing",""),IF(LOWER(AK29)="in progress","Veneer/Wood",""),IF(LOWER(AN29)="in progress","Marble",""),IF(LOWER(AQ29)="in progress","Metal",""),IF(LOWER(AT29)="in progress","Mirror",""),IF(LOWER(AW29)="in progress","Electrical",""),IF(LOWER(AZ29)="in progress","Fabric","")),_xlpm.pa,_xlfn.TEXTJOIN(", ",TRUE,IF(LOWER(AH29)="pending approval","Drawing",""),IF(LOWER(AK29)="pending approval","Veneer/Wood",""),IF(LOWER(AN29)="pending approval","Marble",""),IF(LOWER(AQ29)="pending approval","Metal",""),IF(LOWER(AT29)="pending approval","Mirror",""),IF(LOWER(AW29)="pending approval","Electrical",""),IF(LOWER(AZ29)="pending approval","Fabric","")),_xlpm.ns,_xlfn.TEXTJOIN(", ",TRUE,IF(LOWER(AH29)="not started","Drawing",""),IF(LOWER(AK29)="not started","Veneer/Wood",""),IF(LOWER(AN29)="not started","Marble",""),IF(LOWER(AQ29)="not started","Metal",""),IF(LOWER(AT29)="not started","Mirror",""),IF(LOWER(AW29)="not started","Electrical",""),IF(LOWER(AZ29)="not started","Fabric","")),_xlpm.fab,IF(OR(LOWER(AZ29)="com",LOWER(AZ29)="com pending",LOWER(AZ29)="com received"),"Fabric is "&LOWER(AZ29),""),_xlpm.parts,_xlfn.TEXTJOIN("; ",TRUE,IF(_xlpm.ip<>"","In progress: "&_xlpm.ip,""),IF(_xlpm.pa<>"","Pending approval: "&_xlpm.pa,""),IF(_xlpm.ns<>"","Not started: "&_xlpm.ns,""),_xlpm.fab),_xlpm.deadline,MIN(IF(AND(AH29<>"",LOWER(AH29)<>"approved",LOWER(AH29)<>"n/a",ISNUMBER(AI29)),AI29,1E+99),IF(AND(AK29<>"",LOWER(AK29)<>"approved",LOWER(AK29)<>"n/a",ISNUMBER(AL29)),AL29,1E+99),IF(AND(AN29<>"",LOWER(AN29)<>"approved",LOWER(AN29)<>"n/a",ISNUMBER(AO29)),AO29,1E+99),IF(AND(AQ29<>"",LOWER(AQ29)<>"approved",LOWER(AQ29)<>"n/a",ISNUMBER(AR29)),AR29,1E+99),IF(AND(AT29<>"",LOWER(AT29)<>"approved",LOWER(AT29)<>"n/a",ISNUMBER(AU29)),AU29,1E+99),IF(AND(AW29<>"",LOWER(AW29)<>"approved",LOWER(AW29)<>"n/a",ISNUMBER(AX29)),AX29,1E+99),IF(AND(AZ29<>"",LOWER(AZ29)<>"approved",LOWER(AZ29)<>"n/a",ISNUMBER(BA29)),BA29,1E+99)),_xlpm.sw,IF(AG29="","",IFERROR("SW"&MID(AG29,FIND("/W",AG29)+2,99),"SW "&AG29)),_xlpm.stage&IF(_xlpm.parts="","All development items approved/closed",_xlpm.parts)&IF(AND(_xlpm.parts<>"",_xlpm.deadline<1E+99),"; need approval by "&TEXT(_xlpm.deadline,"d-mmm-yy"),"")&IF(_xlpm.sw<>""," for "&_xlpm.sw,""))) -> READY
A30: =IFERROR(VLOOKUP(E30,'Customer '!$A$4:$D$23,3,FALSE),"") -> RH | B30: NPI | C30: BIEN | D30: Sue Bilstad | E30: RESTORATION HARDWARE_HS | F30: =IFERROR(VLOOKUP(E30,'Customer '!$A$4:$D$28,2,FALSE),"") -> RH | G30: ROSEWOOD CALISTOGA | H30: =IF(OR(DetailTracker[[#This Row],[PROJECT NAME (SHORT)]]="",DetailTracker[[#This Row],[CUSTOMER SHORTEN NAME]]=""),"",IF(ISNUMBER(DetailTracker[[#This Row],[BOQ DATE]]),YEAR(DetailTracker[[#This Row],[BOQ DATE]])&"-"&DetailTracker[[#This Row],[CUSTOMER SHORTEN NAME]]&"-"&DetailTracker[[#This Row],[PROJECT NAME (SHORT)]],IF(OR(DetailTracker[[#This Row],[SHIP MONTH FC]]="TBC",DetailTracker[[#This Row],[SHIP MONTH FC]]="Removed"),DetailTracker[[#This Row],[SHIP MONTH FC]]&"-"&DetailTracker[[#This Row],[CUSTOMER SHORTEN NAME]]&"-"&DetailTracker[[#This Row],[PROJECT NAME (SHORT)]],YEAR(TODAY())&"-"&DetailTracker[[#This Row],[CUSTOMER SHORTEN NAME]]&"-"&DetailTracker[[#This Row],[PROJECT NAME (SHORT)]]))) -> 2025-RH-ROSEWOOD CALISTOGA | I30: =IF(OR($H30="",$B30=""),0,--(COUNTIFS($H$3:$H30,$H30,$B$3:$B30,$B30)=1)) -> 1 | J30: OB | K30: NEW | L30: 7. Mass Production | M30: 45861 | N30: 46170 | P30: US | Q30: CA | R30: 0 | S30: 0 | V30: 38 | W30: 756 | X30: 311473.76 | Y30: 239023 | Z30: 2026/M11 | AA30: =IF(Z30="","",IF(OR(Z30="TBC",Z30="Removed"),Z30,LEFT(Z30,4))) -> 2026 | AB30: 46321 | AC30: 46325 | AD30: 46332 | AE30: 46367 | AF30: =IF(AD30="","",IF(ISNUMBER(AD30),IF(AND(AD30>='2026 Calendar'!$C$4,AD30<='2026 Calendar'!$E$107),LOOKUP(AD30,'2026 Calendar'!$C$4:$C$107,'2026 Calendar'!$A$4:$A$107),YEAR(AD30-WEEKDAY(AD30,2)+4)&"/W"&TEXT(WEEKNUM(AD30,21),"00")),IF(IFERROR(ISNUMBER(SEARCH("/W",AD30)),FALSE),IF(IFERROR(ISNUMBER(SEARCH("-",AD30)),FALSE),LEFT(AD30,SEARCH("-",AD30)-1),AD30),AD30))) -> 2026/W45 | AG30: =IF(AE30="","",IF(ISNUMBER(AE30),IF(AND(AE30>='2026 Calendar'!$C$4,AE30<='2026 Calendar'!$E$107),LOOKUP(AE30,'2026 Calendar'!$C$4:$C$107,'2026 Calendar'!$A$4:$A$107),YEAR(AE30-WEEKDAY(AE30,2)+4)&"/W"&TEXT(WEEKNUM(AE30,21),"00")),IF(IFERROR(ISNUMBER(SEARCH("/W",AE30)),FALSE),IF(IFERROR(ISNUMBER(SEARCH("-",AE30)),FALSE),MID(AE30,SEARCH("-",AE30)+1,100),AE30),AE30))) -> 2026/W50 | AH30: Approved | AJ30: 46176 | AK30: Approved | AM30: 46205 | AN30: Approved | AP30: 46168 | AQ30: Approved | AS30: 46191 | AT30: N/A | AW30: N/A | AZ30: COM Received | BB30: NA | BC30: =IF(J30="","",IF(OR(J30="OB",J30="NOR",J30="FC",J30="PIPELINE"),"Active","Complete")) -> Active | BD30: Yes | BE30: =IF(UPPER(TRIM(J30))="SHIPPED","READY",_xlfn.LET(_xlpm.stage,IF(B30="","",B30&": "),_xlpm.ip,_xlfn.TEXTJOIN(", ",TRUE,IF(LOWER(AH30)="in progress","Drawing",""),IF(LOWER(AK30)="in progress","Veneer/Wood",""),IF(LOWER(AN30)="in progress","Marble",""),IF(LOWER(AQ30)="in progress","Metal",""),IF(LOWER(AT30)="in progress","Mirror",""),IF(LOWER(AW30)="in progress","Electrical",""),IF(LOWER(AZ30)="in progress","Fabric","")),_xlpm.pa,_xlfn.TEXTJOIN(", ",TRUE,IF(LOWER(AH30)="pending approval","Drawing",""),IF(LOWER(AK30)="pending approval","Veneer/Wood",""),IF(LOWER(AN30)="pending approval","Marble",""),IF(LOWER(AQ30)="pending approval","Metal",""),IF(LOWER(AT30)="pending approval","Mirror",""),IF(LOWER(AW30)="pending approval","Electrical",""),IF(LOWER(AZ30)="pending approval","Fabric","")),_xlpm.ns,_xlfn.TEXTJOIN(", ",TRUE,IF(LOWER(AH30)="not started","Drawing",""),IF(LOWER(AK30)="not started","Veneer/Wood",""),IF(LOWER(AN30)="not started","Marble",""),IF(LOWER(AQ30)="not started","Metal",""),IF(LOWER(AT30)="not started","Mirror",""),IF(LOWER(AW30)="not started","Electrical",""),IF(LOWER(AZ30)="not started","Fabric","")),_xlpm.fab,IF(OR(LOWER(AZ30)="com",LOWER(AZ30)="com pending",LOWER(AZ30)="com received"),"Fabric is "&LOWER(AZ30),""),_xlpm.parts,_xlfn.TEXTJOIN("; ",TRUE,IF(_xlpm.ip<>"","In progress: "&_xlpm.ip,""),IF(_xlpm.pa<>"","Pending approval: "&_xlpm.pa,""),IF(_xlpm.ns<>"","Not started: "&_xlpm.ns,""),_xlpm.fab),_xlpm.deadline,MIN(IF(AND(AH30<>"",LOWER(AH30)<>"approved",LOWER(AH30)<>"n/a",ISNUMBER(AI30)),AI30,1E+99),IF(AND(AK30<>"",LOWER(AK30)<>"approved",LOWER(AK30)<>"n/a",ISNUMBER(AL30)),AL30,1E+99),IF(AND(AN30<>"",LOWER(AN30)<>"approved",LOWER(AN30)<>"n/a",ISNUMBER(AO30)),AO30,1E+99),IF(AND(AQ30<>"",LOWER(AQ30)<>"approved",LOWER(AQ30)<>"n/a",ISNUMBER(AR30)),AR30,1E+99),IF(AND(AT30<>"",LOWER(AT30)<>"approved",LOWER(AT30)<>"n/a",ISNUMBER(AU30)),AU30,1E+99),IF(AND(AW30<>"",LOWER(AW30)<>"approved",LOWER(AW30)<>"n/a",ISNUMBER(AX30)),AX30,1E+99),IF(AND(AZ30<>"",LOWER(AZ30)<>"approved",LOWER(AZ30)<>"n/a",ISNUMBER(BA30)),BA30,1E+99)),_xlpm.sw,IF(AG30="","",IFERROR("SW"&MID(AG30,FIND("/W",AG30)+2,99),"SW "&AG30)),_xlpm.stage&IF(_xlpm.parts="","All development items approved/closed",_xlpm.parts)&IF(AND(_xlpm.parts<>"",_xlpm.deadline<1E+99),"; need approval by "&TEXT(_xlpm.deadline,"d-mmm-yy"),"")&IF(_xlpm.sw<>""," for "&_xlpm.sw,""))) -> NPI: Fabric is com received for SW50
A31: =IFERROR(VLOOKUP(E31,'Customer '!$A$4:$D$23,3,FALSE),"") -> RH | B31: NPI | C31: BIEN | D31: Sue Bilstad | E31: RESTORATION HARDWARE_HS | F31: =IFERROR(VLOOKUP(E31,'Customer '!$A$4:$D$28,2,FALSE),"") -> RH | G31: ROSEWOOD CALISTOGA | H31: =IF(OR(DetailTracker[[#This Row],[PROJECT NAME (SHORT)]]="",DetailTracker[[#This Row],[CUSTOMER SHORTEN NAME]]=""),"",IF(ISNUMBER(DetailTracker[[#This Row],[BOQ DATE]]),YEAR(DetailTracker[[#This Row],[BOQ DATE]])&"-"&DetailTracker[[#This Row],[CUSTOMER SHORTEN NAME]]&"-"&DetailTracker[[#This Row],[PROJECT NAME (SHORT)]],IF(OR(DetailTracker[[#This Row],[SHIP MONTH FC]]="TBC",DetailTracker[[#This Row],[SHIP MONTH FC]]="Removed"),DetailTracker[[#This Row],[SHIP MONTH FC]]&"-"&DetailTracker[[#This Row],[CUSTOMER SHORTEN NAME]]&"-"&DetailTracker[[#This Row],[PROJECT NAME (SHORT)]],YEAR(TODAY())&"-"&DetailTracker[[#This Row],[CUSTOMER SHORTEN NAME]]&"-"&DetailTracker[[#This Row],[PROJECT NAME (SHORT)]]))) -> 2025-RH-ROSEWOOD CALISTOGA | I31: =IF(OR($H31="",$B31=""),0,--(COUNTIFS($H$3:$H31,$H31,$B$3:$B31,$B31)=1)) -> 0 | J31: OB | K31: NEW | L31: 7. Mass Production | M31: 45861 | N31: 46170 | P31: US | Q31: CA | R31: 0 | S31: 0 | V31: 38 | W31: 756 | X31: 311473.76 | Y31: 72450.76 | Z31: 2026/M12 | AA31: =IF(Z31="","",IF(OR(Z31="TBC",Z31="Removed"),Z31,LEFT(Z31,4))) -> 2026 | AB31: 46328 | AC31: 46339 | AD31: 46332 | AE31: 46367 | AF31: =IF(AD31="","",IF(ISNUMBER(AD31),IF(AND(AD31>='2026 Calendar'!$C$4,AD31<='2026 Calendar'!$E$107),LOOKUP(AD31,'2026 Calendar'!$C$4:$C$107,'2026 Calendar'!$A$4:$A$107),YEAR(AD31-WEEKDAY(AD31,2)+4)&"/W"&TEXT(WEEKNUM(AD31,21),"00")),IF(IFERROR(ISNUMBER(SEARCH("/W",AD31)),FALSE),IF(IFERROR(ISNUMBER(SEARCH("-",AD31)),FALSE),LEFT(AD31,SEARCH("-",AD31)-1),AD31),AD31))) -> 2026/W45 | AG31: =IF(AE31="","",IF(ISNUMBER(AE31),IF(AND(AE31>='2026 Calendar'!$C$4,AE31<='2026 Calendar'!$E$107),LOOKUP(AE31,'2026 Calendar'!$C$4:$C$107,'2026 Calendar'!$A$4:$A$107),YEAR(AE31-WEEKDAY(AE31,2)+4)&"/W"&TEXT(WEEKNUM(AE31,21),"00")),IF(IFERROR(ISNUMBER(SEARCH("/W",AE31)),FALSE),IF(IFERROR(ISNUMBER(SEARCH("-",AE31)),FALSE),MID(AE31,SEARCH("-",AE31)+1,100),AE31),AE31))) -> 2026/W50 | AH31: Approved | AK31: Approved | AN31: Approved | AP31: 46168 | AQ31: Approved | AS31: 46191 | AT31: N/A | AW31: N/A | AZ31: COM Received | BB31: NA | BC31: =IF(J31="","",IF(OR(J31="OB",J31="NOR",J31="FC",J31="PIPELINE"),"Active","Complete")) -> Active | BD31: Yes | BE31: =IF(UPPER(TRIM(J31))="SHIPPED","READY",_xlfn.LET(_xlpm.stage,IF(B31="","",B31&": "),_xlpm.ip,_xlfn.TEXTJOIN(", ",TRUE,IF(LOWER(AH31)="in progress","Drawing",""),IF(LOWER(AK31)="in progress","Veneer/Wood",""),IF(LOWER(AN31)="in progress","Marble",""),IF(LOWER(AQ31)="in progress","Metal",""),IF(LOWER(AT31)="in progress","Mirror",""),IF(LOWER(AW31)="in progress","Electrical",""),IF(LOWER(AZ31)="in progress","Fabric","")),_xlpm.pa,_xlfn.TEXTJOIN(", ",TRUE,IF(LOWER(AH31)="pending approval","Drawing",""),IF(LOWER(AK31)="pending approval","Veneer/Wood",""),IF(LOWER(AN31)="pending approval","Marble",""),IF(LOWER(AQ31)="pending approval","Metal",""),IF(LOWER(AT31)="pending approval","Mirror",""),IF(LOWER(AW31)="pending approval","Electrical",""),IF(LOWER(AZ31)="pending approval","Fabric","")),_xlpm.ns,_xlfn.TEXTJOIN(", ",TRUE,IF(LOWER(AH31)="not started","Drawing",""),IF(LOWER(AK31)="not started","Veneer/Wood",""),IF(LOWER(AN31)="not started","Marble",""),IF(LOWER(AQ31)="not started","Metal",""),IF(LOWER(AT31)="not started","Mirror",""),IF(LOWER(AW31)="not started","Electrical",""),IF(LOWER(AZ31)="not started","Fabric","")),_xlpm.fab,IF(OR(LOWER(AZ31)="com",LOWER(AZ31)="com pending",LOWER(AZ31)="com received"),"Fabric is "&LOWER(AZ31),""),_xlpm.parts,_xlfn.TEXTJOIN("; ",TRUE,IF(_xlpm.ip<>"","In progress: "&_xlpm.ip,""),IF(_xlpm.pa<>"","Pending approval: "&_xlpm.pa,""),IF(_xlpm.ns<>"","Not started: "&_xlpm.ns,""),_xlpm.fab),_xlpm.deadline,MIN(IF(AND(AH31<>"",LOWER(AH31)<>"approved",LOWER(AH31)<>"n/a",ISNUMBER(AI31)),AI31,1E+99),IF(AND(AK31<>"",LOWER(AK31)<>"approved",LOWER(AK31)<>"n/a",ISNUMBER(AL31)),AL31,1E+99),IF(AND(AN31<>"",LOWER(AN31)<>"approved",LOWER(AN31)<>"n/a",ISNUMBER(AO31)),AO31,1E+99),IF(AND(AQ31<>"",LOWER(AQ31)<>"approved",LOWER(AQ31)<>"n/a",ISNUMBER(AR31)),AR31,1E+99),IF(AND(AT31<>"",LOWER(AT31)<>"approved",LOWER(AT31)<>"n/a",ISNUMBER(AU31)),AU31,1E+99),IF(AND(AW31<>"",LOWER(AW31)<>"approved",LOWER(AW31)<>"n/a",ISNUMBER(AX31)),AX31,1E+99),IF(AND(AZ31<>"",LOWER(AZ31)<>"approved",LOWER(AZ31)<>"n/a",ISNUMBER(BA31)),BA31,1E+99)),_xlpm.sw,IF(AG31="","",IFERROR("SW"&MID(AG31,FIND("/W",AG31)+2,99),"SW "&AG31)),_xlpm.stage&IF(_xlpm.parts="","All development items approved/closed",_xlpm.parts)&IF(AND(_xlpm.parts<>"",_xlpm.deadline<1E+99),"; need approval by "&TEXT(_xlpm.deadline,"d-mmm-yy"),"")&IF(_xlpm.sw<>""," for "&_xlpm.sw,""))) -> NPI: Fabric is com received for SW50
A32: =IFERROR(VLOOKUP(E32,'Customer '!$A$4:$D$23,3,FALSE),"") -> RH | B32: NPI | C32: DUY | D32: Madison Lay | E32: RESTORATION HARDWARE_HS | F32: =IFERROR(VLOOKUP(E32,'Customer '!$A$4:$D$28,2,FALSE),"") -> RH | G32: SNAKE RIVER LODGE BLUEFLAG | H32: =IF(OR(DetailTracker[[#This Row],[PROJECT NAME (SHORT)]]="",DetailTracker[[#This Row],[CUSTOMER SHORTEN NAME]]=""),"",IF(ISNUMBER(DetailTracker[[#This Row],[BOQ DATE]]),YEAR(DetailTracker[[#This Row],[BOQ DATE]])&"-"&DetailTracker[[#This Row],[CUSTOMER SHORTEN NAME]]&"-"&DetailTracker[[#This Row],[PROJECT NAME (SHORT)]],IF(OR(DetailTracker[[#This Row],[SHIP MONTH FC]]="TBC",DetailTracker[[#This Row],[SHIP MONTH FC]]="Removed"),DetailTracker[[#This Row],[SHIP MONTH FC]]&"-"&DetailTracker[[#This Row],[CUSTOMER SHORTEN NAME]]&"-"&DetailTracker[[#This Row],[PROJECT NAME (SHORT)]],YEAR(TODAY())&"-"&DetailTracker[[#This Row],[CUSTOMER SHORTEN NAME]]&"-"&DetailTracker[[#This Row],[PROJECT NAME (SHORT)]]))) -> 2026-RH-SNAKE RIVER LODGE BLUEFLAG | I32: =IF(OR($H32="",$B32=""),0,--(COUNTIFS($H$3:$H32,$H32,$B$3:$B32,$B32)=1)) -> 1 | J32: SHIPPED | K32: NEW | L32: 8. Shipment | M32: 46147 | N32: 46125 | P32: US | Q32: WY | V32: 12 | X32: 203436.01 | Y32: 136716 | Z32: 2026/M08 | AA32: =IF(Z32="","",IF(OR(Z32="TBC",Z32="Removed"),Z32,LEFT(Z32,4))) -> 2026 | AB32: 46242 | AC32: 46249 | AD32: 46242 | AE32: 46263 | AF32: =IF(AD32="","",IF(ISNUMBER(AD32),IF(AND(AD32>='2026 Calendar'!$C$4,AD32<='2026 Calendar'!$E$107),LOOKUP(AD32,'2026 Calendar'!$C$4:$C$107,'2026 Calendar'!$A$4:$A$107),YEAR(AD32-WEEKDAY(AD32,2)+4)&"/W"&TEXT(WEEKNUM(AD32,21),"00")),IF(IFERROR(ISNUMBER(SEARCH("/W",AD32)),FALSE),IF(IFERROR(ISNUMBER(SEARCH("-",AD32)),FALSE),LEFT(AD32,SEARCH("-",AD32)-1),AD32),AD32))) -> 2026/W32 | AG32: =IF(AE32="","",IF(ISNUMBER(AE32),IF(AND(AE32>='2026 Calendar'!$C$4,AE32<='2026 Calendar'!$E$107),LOOKUP(AE32,'2026 Calendar'!$C$4:$C$107,'2026 Calendar'!$A$4:$A$107),YEAR(AE32-WEEKDAY(AE32,2)+4)&"/W"&TEXT(WEEKNUM(AE32,21),"00")),IF(IFERROR(ISNUMBER(SEARCH("/W",AE32)),FALSE),IF(IFERROR(ISNUMBER(SEARCH("-",AE32)),FALSE),MID(AE32,SEARCH("-",AE32)+1,100),AE32),AE32))) -> 2026/W35 | AH32: Approved | AJ32: 46163 | AK32: Approved | AM32: 45813 | AN32: Approved | AQ32: Approved | AT32: N/A | AW32: Approved | AZ32: COM Received | BC32: =IF(J32="","",IF(OR(J32="OB",J32="NOR",J32="FC",J32="PIPELINE"),"Active","Complete")) -> Complete | BD32: Yes | BE32: =IF(UPPER(TRIM(J32))="SHIPPED","READY",_xlfn.LET(_xlpm.stage,IF(B32="","",B32&": "),_xlpm.ip,_xlfn.TEXTJOIN(", ",TRUE,IF(LOWER(AH32)="in progress","Drawing",""),IF(LOWER(AK32)="in progress","Veneer/Wood",""),IF(LOWER(AN32)="in progress","Marble",""),IF(LOWER(AQ32)="in progress","Metal",""),IF(LOWER(AT32)="in progress","Mirror",""),IF(LOWER(AW32)="in progress","Electrical",""),IF(LOWER(AZ32)="in progress","Fabric","")),_xlpm.pa,_xlfn.TEXTJOIN(", ",TRUE,IF(LOWER(AH32)="pending approval","Drawing",""),IF(LOWER(AK32)="pending approval","Veneer/Wood",""),IF(LOWER(AN32)="pending approval","Marble",""),IF(LOWER(AQ32)="pending approval","Metal",""),IF(LOWER(AT32)="pending approval","Mirror",""),IF(LOWER(AW32)="pending approval","Electrical",""),IF(LOWER(AZ32)="pending approval","Fabric","")),_xlpm.ns,_xlfn.TEXTJOIN(", ",TRUE,IF(LOWER(AH32)="not started","Drawing",""),IF(LOWER(AK32)="not started","Veneer/Wood",""),IF(LOWER(AN32)="not started","Marble",""),IF(LOWER(AQ32)="not started","Metal",""),IF(LOWER(AT32)="not started","Mirror",""),IF(LOWER(AW32)="not started","Electrical",""),IF(LOWER(AZ32)="not started","Fabric","")),_xlpm.fab,IF(OR(LOWER(AZ32)="com",LOWER(AZ32)="com pending",LOWER(AZ32)="com received"),"Fabric is "&LOWER(AZ32),""),_xlpm.parts,_xlfn.TEXTJOIN("; ",TRUE,IF(_xlpm.ip<>"","In progress: "&_xlpm.ip,""),IF(_xlpm.pa<>"","Pending approval: "&_xlpm.pa,""),IF(_xlpm.ns<>"","Not started: "&_xlpm.ns,""),_xlpm.fab),_xlpm.deadline,MIN(IF(AND(AH32<>"",LOWER(AH32)<>"approved",LOWER(AH32)<>"n/a",ISNUMBER(AI32)),AI32,1E+99),IF(AND(AK32<>"",LOWER(AK32)<>"approved",LOWER(AK32)<>"n/a",ISNUMBER(AL32)),AL32,1E+99),IF(AND(AN32<>"",LOWER(AN32)<>"approved",LOWER(AN32)<>"n/a",ISNUMBER(AO32)),AO32,1E+99),IF(AND(AQ32<>"",LOWER(AQ32)<>"approved",LOWER(AQ32)<>"n/a",ISNUMBER(AR32)),AR32,1E+99),IF(AND(AT32<>"",LOWER(AT32)<>"approved",LOWER(AT32)<>"n/a",ISNUMBER(AU32)),AU32,1E+99),IF(AND(AW32<>"",LOWER(AW32)<>"approved",LOWER(AW32)<>"n/a",ISNUMBER(AX32)),AX32,1E+99),IF(AND(AZ32<>"",LOWER(AZ32)<>"approved",LOWER(AZ32)<>"n/a",ISNUMBER(BA32)),BA32,1E+99)),_xlpm.sw,IF(AG32="","",IFERROR("SW"&MID(AG32,FIND("/W",AG32)+2,99),"SW "&AG32)),_xlpm.stage&IF(_xlpm.parts="","All development items approved/closed",_xlpm.parts)&IF(AND(_xlpm.parts<>"",_xlpm.deadline<1E+99),"; need approval by "&TEXT(_xlpm.deadline,"d-mmm-yy"),"")&IF(_xlpm.sw<>""," for "&_xlpm.sw,""))) -> READY
A33: =IFERROR(VLOOKUP(E33,'Customer '!$A$4:$D$23,3,FALSE),"") -> RH | B33: NPI | C33: DUY | D33: Madison Lay | E33: RESTORATION HARDWARE_HS | F33: =IFERROR(VLOOKUP(E33,'Customer '!$A$4:$D$28,2,FALSE),"") -> RH | G33: SNAKE RIVER LODGE BLUEFLAG | H33: =IF(OR(DetailTracker[[#This Row],[PROJECT NAME (SHORT)]]="",DetailTracker[[#This Row],[CUSTOMER SHORTEN NAME]]=""),"",IF(ISNUMBER(DetailTracker[[#This Row],[BOQ DATE]]),YEAR(DetailTracker[[#This Row],[BOQ DATE]])&"-"&DetailTracker[[#This Row],[CUSTOMER SHORTEN NAME]]&"-"&DetailTracker[[#This Row],[PROJECT NAME (SHORT)]],IF(OR(DetailTracker[[#This Row],[SHIP MONTH FC]]="TBC",DetailTracker[[#This Row],[SHIP MONTH FC]]="Removed"),DetailTracker[[#This Row],[SHIP MONTH FC]]&"-"&DetailTracker[[#This Row],[CUSTOMER SHORTEN NAME]]&"-"&DetailTracker[[#This Row],[PROJECT NAME (SHORT)]],YEAR(TODAY())&"-"&DetailTracker[[#This Row],[CUSTOMER SHORTEN NAME]]&"-"&DetailTracker[[#This Row],[PROJECT NAME (SHORT)]]))) -> 2026-RH-SNAKE RIVER LODGE BLUEFLAG | I33: =IF(OR($H33="",$B33=""),0,--(COUNTIFS($H$3:$H33,$H33,$B$3:$B33,$B33)=1)) -> 0 | J33: SHIPPED | K33: NEW | L33: 8. Shipment | M33: 46147 | N33: 46125 | P33: US | Q33: WY | R33: 0 | S33: 0 | V33: 12 | X33: 203436.01 | Y33: 66720.49 | Z33: 2026/M08 | AA33: =IF(Z33="","",IF(OR(Z33="TBC",Z33="Removed"),Z33,LEFT(Z33,4))) -> 2026 | AB33: 46242 | AC33: 46249 | AD33: 46242 | AE33: 46263 | AF33: =IF(AD33="","",IF(ISNUMBER(AD33),IF(AND(AD33>='2026 Calendar'!$C$4,AD33<='2026 Calendar'!$E$107),LOOKUP(AD33,'2026 Calendar'!$C$4:$C$107,'2026 Calendar'!$A$4:$A$107),YEAR(AD33-WEEKDAY(AD33,2)+4)&"/W"&TEXT(WEEKNUM(AD33,21),"00")),IF(IFERROR(ISNUMBER(SEARCH("/W",AD33)),FALSE),IF(IFERROR(ISNUMBER(SEARCH("-",AD33)),FALSE),LEFT(AD33,SEARCH("-",AD33)-1),AD33),AD33))) -> 2026/W32 | AG33: =IF(AE33="","",IF(ISNUMBER(AE33),IF(AND(AE33>='2026 Calendar'!$C$4,AE33<='2026 Calendar'!$E$107),LOOKUP(AE33,'2026 Calendar'!$C$4:$C$107,'2026 Calendar'!$A$4:$A$107),YEAR(AE33-WEEKDAY(AE33,2)+4)&"/W"&TEXT(WEEKNUM(AE33,21),"00")),IF(IFERROR(ISNUMBER(SEARCH("/W",AE33)),FALSE),IF(IFERROR(ISNUMBER(SEARCH("-",AE33)),FALSE),MID(AE33,SEARCH("-",AE33)+1,100),AE33),AE33))) -> 2026/W35 | AH33: Approved | AJ33: 46163 | AK33: Approved | AM33: 45813 | AN33: Approved | AQ33: Approved | AT33: N/A | AW33: Approved | AZ33: COM Received | BC33: =IF(J33="","",IF(OR(J33="OB",J33="NOR",J33="FC",J33="PIPELINE"),"Active","Complete")) -> Complete | BD33: Yes | BE33: =IF(UPPER(TRIM(J33))="SHIPPED","READY",_xlfn.LET(_xlpm.stage,IF(B33="","",B33&": "),_xlpm.ip,_xlfn.TEXTJOIN(", ",TRUE,IF(LOWER(AH33)="in progress","Drawing",""),IF(LOWER(AK33)="in progress","Veneer/Wood",""),IF(LOWER(AN33)="in progress","Marble",""),IF(LOWER(AQ33)="in progress","Metal",""),IF(LOWER(AT33)="in progress","Mirror",""),IF(LOWER(AW33)="in progress","Electrical",""),IF(LOWER(AZ33)="in progress","Fabric","")),_xlpm.pa,_xlfn.TEXTJOIN(", ",TRUE,IF(LOWER(AH33)="pending approval","Drawing",""),IF(LOWER(AK33)="pending approval","Veneer/Wood",""),IF(LOWER(AN33)="pending approval","Marble",""),IF(LOWER(AQ33)="pending approval","Metal",""),IF(LOWER(AT33)="pending approval","Mirror",""),IF(LOWER(AW33)="pending approval","Electrical",""),IF(LOWER(AZ33)="pending approval","Fabric","")),_xlpm.ns,_xlfn.TEXTJOIN(", ",TRUE,IF(LOWER(AH33)="not started","Drawing",""),IF(LOWER(AK33)="not started","Veneer/Wood",""),IF(LOWER(AN33)="not started","Marble",""),IF(LOWER(AQ33)="not started","Metal",""),IF(LOWER(AT33)="not started","Mirror",""),IF(LOWER(AW33)="not started","Electrical",""),IF(LOWER(AZ33)="not started","Fabric","")),_xlpm.fab,IF(OR(LOWER(AZ33)="com",LOWER(AZ33)="com pending",LOWER(AZ33)="com received"),"Fabric is "&LOWER(AZ33),""),_xlpm.parts,_xlfn.TEXTJOIN("; ",TRUE,IF(_xlpm.ip<>"","In progress: "&_xlpm.ip,""),IF(_xlpm.pa<>"","Pending approval: "&_xlpm.pa,""),IF(_xlpm.ns<>"","Not started: "&_xlpm.ns,""),_xlpm.fab),_xlpm.deadline,MIN(IF(AND(AH33<>"",LOWER(AH33)<>"approved",LOWER(AH33)<>"n/a",ISNUMBER(AI33)),AI33,1E+99),IF(AND(AK33<>"",LOWER(AK33)<>"approved",LOWER(AK33)<>"n/a",ISNUMBER(AL33)),AL33,1E+99),IF(AND(AN33<>"",LOWER(AN33)<>"approved",LOWER(AN33)<>"n/a",ISNUMBER(AO33)),AO33,1E+99),IF(AND(AQ33<>"",LOWER(AQ33)<>"approved",LOWER(AQ33)<>"n/a",ISNUMBER(AR33)),AR33,1E+99),IF(AND(AT33<>"",LOWER(AT33)<>"approved",LOWER(AT33)<>"n/a",ISNUMBER(AU33)),AU33,1E+99),IF(AND(AW33<>"",LOWER(AW33)<>"approved",LOWER(AW33)<>"n/a",ISNUMBER(AX33)),AX33,1E+99),IF(AND(AZ33<>"",LOWER(AZ33)<>"approved",LOWER(AZ33)<>"n/a",ISNUMBER(BA33)),BA33,1E+99)),_xlpm.sw,IF(AG33="","",IFERROR("SW"&MID(AG33,FIND("/W",AG33)+2,99),"SW "&AG33)),_xlpm.stage&IF(_xlpm.parts="","All development items approved/closed",_xlpm.parts)&IF(AND(_xlpm.parts<>"",_xlpm.deadline<1E+99),"; need approval by "&TEXT(_xlpm.deadline,"d-mmm-yy"),"")&IF(_xlpm.sw<>""," for "&_xlpm.sw,""))) -> READY
A34: =IFERROR(VLOOKUP(E34,'Customer '!$A$4:$D$23,3,FALSE),"") -> RH | B34: NPI | C34: BIEN | D34: Sue Bilstad | E34: RESTORATION HARDWARE_HS | F34: =IFERROR(VLOOKUP(E34,'Customer '!$A$4:$D$28,2,FALSE),"") -> RH | G34: TRUMP LAS VEGAS PENTHOUSES | H34: =IF(OR(DetailTracker[[#This Row],[PROJECT NAME (SHORT)]]="",DetailTracker[[#This Row],[CUSTOMER SHORTEN NAME]]=""),"",IF(ISNUMBER(DetailTracker[[#This Row],[BOQ DATE]]),YEAR(DetailTracker[[#This Row],[BOQ DATE]])&"-"&DetailTracker[[#This Row],[CUSTOMER SHORTEN NAME]]&"-"&DetailTracker[[#This Row],[PROJECT NAME (SHORT)]],IF(OR(DetailTracker[[#This Row],[SHIP MONTH FC]]="TBC",DetailTracker[[#This Row],[SHIP MONTH FC]]="Removed"),DetailTracker[[#This Row],[SHIP MONTH FC]]&"-"&DetailTracker[[#This Row],[CUSTOMER SHORTEN NAME]]&"-"&DetailTracker[[#This Row],[PROJECT NAME (SHORT)]],YEAR(TODAY())&"-"&DetailTracker[[#This Row],[CUSTOMER SHORTEN NAME]]&"-"&DetailTracker[[#This Row],[PROJECT NAME (SHORT)]]))) -> 2025-RH-TRUMP LAS VEGAS PENTHOUSES | I34: =IF(OR($H34="",$B34=""),0,--(COUNTIFS($H$3:$H34,$H34,$B$3:$B34,$B34)=1)) -> 1 | J34: OB | K34: NEW | L34: 7. Mass Production | M34: 45955 | N34: 46254 | P34: US | Q34: NV | R34: 0 | S34: 0 | V34: 36 | W34: 925 | X34: 535191 | Y34: 350863 | Z34: 2027/M01 | AA34: =IF(Z34="","",IF(OR(Z34="TBC",Z34="Removed"),Z34,LEFT(Z34,4))) -> 2027 | AB34: - | AD34: 46395 | AE34: 46416 | AF34: =IF(AD34="","",IF(ISNUMBER(AD34),IF(AND(AD34>='2026 Calendar'!$C$4,AD34<='2026 Calendar'!$E$107),LOOKUP(AD34,'2026 Calendar'!$C$4:$C$107,'2026 Calendar'!$A$4:$A$107),YEAR(AD34-WEEKDAY(AD34,2)+4)&"/W"&TEXT(WEEKNUM(AD34,21),"00")),IF(IFERROR(ISNUMBER(SEARCH("/W",AD34)),FALSE),IF(IFERROR(ISNUMBER(SEARCH("-",AD34)),FALSE),LEFT(AD34,SEARCH("-",AD34)-1),AD34),AD34))) -> 2027/W02 | AG34: =IF(AE34="","",IF(ISNUMBER(AE34),IF(AND(AE34>='2026 Calendar'!$C$4,AE34<='2026 Calendar'!$E$107),LOOKUP(AE34,'2026 Calendar'!$C$4:$C$107,'2026 Calendar'!$A$4:$A$107),YEAR(AE34-WEEKDAY(AE34,2)+4)&"/W"&TEXT(WEEKNUM(AE34,21),"00")),IF(IFERROR(ISNUMBER(SEARCH("/W",AE34)),FALSE),IF(IFERROR(ISNUMBER(SEARCH("-",AE34)),FALSE),MID(AE34,SEARCH("-",AE34)+1,100),AE34),AE34))) -> 2027/W05 | AH34: Approved | AK34: Approved | AN34: Approved | AQ34: Approved | AT34: Approved | AW34: Approved | BC34: =IF(J34="","",IF(OR(J34="OB",J34="NOR",J34="FC",J34="PIPELINE"),"Active","Complete")) -> Active | BD34: Yes | BE34: =IF(UPPER(TRIM(J34))="SHIPPED","READY",_xlfn.LET(_xlpm.stage,IF(B34="","",B34&": "),_xlpm.ip,_xlfn.TEXTJOIN(", ",TRUE,IF(LOWER(AH34)="in progress","Drawing",""),IF(LOWER(AK34)="in progress","Veneer/Wood",""),IF(LOWER(AN34)="in progress","Marble",""),IF(LOWER(AQ34)="in progress","Metal",""),IF(LOWER(AT34)="in progress","Mirror",""),IF(LOWER(AW34)="in progress","Electrical",""),IF(LOWER(AZ34)="in progress","Fabric","")),_xlpm.pa,_xlfn.TEXTJOIN(", ",TRUE,IF(LOWER(AH34)="pending approval","Drawing",""),IF(LOWER(AK34)="pending approval","Veneer/Wood",""),IF(LOWER(AN34)="pending approval","Marble",""),IF(LOWER(AQ34)="pending approval","Metal",""),IF(LOWER(AT34)="pending approval","Mirror",""),IF(LOWER(AW34)="pending approval","Electrical",""),IF(LOWER(AZ34)="pending approval","Fabric","")),_xlpm.ns,_xlfn.TEXTJOIN(", ",TRUE,IF(LOWER(AH34)="not started","Drawing",""),IF(LOWER(AK34)="not started","Veneer/Wood",""),IF(LOWER(AN34)="not started","Marble",""),IF(LOWER(AQ34)="not started","Metal",""),IF(LOWER(AT34)="not started","Mirror",""),IF(LOWER(AW34)="not started","Electrical",""),IF(LOWER(AZ34)="not started","Fabric","")),_xlpm.fab,IF(OR(LOWER(AZ34)="com",LOWER(AZ34)="com pending",LOWER(AZ34)="com received"),"Fabric is "&LOWER(AZ34),""),_xlpm.parts,_xlfn.TEXTJOIN("; ",TRUE,IF(_xlpm.ip<>"","In progress: "&_xlpm.ip,""),IF(_xlpm.pa<>"","Pending approval: "&_xlpm.pa,""),IF(_xlpm.ns<>"","Not started: "&_xlpm.ns,""),_xlpm.fab),_xlpm.deadline,MIN(IF(AND(AH34<>"",LOWER(AH34)<>"approved",LOWER(AH34)<>"n/a",ISNUMBER(AI34)),AI34,1E+99),IF(AND(AK34<>"",LOWER(AK34)<>"approved",LOWER(AK34)<>"n/a",ISNUMBER(AL34)),AL34,1E+99),IF(AND(AN34<>"",LOWER(AN34)<>"approved",LOWER(AN34)<>"n/a",ISNUMBER(AO34)),AO34,1E+99),IF(AND(AQ34<>"",LOWER(AQ34)<>"approved",LOWER(AQ34)<>"n/a",ISNUMBER(AR34)),AR34,1E+99),IF(AND(AT34<>"",LOWER(AT34)<>"approved",LOWER(AT34)<>"n/a",ISNUMBER(AU34)),AU34,1E+99),IF(AND(AW34<>"",LOWER(AW34)<>"approved",LOWER(AW34)<>"n/a",ISNUMBER(AX34)),AX34,1E+99),IF(AND(AZ34<>"",LOWER(AZ34)<>"approved",LOWER(AZ34)<>"n/a",ISNUMBER(BA34)),BA34,1E+99)),_xlpm.sw,IF(AG34="","",IFERROR("SW"&MID(AG34,FIND("/W",AG34)+2,99),"SW "&AG34)),_xlpm.stage&IF(_xlpm.parts="","All development items approved/closed",_xlpm.parts)&IF(AND(_xlpm.parts<>"",_xlpm.deadline<1E+99),"; need approval by "&TEXT(_xlpm.deadline,"d-mmm-yy"),"")&IF(_xlpm.sw<>""," for "&_xlpm.sw,""))) -> NPI: All development items approved/closed for SW05
A35: =IFERROR(VLOOKUP(E35,'Customer '!$A$4:$D$23,3,FALSE),"") -> RH | B35: NPI | C35: BIEN | D35: Sue Bilstad | E35: RESTORATION HARDWARE_HS | F35: =IFERROR(VLOOKUP(E35,'Customer '!$A$4:$D$28,2,FALSE),"") -> RH | G35: TRUMP LAS VEGAS PENTHOUSES | H35: =IF(OR(DetailTracker[[#This Row],[PROJECT NAME (SHORT)]]="",DetailTracker[[#This Row],[CUSTOMER SHORTEN NAME]]=""),"",IF(ISNUMBER(DetailTracker[[#This Row],[BOQ DATE]]),YEAR(DetailTracker[[#This Row],[BOQ DATE]])&"-"&DetailTracker[[#This Row],[CUSTOMER SHORTEN NAME]]&"-"&DetailTracker[[#This Row],[PROJECT NAME (SHORT)]],IF(OR(DetailTracker[[#This Row],[SHIP MONTH FC]]="TBC",DetailTracker[[#This Row],[SHIP MONTH FC]]="Removed"),DetailTracker[[#This Row],[SHIP MONTH FC]]&"-"&DetailTracker[[#This Row],[CUSTOMER SHORTEN NAME]]&"-"&DetailTracker[[#This Row],[PROJECT NAME (SHORT)]],YEAR(TODAY())&"-"&DetailTracker[[#This Row],[CUSTOMER SHORTEN NAME]]&"-"&DetailTracker[[#This Row],[PROJECT NAME (SHORT)]]))) -> 2025-RH-TRUMP LAS VEGAS PENTHOUSES | I35: =IF(OR($H35="",$B35=""),0,--(COUNTIFS($H$3:$H35,$H35,$B$3:$B35,$B35)=1)) -> 0 | J35: OB | K35: NEW | L35: 7. Mass Production | M35: 45955 | N35: 46254 | P35: US | Q35: NV | R35: 0 | S35: 0 | V35: 36 | W35: 925 | X35: 535191 | Y35: 184328 | Z35: 2027/M01 | AA35: =IF(Z35="","",IF(OR(Z35="TBC",Z35="Removed"),Z35,LEFT(Z35,4))) -> 2027 | AB35: - | AD35: 46395 | AE35: 46416 | AF35: =IF(AD35="","",IF(ISNUMBER(AD35),IF(AND(AD35>='2026 Calendar'!$C$4,AD35<='2026 Calendar'!$E$107),LOOKUP(AD35,'2026 Calendar'!$C$4:$C$107,'2026 Calendar'!$A$4:$A$107),YEAR(AD35-WEEKDAY(AD35,2)+4)&"/W"&TEXT(WEEKNUM(AD35,21),"00")),IF(IFERROR(ISNUMBER(SEARCH("/W",AD35)),FALSE),IF(IFERROR(ISNUMBER(SEARCH("-",AD35)),FALSE),LEFT(AD35,SEARCH("-",AD35)-1),AD35),AD35))) -> 2027/W02 | AG35: =IF(AE35="","",IF(ISNUMBER(AE35),IF(AND(AE35>='2026 Calendar'!$C$4,AE35<='2026 Calendar'!$E$107),LOOKUP(AE35,'2026 Calendar'!$C$4:$C$107,'2026 Calendar'!$A$4:$A$107),YEAR(AE35-WEEKDAY(AE35,2)+4)&"/W"&TEXT(WEEKNUM(AE35,21),"00")),IF(IFERROR(ISNUMBER(SEARCH("/W",AE35)),FALSE),IF(IFERROR(ISNUMBER(SEARCH("-",AE35)),FALSE),MID(AE35,SEARCH("-",AE35)+1,100),AE35),AE35))) -> 2027/W05 | AH35: Approved | AK35: Approved | AN35: Approved | AQ35: Approved | AT35: Approved | AW35: Approved | BC35: =IF(J35="","",IF(OR(J35="OB",J35="NOR",J35="FC",J35="PIPELINE"),"Active","Complete")) -> Active | BD35: Yes | BE35: =IF(UPPER(TRIM(J35))="SHIPPED","READY",_xlfn.LET(_xlpm.stage,IF(B35="","",B35&": "),_xlpm.ip,_xlfn.TEXTJOIN(", ",TRUE,IF(LOWER(AH35)="in progress","Drawing",""),IF(LOWER(AK35)="in progress","Veneer/Wood",""),IF(LOWER(AN35)="in progress","Marble",""),IF(LOWER(AQ35)="in progress","Metal",""),IF(LOWER(AT35)="in progress","Mirror",""),IF(LOWER(AW35)="in progress","Electrical",""),IF(LOWER(AZ35)="in progress","Fabric","")),_xlpm.pa,_xlfn.TEXTJOIN(", ",TRUE,IF(LOWER(AH35)="pending approval","Drawing",""),IF(LOWER(AK35)="pending approval","Veneer/Wood",""),IF(LOWER(AN35)="pending approval","Marble",""),IF(LOWER(AQ35)="pending approval","Metal",""),IF(LOWER(AT35)="pending approval","Mirror",""),IF(LOWER(AW35)="pending approval","Electrical",""),IF(LOWER(AZ35)="pending approval","Fabric","")),_xlpm.ns,_xlfn.TEXTJOIN(", ",TRUE,IF(LOWER(AH35)="not started","Drawing",""),IF(LOWER(AK35)="not started","Veneer/Wood",""),IF(LOWER(AN35)="not started","Marble",""),IF(LOWER(AQ35)="not started","Metal",""),IF(LOWER(AT35)="not started","Mirror",""),IF(LOWER(AW35)="not started","Electrical",""),IF(LOWER(AZ35)="not started","Fabric","")),_xlpm.fab,IF(OR(LOWER(AZ35)="com",LOWER(AZ35)="com pending",LOWER(AZ35)="com received"),"Fabric is "&LOWER(AZ35),""),_xlpm.parts,_xlfn.TEXTJOIN("; ",TRUE,IF(_xlpm.ip<>"","In progress: "&_xlpm.ip,""),IF(_xlpm.pa<>"","Pending approval: "&_xlpm.pa,""),IF(_xlpm.ns<>"","Not started: "&_xlpm.ns,""),_xlpm.fab),_xlpm.deadline,MIN(IF(AND(AH35<>"",LOWER(AH35)<>"approved",LOWER(AH35)<>"n/a",ISNUMBER(AI35)),AI35,1E+99),IF(AND(AK35<>"",LOWER(AK35)<>"approved",LOWER(AK35)<>"n/a",ISNUMBER(AL35)),AL35,1E+99),IF(AND(AN35<>"",LOWER(AN35)<>"approved",LOWER(AN35)<>"n/a",ISNUMBER(AO35)),AO35,1E+99),IF(AND(AQ35<>"",LOWER(AQ35)<>"approved",LOWER(AQ35)<>"n/a",ISNUMBER(AR35)),AR35,1E+99),IF(AND(AT35<>"",LOWER(AT35)<>"approved",LOWER(AT35)<>"n/a",ISNUMBER(AU35)),AU35,1E+99),IF(AND(AW35<>"",LOWER(AW35)<>"approved",LOWER(AW35)<>"n/a",ISNUMBER(AX35)),AX35,1E+99),IF(AND(AZ35<>"",LOWER(AZ35)<>"approved",LOWER(AZ35)<>"n/a",ISNUMBER(BA35)),BA35,1E+99)),_xlpm.sw,IF(AG35="","",IFERROR("SW"&MID(AG35,FIND("/W",AG35)+2,99),"SW "&AG35)),_xlpm.stage&IF(_xlpm.parts="","All development items approved/closed",_xlpm.parts)&IF(AND(_xlpm.parts<>"",_xlpm.deadline<1E+99),"; need approval by "&TEXT(_xlpm.deadline,"d-mmm-yy"),"")&IF(_xlpm.sw<>""," for "&_xlpm.sw,""))) -> NPI: All development items approved/closed for SW05
A36: =IFERROR(VLOOKUP(E36,'Customer '!$A$4:$D$23,3,FALSE),"") -> RH | B36: NPI | C36: DUY | D36: Madison Lay | E36: RESTORATION HARDWARE_HS | F36: =IFERROR(VLOOKUP(E36,'Customer '!$A$4:$D$28,2,FALSE),"") -> RH | G36: RITZ DOVE MOUNTAIN | H36: =IF(OR(DetailTracker[[#This Row],[PROJECT NAME (SHORT)]]="",DetailTracker[[#This Row],[CUSTOMER SHORTEN NAME]]=""),"",IF(ISNUMBER(DetailTracker[[#This Row],[BOQ DATE]]),YEAR(DetailTracker[[#This Row],[BOQ DATE]])&"-"&DetailTracker[[#This Row],[CUSTOMER SHORTEN NAME]]&"-"&DetailTracker[[#This Row],[PROJECT NAME (SHORT)]],IF(OR(DetailTracker[[#This Row],[SHIP MONTH FC]]="TBC",DetailTracker[[#This Row],[SHIP MONTH FC]]="Removed"),DetailTracker[[#This Row],[SHIP MONTH FC]]&"-"&DetailTracker[[#This Row],[CUSTOMER SHORTEN NAME]]&"-"&DetailTracker[[#This Row],[PROJECT NAME (SHORT)]],YEAR(TODAY())&"-"&DetailTracker[[#This Row],[CUSTOMER SHORTEN NAME]]&"-"&DetailTracker[[#This Row],[PROJECT NAME (SHORT)]]))) -> 2026-RH-RITZ DOVE MOUNTAIN | I36: =IF(OR($H36="",$B36=""),0,--(COUNTIFS($H$3:$H36,$H36,$B$3:$B36,$B36)=1)) -> 1 | J36: FC | K36: NEW | L36: 4. Prototype Build | M36: 46084 | P36: US | Q36: AZ | R36: 0 | S36: 0 | V36: 14 | X36: 228581 | Y36: 228581 | Z36: 2027/M04 | AA36: =IF(Z36="","",IF(OR(Z36="TBC",Z36="Removed"),Z36,LEFT(Z36,4))) -> 2027 | AB36: - | AD36: 46122 | AE36: 46136 | AF36: =IF(AD36="","",IF(ISNUMBER(AD36),IF(AND(AD36>='2026 Calendar'!$C$4,AD36<='2026 Calendar'!$E$107),LOOKUP(AD36,'2026 Calendar'!$C$4:$C$107,'2026 Calendar'!$A$4:$A$107),YEAR(AD36-WEEKDAY(AD36,2)+4)&"/W"&TEXT(WEEKNUM(AD36,21),"00")),IF(IFERROR(ISNUMBER(SEARCH("/W",AD36)),FALSE),IF(IFERROR(ISNUMBER(SEARCH("-",AD36)),FALSE),LEFT(AD36,SEARCH("-",AD36)-1),AD36),AD36))) -> 2026/W15 | AG36: =IF(AE36="","",IF(ISNUMBER(AE36),IF(AND(AE36>='2026 Calendar'!$C$4,AE36<='2026 Calendar'!$E$107),LOOKUP(AE36,'2026 Calendar'!$C$4:$C$107,'2026 Calendar'!$A$4:$A$107),YEAR(AE36-WEEKDAY(AE36,2)+4)&"/W"&TEXT(WEEKNUM(AE36,21),"00")),IF(IFERROR(ISNUMBER(SEARCH("/W",AE36)),FALSE),IF(IFERROR(ISNUMBER(SEARCH("-",AE36)),FALSE),MID(AE36,SEARCH("-",AE36)+1,100),AE36),AE36))) -> 2026/W17 | AH36: Pending Approval | AK36: Pending Approval | AN36: N/A | AQ36: Pending Approval | AT36: N/A | AW36: N/A | AZ36: COM | BC36: =IF(J36="","",IF(OR(J36="OB",J36="NOR",J36="FC",J36="PIPELINE"),"Active","Complete")) -> Active | BD36: Yes | BE36: =IF(UPPER(TRIM(J36))="SHIPPED","READY",_xlfn.LET(_xlpm.stage,IF(B36="","",B36&": "),_xlpm.ip,_xlfn.TEXTJOIN(", ",TRUE,IF(LOWER(AH36)="in progress","Drawing",""),IF(LOWER(AK36)="in progress","Veneer/Wood",""),IF(LOWER(AN36)="in progress","Marble",""),IF(LOWER(AQ36)="in progress","Metal",""),IF(LOWER(AT36)="in progress","Mirror",""),IF(LOWER(AW36)="in progress","Electrical",""),IF(LOWER(AZ36)="in progress","Fabric","")),_xlpm.pa,_xlfn.TEXTJOIN(", ",TRUE,IF(LOWER(AH36)="pending approval","Drawing",""),IF(LOWER(AK36)="pending approval","Veneer/Wood",""),IF(LOWER(AN36)="pending approval","Marble",""),IF(LOWER(AQ36)="pending approval","Metal",""),IF(LOWER(AT36)="pending approval","Mirror",""),IF(LOWER(AW36)="pending approval","Electrical",""),IF(LOWER(AZ36)="pending approval","Fabric","")),_xlpm.ns,_xlfn.TEXTJOIN(", ",TRUE,IF(LOWER(AH36)="not started","Drawing",""),IF(LOWER(AK36)="not started","Veneer/Wood",""),IF(LOWER(AN36)="not started","Marble",""),IF(LOWER(AQ36)="not started","Metal",""),IF(LOWER(AT36)="not started","Mirror",""),IF(LOWER(AW36)="not started","Electrical",""),IF(LOWER(AZ36)="not started","Fabric","")),_xlpm.fab,IF(OR(LOWER(AZ36)="com",LOWER(AZ36)="com pending",LOWER(AZ36)="com received"),"Fabric is "&LOWER(AZ36),""),_xlpm.parts,_xlfn.TEXTJOIN("; ",TRUE,IF(_xlpm.ip<>"","In progress: "&_xlpm.ip,""),IF(_xlpm.pa<>"","Pending approval: "&_xlpm.pa,""),IF(_xlpm.ns<>"","Not started: "&_xlpm.ns,""),_xlpm.fab),_xlpm.deadline,MIN(IF(AND(AH36<>"",LOWER(AH36)<>"approved",LOWER(AH36)<>"n/a",ISNUMBER(AI36)),AI36,1E+99),IF(AND(AK36<>"",LOWER(AK36)<>"approved",LOWER(AK36)<>"n/a",ISNUMBER(AL36)),AL36,1E+99),IF(AND(AN36<>"",LOWER(AN36)<>"approved",LOWER(AN36)<>"n/a",ISNUMBER(AO36)),AO36,1E+99),IF(AND(AQ36<>"",LOWER(AQ36)<>"approved",LOWER(AQ36)<>"n/a",ISNUMBER(AR36)),AR36,1E+99),IF(AND(AT36<>"",LOWER(AT36)<>"approved",LOWER(AT36)<>"n/a",ISNUMBER(AU36)),AU36,1E+99),IF(AND(AW36<>"",LOWER(AW36)<>"approved",LOWER(AW36)<>"n/a",ISNUMBER(AX36)),AX36,1E+99),IF(AND(AZ36<>"",LOWER(AZ36)<>"approved",LOWER(AZ36)<>"n/a",ISNUMBER(BA36)),BA36,1E+99)),_xlpm.sw,IF(AG36="","",IFERROR("SW"&MID(AG36,FIND("/W",AG36)+2,99),"SW "&AG36)),_xlpm.stage&IF(_xlpm.parts="","All development items approved/closed",_xlpm.parts)&IF(AND(_xlpm.parts<>"",_xlpm.deadline<1E+99),"; need approval by "&TEXT(_xlpm.deadline,"d-mmm-yy"),"")&IF(_xlpm.sw<>""," for "&_xlpm.sw,""))) -> NPI: Pending approval: Drawing, Veneer/Wood, Metal; Fabric is com for SW17
A37: =IFERROR(VLOOKUP(E37,'Customer '!$A$4:$D$23,3,FALSE),"") -> RH | B37: NPI | C37: TU ANH | D37: Sue Bilstad | E37: RESTORATION HARDWARE_HS | F37: =IFERROR(VLOOKUP(E37,'Customer '!$A$4:$D$28,2,FALSE),"") -> RH | G37: MAYBOURNE_ONE WALL STREET NY | H37: =IF(OR(DetailTracker[[#This Row],[PROJECT NAME (SHORT)]]="",DetailTracker[[#This Row],[CUSTOMER SHORTEN NAME]]=""),"",IF(ISNUMBER(DetailTracker[[#This Row],[BOQ DATE]]),YEAR(DetailTracker[[#This Row],[BOQ DATE]])&"-"&DetailTracker[[#This Row],[CUSTOMER SHORTEN NAME]]&"-"&DetailTracker[[#This Row],[PROJECT NAME (SHORT)]],IF(OR(DetailTracker[[#This Row],[SHIP MONTH FC]]="TBC",DetailTracker[[#This Row],[SHIP MONTH FC]]="Removed"),DetailTracker[[#This Row],[SHIP MONTH FC]]&"-"&DetailTracker[[#This Row],[CUSTOMER SHORTEN NAME]]&"-"&DetailTracker[[#This Row],[PROJECT NAME (SHORT)]],YEAR(TODAY())&"-"&DetailTracker[[#This Row],[CUSTOMER SHORTEN NAME]]&"-"&DetailTracker[[#This Row],[PROJECT NAME (SHORT)]]))) -> 2026-RH-MAYBOURNE_ONE WALL STREET NY | I37: =IF(OR($H37="",$B37=""),0,--(COUNTIFS($H$3:$H37,$H37,$B$3:$B37,$B37)=1)) -> 1 | J37: SHIPPED | K37: REO | L37: 8. Shipment | N37: 46079 | P37: US | Q37: NY | V37: 1 | X37: 1672 | Y37: 1672 | Z37: 2026/M04 | AA37: =IF(Z37="","",IF(OR(Z37="TBC",Z37="Removed"),Z37,LEFT(Z37,4))) -> 2026 | AB37: 46113 | AC37: 46120 | AD37: 46116 | AE37: 46116 | AF37: =IF(AD37="","",IF(ISNUMBER(AD37),IF(AND(AD37>='2026 Calendar'!$C$4,AD37<='2026 Calendar'!$E$107),LOOKUP(AD37,'2026 Calendar'!$C$4:$C$107,'2026 Calendar'!$A$4:$A$107),YEAR(AD37-WEEKDAY(AD37,2)+4)&"/W"&TEXT(WEEKNUM(AD37,21),"00")),IF(IFERROR(ISNUMBER(SEARCH("/W",AD37)),FALSE),IF(IFERROR(ISNUMBER(SEARCH("-",AD37)),FALSE),LEFT(AD37,SEARCH("-",AD37)-1),AD37),AD37))) -> 2026/W14 | AG37: =IF(AE37="","",IF(ISNUMBER(AE37),IF(AND(AE37>='2026 Calendar'!$C$4,AE37<='2026 Calendar'!$E$107),LOOKUP(AE37,'2026 Calendar'!$C$4:$C$107,'2026 Calendar'!$A$4:$A$107),YEAR(AE37-WEEKDAY(AE37,2)+4)&"/W"&TEXT(WEEKNUM(AE37,21),"00")),IF(IFERROR(ISNUMBER(SEARCH("/W",AE37)),FALSE),IF(IFERROR(ISNUMBER(SEARCH("-",AE37)),FALSE),MID(AE37,SEARCH("-",AE37)+1,100),AE37),AE37))) -> 2026/W14 | AH37: Approved | AJ37: 46104 | AK37: Approved | AM37: 46104 | AN37: N/A | AQ37: N/A | AT37: N/A | AW37: N/A | AZ37: COM | BB37: 46090 | BC37: =IF(J37="","",IF(OR(J37="OB",J37="NOR",J37="FC",J37="PIPELINE"),"Active","Complete")) -> Complete | BD37: Yes | BE37: =IF(UPPER(TRIM(J37))="SHIPPED","READY",_xlfn.LET(_xlpm.stage,IF(B37="","",B37&": "),_xlpm.ip,_xlfn.TEXTJOIN(", ",TRUE,IF(LOWER(AH37)="in progress","Drawing",""),IF(LOWER(AK37)="in progress","Veneer/Wood",""),IF(LOWER(AN37)="in progress","Marble",""),IF(LOWER(AQ37)="in progress","Metal",""),IF(LOWER(AT37)="in progress","Mirror",""),IF(LOWER(AW37)="in progress","Electrical",""),IF(LOWER(AZ37)="in progress","Fabric","")),_xlpm.pa,_xlfn.TEXTJOIN(", ",TRUE,IF(LOWER(AH37)="pending approval","Drawing",""),IF(LOWER(AK37)="pending approval","Veneer/Wood",""),IF(LOWER(AN37)="pending approval","Marble",""),IF(LOWER(AQ37)="pending approval","Metal",""),IF(LOWER(AT37)="pending approval","Mirror",""),IF(LOWER(AW37)="pending approval","Electrical",""),IF(LOWER(AZ37)="pending approval","Fabric","")),_xlpm.ns,_xlfn.TEXTJOIN(", ",TRUE,IF(LOWER(AH37)="not started","Drawing",""),IF(LOWER(AK37)="not started","Veneer/Wood",""),IF(LOWER(AN37)="not started","Marble",""),IF(LOWER(AQ37)="not started","Metal",""),IF(LOWER(AT37)="not started","Mirror",""),IF(LOWER(AW37)="not started","Electrical",""),IF(LOWER(AZ37)="not started","Fabric","")),_xlpm.fab,IF(OR(LOWER(AZ37)="com",LOWER(AZ37)="com pending",LOWER(AZ37)="com received"),"Fabric is "&LOWER(AZ37),""),_xlpm.parts,_xlfn.TEXTJOIN("; ",TRUE,IF(_xlpm.ip<>"","In progress: "&_xlpm.ip,""),IF(_xlpm.pa<>"","Pending approval: "&_xlpm.pa,""),IF(_xlpm.ns<>"","Not started: "&_xlpm.ns,""),_xlpm.fab),_xlpm.deadline,MIN(IF(AND(AH37<>"",LOWER(AH37)<>"approved",LOWER(AH37)<>"n/a",ISNUMBER(AI37)),AI37,1E+99),IF(AND(AK37<>"",LOWER(AK37)<>"approved",LOWER(AK37)<>"n/a",ISNUMBER(AL37)),AL37,1E+99),IF(AND(AN37<>"",LOWER(AN37)<>"approved",LOWER(AN37)<>"n/a",ISNUMBER(AO37)),AO37,1E+99),IF(AND(AQ37<>"",LOWER(AQ37)<>"approved",LOWER(AQ37)<>"n/a",ISNUMBER(AR37)),AR37,1E+99),IF(AND(AT37<>"",LOWER(AT37)<>"approved",LOWER(AT37)<>"n/a",ISNUMBER(AU37)),AU37,1E+99),IF(AND(AW37<>"",LOWER(AW37)<>"approved",LOWER(AW37)<>"n/a",ISNUMBER(AX37)),AX37,1E+99),IF(AND(AZ37<>"",LOWER(AZ37)<>"approved",LOWER(AZ37)<>"n/a",ISNUMBER(BA37)),BA37,1E+99)),_xlpm.sw,IF(AG37="","",IFERROR("SW"&MID(AG37,FIND("/W",AG37)+2,99),"SW "&AG37)),_xlpm.stage&IF(_xlpm.parts="","All development items approved/closed",_xlpm.parts)&IF(AND(_xlpm.parts<>"",_xlpm.deadline<1E+99),"; need approval by "&TEXT(_xlpm.deadline,"d-mmm-yy"),"")&IF(_xlpm.sw<>""," for "&_xlpm.sw,""))) -> READY
